Workbook

Sheet 📋 Portada
B3: HUELLA SOCIAL — COOPERATIVAS DE AHORRO Y CRÉDITO
B6: Cuenta Satélite del Sector Cooperativo Financiero Chileno
B10: CONTENIDO DEL ARCHIVO
B12: 📊 1. Agregados DAES
B13: Totales anuales 2014–2024 del segmento no supervisado por CMF. Incluye P1, B1g, D1, B2g, Rem, PIB y Aporte (%).
B15: 🏦 2. Agregados CMF
B16: Totales anuales 2014–2025 de las 7 CAC supervisadas por CMF. Incluye P1, B1g, Rem, activos, depósitos y colocaciones.
B18: 📅 3. CMF Feb-2026
B19: Resultados acumulados enero–febrero 2026 de las 7 CAC CMF. Datos parciales (2 meses); incluye B1g anualizado y aporte referencial.
B21: 📁 4. Panel DAES
B22: Una fila por cooperativa×año. Todas las entidades DAES con sus variables de cuenta de producción y balance.
B24: 📁 5. Panel CMF
... B39: • Coopeuch aparece en DAES hasta 2016 (supervisada por SBIF). Desde 2017 figura en el panel CMF.

Sheet 📊 Agregados DAES
A1: CUENTA DE PRODUCCIÓN Y GENERACIÓN DEL INGRESO — SEGMENTO DAES (CAC no supervisadas por CMF)
A2: Cifras en millones de pesos corrientes (MM$). P1 = Total Ingresos Operación | P2 = α×P1 (α=0,3776) | B1g = P1−P2 | PIB: Banco Central, ref. 2018
A3: Año | B3: N | C3: P1 (MM$) | D3: P2 (MM$) | E3: B1g (MM$) | F3: D1 (MM$) | G3: B2g (MM$) | H3: Rem (MM$) | I3: D1/B1g | J3: PIB Chile (MM$) | K3: Aporte (%)
A4: 2014 | B4: =+COUNTIFS('📁 Panel DAES'!$D$3:$D$135,'📊 Agregados DAES'!A4,'📁 Panel DAES'!$E$3:$E$135,"<>",'📁 Panel DAES'!$H$3:$H$135,"<>") -> 2 | C4: =+SUMIF('📁 Panel DAES'!$D$3:$D$135,'📊 Agregados DAES'!A4,'📁 Panel DAES'!$E$3:$E$135) -> 247.89282 | D4: =0.3776*C4 -> 93.604329 | E4: =+C4-D4 -> 154.28849 | F4: =+SUMIF('📁 Panel DAES'!$D$3:$D$135,'📊 Agregados DAES'!A4,'📁 Panel DAES'!$H$3:$H$135) -> 78.223597 | G4: =+E4-F4 -> 76.064894 | H4: =+SUMIF('📁 Panel DAES'!$D$3:$D$135,'📊 Agregados DAES'!A4,'📁 Panel DAES'!$J$3:$J$135) -> -6.852924 | I4: =+F4/E4 -> 0.50699567 | J4: 144706000 | K4: =+(E4/J4)*100 -> 0.00010662204
A5: 2015 | B5: =+COUNTIFS('📁 Panel DAES'!$D$3:$D$135,'📊 Agregados DAES'!A5,'📁 Panel DAES'!$E$3:$E$135,"<>",'📁 Panel DAES'!$H$3:$H$135,"<>") -> 7 | C5: =+SUMIF('📁 Panel DAES'!$D$3:$D$135,'📊 Agregados DAES'!A5,'📁 Panel DAES'!$E$3:$E$135) -> 5426.0644 | D5: =0.3776*C5 -> 2048.8819 | E5: =+C5-D5 -> 3377.1825 | F5: =+SUMIF('📁 Panel DAES'!$D$3:$D$135,'📊 Agregados DAES'!A5,'📁 Panel DAES'!$H$3:$H$135) -> 1762.8158 | G5: =+E5-F5 -> 1614.3667 | H5: =+SUMIF('📁 Panel DAES'!$D$3:$D$135,'📊 Agregados DAES'!A5,'📁 Panel DAES'!$J$3:$J$135) -> 740.60321 | I5: =+F5/E5 -> 0.52197825 | J5: 158623000 | K5: =+(E5/J5)*100 -> 0.0021290623
A6: 2016 | B6: =+COUNTIFS('📁 Panel DAES'!$D$3:$D$135,'📊 Agregados DAES'!A6,'📁 Panel DAES'!$E$3:$E$135,"<>",'📁 Panel DAES'!$H$3:$H$135,"<>") -> 9 | C6: =+SUMIF('📁 Panel DAES'!$D$3:$D$135,'📊 Agregados DAES'!A6,'📁 Panel DAES'!$E$3:$E$135) -> 6083.2353 | D6: =0.3776*C6 -> 2297.0296 | E6: =+C6-D6 -> 3786.2056 | F6: =+SUMIF('📁 Panel DAES'!$D$3:$D$135,'📊 Agregados DAES'!A6,'📁 Panel DAES'!$H$3:$H$135) -> 2000.2757 | G6: =+E6-F6 -> 1785.9299 | H6: =+SUMIF('📁 Panel DAES'!$D$3:$D$135,'📊 Agregados DAES'!A6,'📁 Panel DAES'!$J$3:$J$135) -> 350.45645 | I6: =+F6/E6 -> 0.52830614 | J6: 168765000 | K6: =+(E6/J6)*100 -> 0.002243478
A7: 2017 | B7: =+COUNTIFS('📁 Panel DAES'!$D$3:$D$135,'📊 Agregados DAES'!A7,'📁 Panel DAES'!$E$3:$E$135,"<>",'📁 Panel DAES'!$H$3:$H$135,"<>") -> 12 | C7: =+SUMIF('📁 Panel DAES'!$D$3:$D$135,'📊 Agregados DAES'!A7,'📁 Panel DAES'!$E$3:$E$135) -> 6224.2481 | D7: =0.3776*C7 -> 2350.2761 | E7: =+C7-D7 -> 3873.972 | F7: =+SUMIF('📁 Panel DAES'!$D$3:$D$135,'📊 Agregados DAES'!A7,'📁 Panel DAES'!$H$3:$H$135) -> 2622.2251 | G7: =+E7-F7 -> 1251.7469 | H7: =+SUMIF('📁 Panel DAES'!$D$3:$D$135,'📊 Agregados DAES'!A7,'📁 Panel DAES'!$J$3:$J$135) -> 260.27679 | I7: =+F7/E7 -> 0.67688283 | J7: 179315000 | K7: =+(E7/J7)*100 -> 0.0021604283
A8: 2018 | B8: =+COUNTIFS('📁 Panel DAES'!$D$3:$D$135,'📊 Agregados DAES'!A8,'📁 Panel DAES'!$E$3:$E$135,"<>",'📁 Panel DAES'!$H$3:$H$135,"<>") -> 14 | C8: =+SUMIF('📁 Panel DAES'!$D$3:$D$135,'📊 Agregados DAES'!A8,'📁 Panel DAES'!$E$3:$E$135) -> 8977.2604 | D8: =0.3776*C8 -> 3389.8135 | E8: =+C8-D8 -> 5587.4469 | F8: =+SUMIF('📁 Panel DAES'!$D$3:$D$135,'📊 Agregados DAES'!A8,'📁 Panel DAES'!$H$3:$H$135) -> 4385.2416 | G8: =+E8-F8 -> 1202.2052 | H8: =+SUMIF('📁 Panel DAES'!$D$3:$D$135,'📊 Agregados DAES'!A8,'📁 Panel DAES'!$J$3:$J$135) -> 628.3566 | I8: =+F8/E8 -> 0.78483818 | J8: 189435000 | K8: =+(E8/J8)*100 -> 0.0029495325
A9: 2019 | B9: =+COUNTIFS('📁 Panel DAES'!$D$3:$D$135,'📊 Agregados DAES'!A9,'📁 Panel DAES'!$E$3:$E$135,"<>",'📁 Panel DAES'!$H$3:$H$135,"<>") -> 6 | C9: =+SUMIF('📁 Panel DAES'!$D$3:$D$135,'📊 Agregados DAES'!A9,'📁 Panel DAES'!$E$3:$E$135) -> 4667.2517 | D9: =0.3776*C9 -> 1762.3542 | E9: =+C9-D9 -> 2904.8974 | F9: =+SUMIF('📁 Panel DAES'!$D$3:$D$135,'📊 Agregados DAES'!A9,'📁 Panel DAES'!$H$3:$H$135) -> 1854.9876 | G9: =+E9-F9 -> 1049.9099 | H9: =+SUMIF('📁 Panel DAES'!$D$3:$D$135,'📊 Agregados DAES'!A9,'📁 Panel DAES'!$J$3:$J$135) -> 503.36676 | I9: =+F9/E9 -> 0.63857248 | J9: 195548000 | K9: =+(E9/J9)*100 -> 0.0014855163
A10: 2020 | B10: =+COUNTIFS('📁 Panel DAES'!$D$3:$D$135,'📊 Agregados DAES'!A10,'📁 Panel DAES'!$E$3:$E$135,"<>",'📁 Panel DAES'!$H$3:$H$135,"<>") -> 10 | C10: =+SUMIF('📁 Panel DAES'!$D$3:$D$135,'📊 Agregados DAES'!A10,'📁 Panel DAES'!$E$3:$E$135) -> 6164.6371 | D10: =0.3776*C10 -> 2327.767 | E10: =+C10-D10 -> 3836.8702 | F10: =+SUMIF('📁 Panel DAES'!$D$3:$D$135,'📊 Agregados DAES'!A10,'📁 Panel DAES'!$H$3:$H$135) -> 2419.9054 | G10: =+E10-F10 -> 1416.9648 | H10: =+SUMIF('📁 Panel DAES'!$D$3:$D$135,'📊 Agregados DAES'!A10,'📁 Panel DAES'!$J$3:$J$135) -> 155.04948 | I10: =+F10/E10 -> 0.63069776 | J10: 201307000 | K10: =+(E10/J10)*100 -> 0.0019059795
A11: 2021 | B11: =+COUNTIFS('📁 Panel DAES'!$D$3:$D$135,'📊 Agregados DAES'!A11,'📁 Panel DAES'!$E$3:$E$135,"<>",'📁 Panel DAES'!$H$3:$H$135,"<>") -> 10 | C11: =+SUMIF('📁 Panel DAES'!$D$3:$D$135,'📊 Agregados DAES'!A11,'📁 Panel DAES'!$E$3:$E$135) -> 6010.5201 | D11: =0.3776*C11 -> 2269.5724 | E11: =+C11-D11 -> 3740.9477 | F11: =+SUMIF('📁 Panel DAES'!$D$3:$D$135,'📊 Agregados DAES'!A11,'📁 Panel DAES'!$H$3:$H$135) -> 2030.0232 | G11: =+E11-F11 -> 1710.9245 | H11: =+SUMIF('📁 Panel DAES'!$D$3:$D$135,'📊 Agregados DAES'!A11,'📁 Panel DAES'!$J$3:$J$135) -> 29.251521 | I11: =+F11/E11 -> 0.54264944 | J11: 239556000 | K11: =+(E11/J11)*100 -> 0.0015616172
A12: 2022 | B12: =+COUNTIFS('📁 Panel DAES'!$D$3:$D$135,'📊 Agregados DAES'!A12,'📁 Panel DAES'!$E$3:$E$135,"<>",'📁 Panel DAES'!$H$3:$H$135,"<>") -> 19 | C12: =+SUMIF('📁 Panel DAES'!$D$3:$D$135,'📊 Agregados DAES'!A12,'📁 Panel DAES'!$E$3:$E$135) -> 22171.988 | D12: =0.3776*C12 -> 8372.1428 | E12: =+C12-D12 -> 13799.846 | F12: =+SUMIF('📁 Panel DAES'!$D$3:$D$135,'📊 Agregados DAES'!A12,'📁 Panel DAES'!$H$3:$H$135) -> 6967.3719 | G12: =+E12-F12 -> 6832.4737 | H12: =+SUMIF('📁 Panel DAES'!$D$3:$D$135,'📊 Agregados DAES'!A12,'📁 Panel DAES'!$J$3:$J$135) -> -2572.8427 | I12: =+F12/E12 -> 0.50488767 | J12: 262954000 | K12: =+(E12/J12)*100 -> 0.0052480075
A13: 2023 | B13: =+COUNTIFS('📁 Panel DAES'!$D$3:$D$135,'📊 Agregados DAES'!A13,'📁 Panel DAES'!$E$3:$E$135,"<>",'📁 Panel DAES'!$H$3:$H$135,"<>") -> 22 | C13: =+SUMIF('📁 Panel DAES'!$D$3:$D$135,'📊 Agregados DAES'!A13,'📁 Panel DAES'!$E$3:$E$135) -> 47404.627 | D13: =0.3776*C13 -> 17899.987 | E13: =+C13-D13 -> 29504.64 | F13: =+SUMIF('📁 Panel DAES'!$D$3:$D$135,'📊 Agregados DAES'!A13,'📁 Panel DAES'!$H$3:$H$135) -> 12582.384 | G13: =+E13-F13 -> 16922.255 | H13: =+SUMIF('📁 Panel DAES'!$D$3:$D$135,'📊 Agregados DAES'!A13,'📁 Panel DAES'!$J$3:$J$135) -> 2542.8579 | I13: =+F13/E13 -> 0.42645443 | J13: 282097000 | K13: =+(E13/J13)*100 -> 0.010459041
A14: 2024 | B14: =+COUNTIFS('📁 Panel DAES'!$D$3:$D$135,'📊 Agregados DAES'!A14,'📁 Panel DAES'!$E$3:$E$135,"<>",'📁 Panel DAES'!$H$3:$H$135,"<>") -> 11 | C14: =+SUMIF('📁 Panel DAES'!$D$3:$D$135,'📊 Agregados DAES'!A14,'📁 Panel DAES'!$E$3:$E$135) -> 18135.86 | D14: =0.3776*C14 -> 6848.1009 | E14: =+C14-D14 -> 11287.759 | F14: =+SUMIF('📁 Panel DAES'!$D$3:$D$135,'📊 Agregados DAES'!A14,'📁 Panel DAES'!$H$3:$H$135) -> 8269.4476 | G14: =+E14-F14 -> 3018.3119 | H14: =+SUMIF('📁 Panel DAES'!$D$3:$D$135,'📊 Agregados DAES'!A14,'📁 Panel DAES'!$J$3:$J$135) -> 2246.7217 | I14: =+F14/E14 -> 0.7326031 | J14: 310681000 | K14: =+(E14/J14)*100 -> 0.0036332313
A15: TOTAL PERÍODO | C15: =+SUM(C4:C14) -> 131513.59 | D15: =+SUM(D4:D14) -> 49659.53 | E15: =+SUM(E4:E14) -> 81854.055 | F15: =+SUM(F4:F14) -> 44972.902 | G15: =+SUM(G4:G14) -> 36881.154 | H15: =+SUM(H4:H14) -> 4877.2447 | I15: — | J15: — | K15: —
A17: CUENTA FINANCIERA — BALANCE GENERAL
A18: F2 = Depósitos captados (vista + plazo) | F4 = Colocaciones netas (total − provisiones)
A19: Año | B19: N | C19: Activos (MM$) | D19: Patrimonio (MM$) | E19: F2 Depósitos (MM$) | F19: F4 Colocaciones (MM$) | G19: F4/Activos | H19: F2/Activos
A20: 2014 | B20: =+COUNTIFS('📁 Panel DAES'!$D$3:$D$135,'📊 Agregados DAES'!A20,'📁 Panel DAES'!$K$3:$K$135,"<>",'📁 Panel DAES'!$L$3:$L$135,"<>",'📁 Panel DAES'!$M$3:$M$135,"<>",'📁 Panel DAES'!$N$3:$N$135,"<>") -> 2 | C20: =+SUMIF('📁 Panel DAES'!$D$3:$D$135,'📊 Agregados DAES'!A20,'📁 Panel DAES'!$K$3:$K$135) -> 1226.5979 | D20: =+SUMIF('📁 Panel DAES'!$D$3:$D$135,'📊 Agregados DAES'!A20,'📁 Panel DAES'!$L$3:$L$135) -> 1132.5209 | E20: =+SUMIF('📁 Panel DAES'!$D$3:$D$135,'📊 Agregados DAES'!A20,'📁 Panel DAES'!$M$3:$M$135) -> 72.623722 | F20: =+SUMIF('📁 Panel DAES'!$D$3:$D$135,'📊 Agregados DAES'!A20,'📁 Panel DAES'!$N$3:$N$135) -> 847.35116 | G20: =+F20/C20 -> 0.69081411 | H20: =+E20/C20 -> 0.059207439
A21: 2015 | B21: =+COUNTIFS('📁 Panel DAES'!$D$3:$D$135,'📊 Agregados DAES'!A21,'📁 Panel DAES'!$K$3:$K$135,"<>",'📁 Panel DAES'!$L$3:$L$135,"<>",'📁 Panel DAES'!$M$3:$M$135,"<>",'📁 Panel DAES'!$N$3:$N$135,"<>") -> 7 | C21: =+SUMIF('📁 Panel DAES'!$D$3:$D$135,'📊 Agregados DAES'!A21,'📁 Panel DAES'!$K$3:$K$135) -> 32039.86 | D21: =+SUMIF('📁 Panel DAES'!$D$3:$D$135,'📊 Agregados DAES'!A21,'📁 Panel DAES'!$L$3:$L$135) -> 26762.114 | E21: =+SUMIF('📁 Panel DAES'!$D$3:$D$135,'📊 Agregados DAES'!A21,'📁 Panel DAES'!$M$3:$M$135) -> 4996.6645 | F21: =+SUMIF('📁 Panel DAES'!$D$3:$D$135,'📊 Agregados DAES'!A21,'📁 Panel DAES'!$N$3:$N$135) -> 23988.19 | G21: =+F21/C21 -> 0.74869834 | H21: =+E21/C21 -> 0.15595151
A22: 2016 | B22: =+COUNTIFS('📁 Panel DAES'!$D$3:$D$135,'📊 Agregados DAES'!A22,'📁 Panel DAES'!$K$3:$K$135,"<>",'📁 Panel DAES'!$L$3:$L$135,"<>",'📁 Panel DAES'!$M$3:$M$135,"<>",'📁 Panel DAES'!$N$3:$N$135,"<>") -> 7 | C22: =+SUMIF('📁 Panel DAES'!$D$3:$D$135,'📊 Agregados DAES'!A22,'📁 Panel DAES'!$K$3:$K$135) -> 10349.981 | D22: =+SUMIF('📁 Panel DAES'!$D$3:$D$135,'📊 Agregados DAES'!A22,'📁 Panel DAES'!$L$3:$L$135) -> 4680.602 | E22: =+SUMIF('📁 Panel DAES'!$D$3:$D$135,'📊 Agregados DAES'!A22,'📁 Panel DAES'!$M$3:$M$135) -> 5060.6694 | F22: =+SUMIF('📁 Panel DAES'!$D$3:$D$135,'📊 Agregados DAES'!A22,'📁 Panel DAES'!$N$3:$N$135) -> 7276.6831 | G22: =+F22/C22 -> 0.70306245 | H22: =+E22/C22 -> 0.48895446
A23: 2017 | B23: =+COUNTIFS('📁 Panel DAES'!$D$3:$D$135,'📊 Agregados DAES'!A23,'📁 Panel DAES'!$K$3:$K$135,"<>",'📁 Panel DAES'!$L$3:$L$135,"<>",'📁 Panel DAES'!$M$3:$M$135,"<>",'📁 Panel DAES'!$N$3:$N$135,"<>") -> 7 | C23: =+SUMIF('📁 Panel DAES'!$D$3:$D$135,'📊 Agregados DAES'!A23,'📁 Panel DAES'!$K$3:$K$135) -> 32452.608 | D23: =+SUMIF('📁 Panel DAES'!$D$3:$D$135,'📊 Agregados DAES'!A23,'📁 Panel DAES'!$L$3:$L$135) -> 17330.129 | E23: =+SUMIF('📁 Panel DAES'!$D$3:$D$135,'📊 Agregados DAES'!A23,'📁 Panel DAES'!$M$3:$M$135) -> 8733.3372 | F23: =+SUMIF('📁 Panel DAES'!$D$3:$D$135,'📊 Agregados DAES'!A23,'📁 Panel DAES'!$N$3:$N$135) -> 15278.378 | G23: =+F23/C23 -> 0.47079045 | H23: =+E23/C23 -> 0.26911049
A24: 2018 | B24: =+COUNTIFS('📁 Panel DAES'!$D$3:$D$135,'📊 Agregados DAES'!A24,'📁 Panel DAES'!$K$3:$K$135,"<>",'📁 Panel DAES'!$L$3:$L$135,"<>",'📁 Panel DAES'!$M$3:$M$135,"<>",'📁 Panel DAES'!$N$3:$N$135,"<>") -> 10 | C24: =+SUMIF('📁 Panel DAES'!$D$3:$D$135,'📊 Agregados DAES'!A24,'📁 Panel DAES'!$K$3:$K$135) -> 51825.685 | D24: =+SUMIF('📁 Panel DAES'!$D$3:$D$135,'📊 Agregados DAES'!A24,'📁 Panel DAES'!$L$3:$L$135) -> 19382.343 | E24: =+SUMIF('📁 Panel DAES'!$D$3:$D$135,'📊 Agregados DAES'!A24,'📁 Panel DAES'!$M$3:$M$135) -> 12619.894 | F24: =+SUMIF('📁 Panel DAES'!$D$3:$D$135,'📊 Agregados DAES'!A24,'📁 Panel DAES'!$N$3:$N$135) -> 29732.94 | G24: =+F24/C24 -> 0.57371051 | H24: =+E24/C24 -> 0.24350655
A25: 2019 | B25: =+COUNTIFS('📁 Panel DAES'!$D$3:$D$135,'📊 Agregados DAES'!A25,'📁 Panel DAES'!$K$3:$K$135,"<>",'📁 Panel DAES'!$L$3:$L$135,"<>",'📁 Panel DAES'!$M$3:$M$135,"<>",'📁 Panel DAES'!$N$3:$N$135,"<>") -> 6 | C25: =+SUMIF('📁 Panel DAES'!$D$3:$D$135,'📊 Agregados DAES'!A25,'📁 Panel DAES'!$K$3:$K$135) -> 33039.67 | D25: =+SUMIF('📁 Panel DAES'!$D$3:$D$135,'📊 Agregados DAES'!A25,'📁 Panel DAES'!$L$3:$L$135) -> 14893.597 | E25: =+SUMIF('📁 Panel DAES'!$D$3:$D$135,'📊 Agregados DAES'!A25,'📁 Panel DAES'!$M$3:$M$135) -> 15387.076 | F25: =+SUMIF('📁 Panel DAES'!$D$3:$D$135,'📊 Agregados DAES'!A25,'📁 Panel DAES'!$N$3:$N$135) -> 23618.052 | G25: =+F25/C25 -> 0.71483921 | H25: =+E25/C25 -> 0.46571517
A26: 2020 | B26: =+COUNTIFS('📁 Panel DAES'!$D$3:$D$135,'📊 Agregados DAES'!A26,'📁 Panel DAES'!$K$3:$K$135,"<>",'📁 Panel DAES'!$L$3:$L$135,"<>",'📁 Panel DAES'!$M$3:$M$135,"<>",'📁 Panel DAES'!$N$3:$N$135,"<>") -> 9 | C26: =+SUMIF('📁 Panel DAES'!$D$3:$D$135,'📊 Agregados DAES'!A26,'📁 Panel DAES'!$K$3:$K$135) -> 47098.723 | D26: =+SUMIF('📁 Panel DAES'!$D$3:$D$135,'📊 Agregados DAES'!A26,'📁 Panel DAES'!$L$3:$L$135) -> 23639.688 | E26: =+SUMIF('📁 Panel DAES'!$D$3:$D$135,'📊 Agregados DAES'!A26,'📁 Panel DAES'!$M$3:$M$135) -> 21306.056 | F26: =+SUMIF('📁 Panel DAES'!$D$3:$D$135,'📊 Agregados DAES'!A26,'📁 Panel DAES'!$N$3:$N$135) -> 27462.093 | G26: =+F26/C26 -> 0.58307509 | H26: =+E26/C26 -> 0.45237014
A27: 2021 | B27: =+COUNTIFS('📁 Panel DAES'!$D$3:$D$135,'📊 Agregados DAES'!A27,'📁 Panel DAES'!$K$3:$K$135,"<>",'📁 Panel DAES'!$L$3:$L$135,"<>",'📁 Panel DAES'!$M$3:$M$135,"<>",'📁 Panel DAES'!$N$3:$N$135,"<>") -> 8 | C27: =+SUMIF('📁 Panel DAES'!$D$3:$D$135,'📊 Agregados DAES'!A27,'📁 Panel DAES'!$K$3:$K$135) -> 46796.015 | D27: =+SUMIF('📁 Panel DAES'!$D$3:$D$135,'📊 Agregados DAES'!A27,'📁 Panel DAES'!$L$3:$L$135) -> 25103.643 | E27: =+SUMIF('📁 Panel DAES'!$D$3:$D$135,'📊 Agregados DAES'!A27,'📁 Panel DAES'!$M$3:$M$135) -> 19693.459 | F27: =+SUMIF('📁 Panel DAES'!$D$3:$D$135,'📊 Agregados DAES'!A27,'📁 Panel DAES'!$N$3:$N$135) -> 27701.892 | G27: =+F27/C27 -> 0.59197116 | H27: =+E27/C27 -> 0.42083624
A28: 2022 | B28: =+COUNTIFS('📁 Panel DAES'!$D$3:$D$135,'📊 Agregados DAES'!A28,'📁 Panel DAES'!$K$3:$K$135,"<>",'📁 Panel DAES'!$L$3:$L$135,"<>",'📁 Panel DAES'!$M$3:$M$135,"<>",'📁 Panel DAES'!$N$3:$N$135,"<>") -> 15 | C28: =+SUMIF('📁 Panel DAES'!$D$3:$D$135,'📊 Agregados DAES'!A28,'📁 Panel DAES'!$K$3:$K$135) -> 84588.66 | D28: =+SUMIF('📁 Panel DAES'!$D$3:$D$135,'📊 Agregados DAES'!A28,'📁 Panel DAES'!$L$3:$L$135) -> 46311.421 | E28: =+SUMIF('📁 Panel DAES'!$D$3:$D$135,'📊 Agregados DAES'!A28,'📁 Panel DAES'!$M$3:$M$135) -> 34145.43 | F28: =+SUMIF('📁 Panel DAES'!$D$3:$D$135,'📊 Agregados DAES'!A28,'📁 Panel DAES'!$N$3:$N$135) -> 56563.259 | G28: =+F28/C28 -> 0.66868608 | H28: =+E28/C28 -> 0.40366439
A29: 2023 | B29: =+COUNTIFS('📁 Panel DAES'!$D$3:$D$135,'📊 Agregados DAES'!A29,'📁 Panel DAES'!$K$3:$K$135,"<>",'📁 Panel DAES'!$L$3:$L$135,"<>",'📁 Panel DAES'!$M$3:$M$135,"<>",'📁 Panel DAES'!$N$3:$N$135,"<>") -> 18 | C29: =+SUMIF('📁 Panel DAES'!$D$3:$D$135,'📊 Agregados DAES'!A29,'📁 Panel DAES'!$K$3:$K$135) -> 165905.33 | D29: =+SUMIF('📁 Panel DAES'!$D$3:$D$135,'📊 Agregados DAES'!A29,'📁 Panel DAES'!$L$3:$L$135) -> 71655.962 | E29: =+SUMIF('📁 Panel DAES'!$D$3:$D$135,'📊 Agregados DAES'!A29,'📁 Panel DAES'!$M$3:$M$135) -> 87353.148 | F29: =+SUMIF('📁 Panel DAES'!$D$3:$D$135,'📊 Agregados DAES'!A29,'📁 Panel DAES'!$N$3:$N$135) -> 114808.28 | G29: =+F29/C29 -> 0.69201078 | H29: =+E29/C29 -> 0.52652406
A30: 2024 | B30: =+COUNTIFS('📁 Panel DAES'!$D$3:$D$135,'📊 Agregados DAES'!A30,'📁 Panel DAES'!$K$3:$K$135,"<>",'📁 Panel DAES'!$L$3:$L$135,"<>",'📁 Panel DAES'!$M$3:$M$135,"<>",'📁 Panel DAES'!$N$3:$N$135,"<>") -> 11 | C30: =+SUMIF('📁 Panel DAES'!$D$3:$D$135,'📊 Agregados DAES'!A30,'📁 Panel DAES'!$K$3:$K$135) -> 107922.7 | D30: =+SUMIF('📁 Panel DAES'!$D$3:$D$135,'📊 Agregados DAES'!A30,'📁 Panel DAES'!$L$3:$L$135) -> 44311.961 | E30: =+SUMIF('📁 Panel DAES'!$D$3:$D$135,'📊 Agregados DAES'!A30,'📁 Panel DAES'!$M$3:$M$135) -> 59798.903 | F30: =+SUMIF('📁 Panel DAES'!$D$3:$D$135,'📊 Agregados DAES'!A30,'📁 Panel DAES'!$N$3:$N$135) -> 81305.028 | G30: =+F30/C30 -> 0.75336356 | H30: =+E30/C30 -> 0.55409015
A31: TOTAL PERÍODO | C31: =+SUM(C20:C30) -> 613245.83 | D31: =+SUM(D20:D30) -> 295203.98 | E31: =+SUM(E20:E30) -> 269167.26 | F31: =+SUM(F20:F30) -> 408582.14 | G31: — | H31: —

Sheet 🏦 Agregados CMF
A1: CUENTA DE PRODUCCIÓN Y GENERACIÓN DEL INGRESO — SEGMENTO CMF (7 CAC supervisadas 2013–2025)
A2: P2 = α×P1 (α=0,3776) | B1g = P1−P2 | PIB: Banco Central ref. 2018
A3: Año | B3: N | C3: P1 (MM$) | D3: P2 (MM$) | E3: B1g (MM$) | F3: D1 (MM$) | G3: B2g (MM$) | H3: Rem (MM$) | I3: D1/B1g | J3: PIB Chile (MM$) | K3: Aporte (%)
A4: 2013 | B4: =+COUNTIF('📁 Panel CMF'!$D$3:$D$93,'🏦 Agregados CMF'!A4) -> 7 | C4: =+SUMIF('📁 Panel CMF'!$D$3:$D$93,'🏦 Agregados CMF'!A4,'📁 Panel CMF'!$E$3:$E$93) -> 260475 | D4: =0.3776*C4 -> 98355.36 | E4: =+C4-D4 -> 162119.64 | F4: =+SUMIF('📁 Panel CMF'!$D$3:$D$93,'🏦 Agregados CMF'!A4,'📁 Panel CMF'!$H$3:$H$93) -> 61877.3 | G4: =+E4-F4 -> 100242.34 | H4: =+SUMIF('📁 Panel CMF'!$D$3:$D$93,'🏦 Agregados CMF'!A4,'📁 Panel CMF'!$J$3:$J$93) -> 22868.4 | I4: =+F4/E4 -> 0.38167677 | J4: 136003000 | K4: =+(E4/J4)*100 -> 0.11920299
A5: 2014 | B5: =+COUNTIF('📁 Panel CMF'!$D$3:$D$93,'🏦 Agregados CMF'!A5) -> 7 | C5: =+SUMIF('📁 Panel CMF'!$D$3:$D$93,'🏦 Agregados CMF'!A5,'📁 Panel CMF'!$E$3:$E$93) -> 248405.1 | D5: =0.3776*C5 -> 93797.766 | E5: =+C5-D5 -> 154607.33 | F5: =+SUMIF('📁 Panel CMF'!$D$3:$D$93,'🏦 Agregados CMF'!A5,'📁 Panel CMF'!$H$3:$H$93) -> 58544.8 | G5: =+E5-F5 -> 96062.534 | H5: =+SUMIF('📁 Panel CMF'!$D$3:$D$93,'🏦 Agregados CMF'!A5,'📁 Panel CMF'!$J$3:$J$93) -> 23293.4 | I5: =+F5/E5 -> 0.37866768 | J5: 144706000 | K5: =+(E5/J5)*100 -> 0.10684238
A6: 2015 | B6: =+COUNTIF('📁 Panel CMF'!$D$3:$D$93,'🏦 Agregados CMF'!A6) -> 7 | C6: =+SUMIF('📁 Panel CMF'!$D$3:$D$93,'🏦 Agregados CMF'!A6,'📁 Panel CMF'!$E$3:$E$93) -> 253822 | D6: =0.3776*C6 -> 95843.187 | E6: =+C6-D6 -> 157978.81 | F6: =+SUMIF('📁 Panel CMF'!$D$3:$D$93,'🏦 Agregados CMF'!A6,'📁 Panel CMF'!$H$3:$H$93) -> 63039.1 | G6: =+E6-F6 -> 94939.713 | H6: =+SUMIF('📁 Panel CMF'!$D$3:$D$93,'🏦 Agregados CMF'!A6,'📁 Panel CMF'!$J$3:$J$93) -> 35676.7 | I6: =+F6/E6 -> 0.39903515 | J6: 158623000 | K6: =+(E6/J6)*100 -> 0.099593888
A7: 2016 | B7: =+COUNTIF('📁 Panel CMF'!$D$3:$D$93,'🏦 Agregados CMF'!A7) -> 7 | C7: =+SUMIF('📁 Panel CMF'!$D$3:$D$93,'🏦 Agregados CMF'!A7,'📁 Panel CMF'!$E$3:$E$93) -> 268230.9 | D7: =0.3776*C7 -> 101283.99 | E7: =+C7-D7 -> 166946.91 | F7: =+SUMIF('📁 Panel CMF'!$D$3:$D$93,'🏦 Agregados CMF'!A7,'📁 Panel CMF'!$H$3:$H$93) -> 70127.7 | G7: =+E7-F7 -> 96819.212 | H7: =+SUMIF('📁 Panel CMF'!$D$3:$D$93,'🏦 Agregados CMF'!A7,'📁 Panel CMF'!$J$3:$J$93) -> 47670.3 | I7: =+F7/E7 -> 0.42005988 | J7: 168765000 | K7: =+(E7/J7)*100 -> 0.09892271
A8: 2017 | B8: =+COUNTIF('📁 Panel CMF'!$D$3:$D$93,'🏦 Agregados CMF'!A8) -> 7 | C8: =+SUMIF('📁 Panel CMF'!$D$3:$D$93,'🏦 Agregados CMF'!A8,'📁 Panel CMF'!$E$3:$E$93) -> 242779 | D8: =0.3776*C8 -> 91673.35 | E8: =+C8-D8 -> 151105.65 | F8: =+SUMIF('📁 Panel CMF'!$D$3:$D$93,'🏦 Agregados CMF'!A8,'📁 Panel CMF'!$H$3:$H$93) -> 73823 | G8: =+E8-F8 -> 77282.65 | H8: =+SUMIF('📁 Panel CMF'!$D$3:$D$93,'🏦 Agregados CMF'!A8,'📁 Panel CMF'!$J$3:$J$93) -> 67971 | I8: =+F8/E8 -> 0.48855222 | J8: 179315000 | K8: =+(E8/J8)*100 -> 0.084268271
A9: 2018 | B9: =+COUNTIF('📁 Panel CMF'!$D$3:$D$93,'🏦 Agregados CMF'!A9) -> 7 | C9: =+SUMIF('📁 Panel CMF'!$D$3:$D$93,'🏦 Agregados CMF'!A9,'📁 Panel CMF'!$E$3:$E$93) -> 257678 | D9: =0.3776*C9 -> 97299.213 | E9: =+C9-D9 -> 160378.79 | F9: =+SUMIF('📁 Panel CMF'!$D$3:$D$93,'🏦 Agregados CMF'!A9,'📁 Panel CMF'!$H$3:$H$93) -> 77911 | G9: =+E9-F9 -> 82467.787 | H9: =+SUMIF('📁 Panel CMF'!$D$3:$D$93,'🏦 Agregados CMF'!A9,'📁 Panel CMF'!$J$3:$J$93) -> 75638 | I9: =+F9/E9 -> 0.48579367 | J9: 189435000 | K9: =+(E9/J9)*100 -> 0.084661645
A10: 2019 | B10: =+COUNTIF('📁 Panel CMF'!$D$3:$D$93,'🏦 Agregados CMF'!A10) -> 7 | C10: =+SUMIF('📁 Panel CMF'!$D$3:$D$93,'🏦 Agregados CMF'!A10,'📁 Panel CMF'!$E$3:$E$93) -> 277718 | D10: =0.3776*C10 -> 104866.32 | E10: =+C10-D10 -> 172851.68 | F10: =+SUMIF('📁 Panel CMF'!$D$3:$D$93,'🏦 Agregados CMF'!A10,'📁 Panel CMF'!$H$3:$H$93) -> 83157 | G10: =+E10-F10 -> 89694.683 | H10: =+SUMIF('📁 Panel CMF'!$D$3:$D$93,'🏦 Agregados CMF'!A10,'📁 Panel CMF'!$J$3:$J$93) -> 78686 | I10: =+F10/E10 -> 0.48108875 | J10: 195548000 | K10: =+(E10/J10)*100 -> 0.08839348
A11: 2020 | B11: =+COUNTIF('📁 Panel CMF'!$D$3:$D$93,'🏦 Agregados CMF'!A11) -> 7 | C11: =+SUMIF('📁 Panel CMF'!$D$3:$D$93,'🏦 Agregados CMF'!A11,'📁 Panel CMF'!$E$3:$E$93) -> 269886 | D11: =0.3776*C11 -> 101908.95 | E11: =+C11-D11 -> 167977.05 | F11: =+SUMIF('📁 Panel CMF'!$D$3:$D$93,'🏦 Agregados CMF'!A11,'📁 Panel CMF'!$H$3:$H$93) -> 87279 | G11: =+E11-F11 -> 80698.046 | H11: =+SUMIF('📁 Panel CMF'!$D$3:$D$93,'🏦 Agregados CMF'!A11,'📁 Panel CMF'!$J$3:$J$93) -> 67319 | I11: =+F11/E11 -> 0.51958885 | J11: 201307000 | K11: =+(E11/J11)*100 -> 0.083443222
A12: 2021 | B12: =+COUNTIF('📁 Panel CMF'!$D$3:$D$93,'🏦 Agregados CMF'!A12) -> 7 | C12: =+SUMIF('📁 Panel CMF'!$D$3:$D$93,'🏦 Agregados CMF'!A12,'📁 Panel CMF'!$E$3:$E$93) -> 275612 | D12: =0.3776*C12 -> 104071.09 | E12: =+C12-D12 -> 171540.91 | F12: =+SUMIF('📁 Panel CMF'!$D$3:$D$93,'🏦 Agregados CMF'!A12,'📁 Panel CMF'!$H$3:$H$93) -> 88696 | G12: =+E12-F12 -> 82844.909 | H12: =+SUMIF('📁 Panel CMF'!$D$3:$D$93,'🏦 Agregados CMF'!A12,'📁 Panel CMF'!$J$3:$J$93) -> 99711 | I12: =+F12/E12 -> 0.51705451 | J12: 239556000 | K12: =+(E12/J12)*100 -> 0.071607853
A13: 2022 | B13: =+COUNTIF('📁 Panel CMF'!$D$3:$D$93,'🏦 Agregados CMF'!A13) -> 7 | C13: =+SUMIF('📁 Panel CMF'!$D$3:$D$93,'🏦 Agregados CMF'!A13,'📁 Panel CMF'!$E$3:$E$93) -> 339948 | D13: =0.3776*C13 -> 128364.36 | E13: =+C13-D13 -> 211583.64 | F13: =+SUMIF('📁 Panel CMF'!$D$3:$D$93,'🏦 Agregados CMF'!A13,'📁 Panel CMF'!$H$3:$H$93) -> 91779.8 | G13: =+E13-F13 -> 119803.84 | H13: =+SUMIF('📁 Panel CMF'!$D$3:$D$93,'🏦 Agregados CMF'!A13,'📁 Panel CMF'!$J$3:$J$93) -> 128122 | I13: =+F13/E13 -> 0.43377551 | J13: 262954000 | K13: =+(E13/J13)*100 -> 0.080464125
A14: 2023 | B14: =+COUNTIF('📁 Panel CMF'!$D$3:$D$93,'🏦 Agregados CMF'!A14) -> 7 | C14: =+SUMIF('📁 Panel CMF'!$D$3:$D$93,'🏦 Agregados CMF'!A14,'📁 Panel CMF'!$E$3:$E$93) -> 337614 | D14: =0.3776*C14 -> 127483.05 | E14: =+C14-D14 -> 210130.95 | F14: =+SUMIF('📁 Panel CMF'!$D$3:$D$93,'🏦 Agregados CMF'!A14,'📁 Panel CMF'!$H$3:$H$93) -> 92726.6 | G14: =+E14-F14 -> 117404.35 | H14: =+SUMIF('📁 Panel CMF'!$D$3:$D$93,'🏦 Agregados CMF'!A14,'📁 Panel CMF'!$J$3:$J$93) -> 92033 | I14: =+F14/E14 -> 0.44128006 | J14: 282097000 | K14: =+(E14/J14)*100 -> 0.0744889
A15: 2024 | B15: =+COUNTIF('📁 Panel CMF'!$D$3:$D$93,'🏦 Agregados CMF'!A15) -> 7 | C15: =+SUMIF('📁 Panel CMF'!$D$3:$D$93,'🏦 Agregados CMF'!A15,'📁 Panel CMF'!$E$3:$E$93) -> 404738 | D15: =0.3776*C15 -> 152829.07 | E15: =+C15-D15 -> 251908.93 | F15: =+SUMIF('📁 Panel CMF'!$D$3:$D$93,'🏦 Agregados CMF'!A15,'📁 Panel CMF'!$H$3:$H$93) -> 109310 | G15: =+E15-F15 -> 142598.93 | H15: =+SUMIF('📁 Panel CMF'!$D$3:$D$93,'🏦 Agregados CMF'!A15,'📁 Panel CMF'!$J$3:$J$93) -> 101974 | I15: =+F15/E15 -> 0.43392666 | J15: 310681000 | K15: =+(E15/J15)*100 -> 0.081082825
A16: 2025 | B16: =+COUNTIF('📁 Panel CMF'!$D$3:$D$93,'🏦 Agregados CMF'!A16) -> 7 | C16: =+SUMIF('📁 Panel CMF'!$D$3:$D$93,'🏦 Agregados CMF'!A16,'📁 Panel CMF'!$E$3:$E$93) -> 445885 | D16: =0.3776*C16 -> 168366.18 | E16: =+C16-D16 -> 277518.82 | F16: =+SUMIF('📁 Panel CMF'!$D$3:$D$93,'🏦 Agregados CMF'!A16,'📁 Panel CMF'!$H$3:$H$93) -> 122763.2 | G16: =+E16-F16 -> 154755.62 | H16: =+SUMIF('📁 Panel CMF'!$D$3:$D$93,'🏦 Agregados CMF'!A16,'📁 Panel CMF'!$J$3:$J$93) -> 108265 | I16: =+F16/E16 -> 0.4423599 | J16: 339978000 | K16: =+(E16/J16)*100 -> 0.081628465
A17: TOTAL PERÍODO | C17: =+SUM(C4:C16) -> 3882791 | D17: =+SUM(D4:D16) -> 1466141.9 | E17: =+SUM(E4:E16) -> 2416649.1 | F17: =+SUM(F4:F16) -> 1081034.5 | G17: =+SUM(G4:G16) -> 1335614.6 | H17: =+SUM(H4:H16) -> 949227.8 | I17: — | J17: —
A21: CUENTA FINANCIERA — BALANCE GENERAL
A22: F2 = Depósitos captados (vista + plazo) | F4 = Colocaciones netas (total − provisiones)
A23: Año | B23: N | C23: Activos (MM$) | D23: Patrimonio (MM$) | E23: F2 Depósitos (MM$) | F23: F4 Colocaciones (MM$) | G23: F4/Activos | H23: F2/Activos
A24: 2013 | B24: =+COUNTIF('📁 Panel CMF'!$D$3:$D$93,'🏦 Agregados CMF'!A24) -> 7 | C24: =+SUMIF('📁 Panel CMF'!$D$3:$D$93,'🏦 Agregados CMF'!A24,'📁 Panel CMF'!$M$3:$M$93) -> 1434093.4 | D24: =+SUMIF('📁 Panel CMF'!$D$3:$D$93,'🏦 Agregados CMF'!A24,'📁 Panel CMF'!$N$3:$N$93) -> 439510.7 | E24: =+SUMIF('📁 Panel CMF'!$D$3:$D$93,'🏦 Agregados CMF'!A24,'📁 Panel CMF'!$K$3:$K$93) -> 709177.9 | F24: =+SUMIF('📁 Panel CMF'!$D$3:$D$93,'🏦 Agregados CMF'!A24,'📁 Panel CMF'!$L$3:$L$93) -> 1274441.1 | G24: =+F24/C24 -> 0.88867371 | H24: =+E24/C24 -> 0.49451305
A25: 2014 | B25: =+COUNTIF('📁 Panel CMF'!$D$3:$D$93,'🏦 Agregados CMF'!A25) -> 7 | C25: =+SUMIF('📁 Panel CMF'!$D$3:$D$93,'🏦 Agregados CMF'!A25,'📁 Panel CMF'!$M$3:$M$93) -> 1432048 | D25: =+SUMIF('📁 Panel CMF'!$D$3:$D$93,'🏦 Agregados CMF'!A25,'📁 Panel CMF'!$N$3:$N$93) -> 449722.7 | E25: =+SUMIF('📁 Panel CMF'!$D$3:$D$93,'🏦 Agregados CMF'!A25,'📁 Panel CMF'!$K$3:$K$93) -> 716124.9 | F25: =+SUMIF('📁 Panel CMF'!$D$3:$D$93,'🏦 Agregados CMF'!A25,'📁 Panel CMF'!$L$3:$L$93) -> 1266778.5 | G25: =+F25/C25 -> 0.88459221 | H25: =+E25/C25 -> 0.50007046
A26: 2015 | B26: =+COUNTIF('📁 Panel CMF'!$D$3:$D$93,'🏦 Agregados CMF'!A26) -> 7 | C26: =+SUMIF('📁 Panel CMF'!$D$3:$D$93,'🏦 Agregados CMF'!A26,'📁 Panel CMF'!$M$3:$M$93) -> 1529424.5 | D26: =+SUMIF('📁 Panel CMF'!$D$3:$D$93,'🏦 Agregados CMF'!A26,'📁 Panel CMF'!$N$3:$N$93) -> 491407.2 | E26: =+SUMIF('📁 Panel CMF'!$D$3:$D$93,'🏦 Agregados CMF'!A26,'📁 Panel CMF'!$K$3:$K$93) -> 742253.9 | F26: =+SUMIF('📁 Panel CMF'!$D$3:$D$93,'🏦 Agregados CMF'!A26,'📁 Panel CMF'!$L$3:$L$93) -> 1331001.7 | G26: =+F26/C26 -> 0.8702631 | H26: =+E26/C26 -> 0.48531582
A27: 2016 | B27: =+COUNTIF('📁 Panel CMF'!$D$3:$D$93,'🏦 Agregados CMF'!A27) -> 7 | C27: =+SUMIF('📁 Panel CMF'!$D$3:$D$93,'🏦 Agregados CMF'!A27,'📁 Panel CMF'!$M$3:$M$93) -> 1666467.7 | D27: =+SUMIF('📁 Panel CMF'!$D$3:$D$93,'🏦 Agregados CMF'!A27,'📁 Panel CMF'!$N$3:$N$93) -> 533773.4 | E27: =+SUMIF('📁 Panel CMF'!$D$3:$D$93,'🏦 Agregados CMF'!A27,'📁 Panel CMF'!$K$3:$K$93) -> 845168.9 | F27: =+SUMIF('📁 Panel CMF'!$D$3:$D$93,'🏦 Agregados CMF'!A27,'📁 Panel CMF'!$L$3:$L$93) -> 1417495.1 | G27: =+F27/C27 -> 0.8505986 | H27: =+E27/C27 -> 0.50716188
A28: 2017 | B28: =+COUNTIF('📁 Panel CMF'!$D$3:$D$93,'🏦 Agregados CMF'!A28) -> 7 | C28: =+SUMIF('📁 Panel CMF'!$D$3:$D$93,'🏦 Agregados CMF'!A28,'📁 Panel CMF'!$M$3:$M$93) -> 1810978 | D28: =+SUMIF('📁 Panel CMF'!$D$3:$D$93,'🏦 Agregados CMF'!A28,'📁 Panel CMF'!$N$3:$N$93) -> 510013 | E28: =+SUMIF('📁 Panel CMF'!$D$3:$D$93,'🏦 Agregados CMF'!A28,'📁 Panel CMF'!$K$3:$K$93) -> 849926 | F28: =+SUMIF('📁 Panel CMF'!$D$3:$D$93,'🏦 Agregados CMF'!A28,'📁 Panel CMF'!$L$3:$L$93) -> 1563136 | G28: =+F28/C28 -> 0.86314467 | H28: =+E28/C28 -> 0.46931879
A29: 2018 | B29: =+COUNTIF('📁 Panel CMF'!$D$3:$D$93,'🏦 Agregados CMF'!A29) -> 7 | C29: =+SUMIF('📁 Panel CMF'!$D$3:$D$93,'🏦 Agregados CMF'!A29,'📁 Panel CMF'!$M$3:$M$93) -> 1981664 | D29: =+SUMIF('📁 Panel CMF'!$D$3:$D$93,'🏦 Agregados CMF'!A29,'📁 Panel CMF'!$N$3:$N$93) -> 538757 | E29: =+SUMIF('📁 Panel CMF'!$D$3:$D$93,'🏦 Agregados CMF'!A29,'📁 Panel CMF'!$K$3:$K$93) -> 925938 | F29: =+SUMIF('📁 Panel CMF'!$D$3:$D$93,'🏦 Agregados CMF'!A29,'📁 Panel CMF'!$L$3:$L$93) -> 1669836 | G29: =+F29/C29 -> 0.84264335 | H29: =+E29/C29 -> 0.46725277
A30: 2019 | B30: =+COUNTIF('📁 Panel CMF'!$D$3:$D$93,'🏦 Agregados CMF'!A30) -> 7 | C30: =+SUMIF('📁 Panel CMF'!$D$3:$D$93,'🏦 Agregados CMF'!A30,'📁 Panel CMF'!$M$3:$M$93) -> 2196438 | D30: =+SUMIF('📁 Panel CMF'!$D$3:$D$93,'🏦 Agregados CMF'!A30,'📁 Panel CMF'!$N$3:$N$93) -> 577075 | E30: =+SUMIF('📁 Panel CMF'!$D$3:$D$93,'🏦 Agregados CMF'!A30,'📁 Panel CMF'!$K$3:$K$93) -> 1046676 | F30: =+SUMIF('📁 Panel CMF'!$D$3:$D$93,'🏦 Agregados CMF'!A30,'📁 Panel CMF'!$L$3:$L$93) -> 1816557 | G30: =+F30/C30 -> 0.82704679 | H30: =+E30/C30 -> 0.47653337
A31: 2020 | B31: =+COUNTIF('📁 Panel CMF'!$D$3:$D$93,'🏦 Agregados CMF'!A31) -> 7 | C31: =+SUMIF('📁 Panel CMF'!$D$3:$D$93,'🏦 Agregados CMF'!A31,'📁 Panel CMF'!$M$3:$M$93) -> 2539812 | D31: =+SUMIF('📁 Panel CMF'!$D$3:$D$93,'🏦 Agregados CMF'!A31,'📁 Panel CMF'!$N$3:$N$93) -> 622202 | E31: =+SUMIF('📁 Panel CMF'!$D$3:$D$93,'🏦 Agregados CMF'!A31,'📁 Panel CMF'!$K$3:$K$93) -> 1335887 | F31: =+SUMIF('📁 Panel CMF'!$D$3:$D$93,'🏦 Agregados CMF'!A31,'📁 Panel CMF'!$L$3:$L$93) -> 1845854 | G31: =+F31/C31 -> 0.72676797 | H31: =+E31/C31 -> 0.52597869
A32: 2021 | B32: =+COUNTIF('📁 Panel CMF'!$D$3:$D$93,'🏦 Agregados CMF'!A32) -> 7 | C32: =+SUMIF('📁 Panel CMF'!$D$3:$D$93,'🏦 Agregados CMF'!A32,'📁 Panel CMF'!$M$3:$M$93) -> 2839874 | D32: =+SUMIF('📁 Panel CMF'!$D$3:$D$93,'🏦 Agregados CMF'!A32,'📁 Panel CMF'!$N$3:$N$93) -> 662605 | E32: =+SUMIF('📁 Panel CMF'!$D$3:$D$93,'🏦 Agregados CMF'!A32,'📁 Panel CMF'!$K$3:$K$93) -> 1672418 | F32: =+SUMIF('📁 Panel CMF'!$D$3:$D$93,'🏦 Agregados CMF'!A32,'📁 Panel CMF'!$L$3:$L$93) -> 1927331 | G32: =+F32/C32 -> 0.67866779 | H32: =+E32/C32 -> 0.5889057
A33: 2022 | B33: =+COUNTIF('📁 Panel CMF'!$D$3:$D$93,'🏦 Agregados CMF'!A33) -> 7 | C33: =+SUMIF('📁 Panel CMF'!$D$3:$D$93,'🏦 Agregados CMF'!A33,'📁 Panel CMF'!$M$3:$M$93) -> 3148866 | D33: =+SUMIF('📁 Panel CMF'!$D$3:$D$93,'🏦 Agregados CMF'!A33,'📁 Panel CMF'!$N$3:$N$93) -> 754875 | E33: =+SUMIF('📁 Panel CMF'!$D$3:$D$93,'🏦 Agregados CMF'!A33,'📁 Panel CMF'!$K$3:$K$93) -> 1851317 | F33: =+SUMIF('📁 Panel CMF'!$D$3:$D$93,'🏦 Agregados CMF'!A33,'📁 Panel CMF'!$L$3:$L$93) -> 2320141 | G33: =+F33/C33 -> 0.73681795 | H33: =+E33/C33 -> 0.58793134
A34: 2023 | B34: =+COUNTIF('📁 Panel CMF'!$D$3:$D$93,'🏦 Agregados CMF'!A34) -> 7 | C34: =+SUMIF('📁 Panel CMF'!$D$3:$D$93,'🏦 Agregados CMF'!A34,'📁 Panel CMF'!$M$3:$M$93) -> 3570911 | D34: =+SUMIF('📁 Panel CMF'!$D$3:$D$93,'🏦 Agregados CMF'!A34,'📁 Panel CMF'!$N$3:$N$93) -> 780738 | E34: =+SUMIF('📁 Panel CMF'!$D$3:$D$93,'🏦 Agregados CMF'!A34,'📁 Panel CMF'!$K$3:$K$93) -> 2227089 | F34: =+SUMIF('📁 Panel CMF'!$D$3:$D$93,'🏦 Agregados CMF'!A34,'📁 Panel CMF'!$L$3:$L$93) -> 2709167 | G34: =+F34/C34 -> 0.75867671 | H34: =+E34/C34 -> 0.6236753
A35: 2024 | B35: =+COUNTIF('📁 Panel CMF'!$D$3:$D$93,'🏦 Agregados CMF'!A35) -> 7 | C35: =+SUMIF('📁 Panel CMF'!$D$3:$D$93,'🏦 Agregados CMF'!A35,'📁 Panel CMF'!$M$3:$M$93) -> 4056784 | D35: =+SUMIF('📁 Panel CMF'!$D$3:$D$93,'🏦 Agregados CMF'!A35,'📁 Panel CMF'!$N$3:$N$93) -> 862532 | E35: =+SUMIF('📁 Panel CMF'!$D$3:$D$93,'🏦 Agregados CMF'!A35,'📁 Panel CMF'!$K$3:$K$93) -> 2536374 | F35: =+SUMIF('📁 Panel CMF'!$D$3:$D$93,'🏦 Agregados CMF'!A35,'📁 Panel CMF'!$L$3:$L$93) -> 3042152 | G35: =+F35/C35 -> 0.74989253 | H35: =+E35/C35 -> 0.62521791
A36: 2025 | B36: =+COUNTIF('📁 Panel CMF'!$D$3:$D$93,'🏦 Agregados CMF'!A36) -> 7 | C36: =+SUMIF('📁 Panel CMF'!$D$3:$D$93,'🏦 Agregados CMF'!A36,'📁 Panel CMF'!$M$3:$M$93) -> 4481909 | D36: =+SUMIF('📁 Panel CMF'!$D$3:$D$93,'🏦 Agregados CMF'!A36,'📁 Panel CMF'!$N$3:$N$93) -> 915240 | E36: =+SUMIF('📁 Panel CMF'!$D$3:$D$93,'🏦 Agregados CMF'!A36,'📁 Panel CMF'!$K$3:$K$93) -> 2761339 | F36: =+SUMIF('📁 Panel CMF'!$D$3:$D$93,'🏦 Agregados CMF'!A36,'📁 Panel CMF'!$L$3:$L$93) -> 3369182 | G36: =+F36/C36 -> 0.75172923 | H36: =+E36/C36 -> 0.61610778
A37: TOTAL PERÍODO | C37: =+SUM(C24:C36) -> 32689270 | D37: =+SUM(D24:D36) -> 8138451 | E37: =+SUM(E24:E36) -> 18219690 | F37: =+SUM(F24:F36) -> 25553072 | G37: — | H37: —

Sheet 🏦 Agregado Total
A1: CUENTA DE PRODUCCIÓN Y GENERACIÓN DEL INGRESO TOTAL — CMF + DAES
A2: P2 = α×P1 (α=0,3776) | B1g = P1−P2 | PIB: Banco Central ref. 2018
A3: Año | B3: N | C3: P1 (MM$) | D3: P2 (MM$) | E3: B1g (MM$) | F3: D1 (MM$) | G3: B2g (MM$) | H3: Rem (MM$) | I3: D1/B1g | J3: PIB Chile (MM$) | K3: Aporte (%)
A4: 2013 | B4: 7 | C4: =+SUMIF('📁 Panel CMF'!$D$3:$D$93,'🏦 Agregados CMF'!A4,'📁 Panel CMF'!$E$3:$E$93) -> 260475 | D4: =0.3776*C4 -> 98355.36 | E4: =+C4-D4 -> 162119.64 | F4: =+SUMIF('📁 Panel CMF'!$D$3:$D$93,'🏦 Agregados CMF'!A4,'📁 Panel CMF'!$H$3:$H$93) -> 61877.3 | G4: =+E4-F4 -> 100242.34 | H4: =+SUMIF('📁 Panel CMF'!$D$3:$D$93,'🏦 Agregados CMF'!A4,'📁 Panel CMF'!$J$3:$J$93) -> 22868.4 | I4: =+F4/E4 -> 0.38167677 | J4: 136003000 | K4: =+(E4/J4)*100 -> 0.11920299
A5: 2014 | B5: =+'📊 Agregados DAES'!B4+'🏦 Agregados CMF'!B5 -> 9 | C5: =+'🏦 Agregados CMF'!C5+'📊 Agregados DAES'!C4 -> 248652.99 | D5: =0.3776*C5 -> 93891.37 | E5: =+C5-D5 -> 154761.62 | F5: =+'🏦 Agregados CMF'!F5+'📊 Agregados DAES'!F4 -> 58623.024 | G5: =+E5-F5 -> 96138.599 | H5: =+'📊 Agregados DAES'!H4+'🏦 Agregados CMF'!H5 -> 23286.547 | I5: =+F5/E5 -> 0.37879561 | J5: 144706000 | K5: =+(E5/J5)*100 -> 0.106949
A6: 2015 | B6: =+'📊 Agregados DAES'!B5+'🏦 Agregados CMF'!B6 -> 14 | C6: =+'🏦 Agregados CMF'!C6+'📊 Agregados DAES'!C5 -> 259248.06 | D6: =0.3776*C6 -> 97892.069 | E6: =+C6-D6 -> 161356 | F6: =+'🏦 Agregados CMF'!F6+'📊 Agregados DAES'!F5 -> 64801.916 | G6: =+E6-F6 -> 96554.079 | H6: =+'📊 Agregados DAES'!H5+'🏦 Agregados CMF'!H6 -> 36417.303 | I6: =+F6/E6 -> 0.40160835 | J6: 158623000 | K6: =+(E6/J6)*100 -> 0.10172295
A7: 2016 | B7: =+'📊 Agregados DAES'!B6+'🏦 Agregados CMF'!B7 -> 16 | C7: =+'🏦 Agregados CMF'!C7+'📊 Agregados DAES'!C6 -> 274314.14 | D7: =0.3776*C7 -> 103581.02 | E7: =+C7-D7 -> 170733.12 | F7: =+'🏦 Agregados CMF'!F7+'📊 Agregados DAES'!F6 -> 72127.976 | G7: =+E7-F7 -> 98605.142 | H7: =+'📊 Agregados DAES'!H6+'🏦 Agregados CMF'!H7 -> 48020.756 | I7: =+F7/E7 -> 0.42246037 | J7: 168765000 | K7: =+(E7/J7)*100 -> 0.10116619
A8: 2017 | B8: =+'📊 Agregados DAES'!B7+'🏦 Agregados CMF'!B8 -> 19 | C8: =+'🏦 Agregados CMF'!C8+'📊 Agregados DAES'!C7 -> 249003.25 | D8: =0.3776*C8 -> 94023.626 | E8: =+C8-D8 -> 154979.62 | F8: =+'🏦 Agregados CMF'!F8+'📊 Agregados DAES'!F7 -> 76445.225 | G8: =+E8-F8 -> 78534.396 | H8: =+'📊 Agregados DAES'!H7+'🏦 Agregados CMF'!H8 -> 68231.277 | I8: =+F8/E8 -> 0.49325985 | J8: 179315000 | K8: =+(E8/J8)*100 -> 0.086428699
A9: 2018 | B9: =+'📊 Agregados DAES'!B8+'🏦 Agregados CMF'!B9 -> 21 | C9: =+'🏦 Agregados CMF'!C9+'📊 Agregados DAES'!C8 -> 266655.26 | D9: =0.3776*C9 -> 100689.03 | E9: =+C9-D9 -> 165966.23 | F9: =+'🏦 Agregados CMF'!F9+'📊 Agregados DAES'!F8 -> 82296.242 | G9: =+E9-F9 -> 83669.992 | H9: =+'📊 Agregados DAES'!H8+'🏦 Agregados CMF'!H9 -> 76266.357 | I9: =+F9/E9 -> 0.49586135 | J9: 189435000 | K9: =+(E9/J9)*100 -> 0.087611177
A10: 2019 | B10: =+'📊 Agregados DAES'!B9+'🏦 Agregados CMF'!B10 -> 13 | C10: =+'🏦 Agregados CMF'!C10+'📊 Agregados DAES'!C9 -> 282385.25 | D10: =0.3776*C10 -> 106628.67 | E10: =+C10-D10 -> 175756.58 | F10: =+'🏦 Agregados CMF'!F10+'📊 Agregados DAES'!F9 -> 85011.988 | G10: =+E10-F10 -> 90744.593 | H10: =+'📊 Agregados DAES'!H9+'🏦 Agregados CMF'!H10 -> 79189.367 | I10: =+F10/E10 -> 0.48369163 | J10: 195548000 | K10: =+(E10/J10)*100 -> 0.089878997
A11: 2020 | B11: =+'📊 Agregados DAES'!B10+'🏦 Agregados CMF'!B11 -> 17 | C11: =+'🏦 Agregados CMF'!C11+'📊 Agregados DAES'!C10 -> 276050.64 | D11: =0.3776*C11 -> 104236.72 | E11: =+C11-D11 -> 171813.92 | F11: =+'🏦 Agregados CMF'!F11+'📊 Agregados DAES'!F10 -> 89698.905 | G11: =+E11-F11 -> 82115.011 | H11: =+'📊 Agregados DAES'!H10+'🏦 Agregados CMF'!H11 -> 67474.049 | I11: =+F11/E11 -> 0.52207008 | J11: 201307000 | K11: =+(E11/J11)*100 -> 0.085349201
A12: 2021 | B12: =+'📊 Agregados DAES'!B11+'🏦 Agregados CMF'!B12 -> 17 | C12: =+'🏦 Agregados CMF'!C12+'📊 Agregados DAES'!C11 -> 281622.52 | D12: =0.3776*C12 -> 106340.66 | E12: =+C12-D12 -> 175281.86 | F12: =+'🏦 Agregados CMF'!F12+'📊 Agregados DAES'!F11 -> 90726.023 | G12: =+E12-F12 -> 84555.833 | H12: =+'📊 Agregados DAES'!H11+'🏦 Agregados CMF'!H12 -> 99740.252 | I12: =+F12/E12 -> 0.51760077 | J12: 239556000 | K12: =+(E12/J12)*100 -> 0.07316947
A13: 2022 | B13: =+'📊 Agregados DAES'!B12+'🏦 Agregados CMF'!B13 -> 26 | C13: =+'🏦 Agregados CMF'!C13+'📊 Agregados DAES'!C12 -> 362119.99 | D13: =0.3776*C13 -> 136736.51 | E13: =+C13-D13 -> 225383.48 | F13: =+'🏦 Agregados CMF'!F13+'📊 Agregados DAES'!F12 -> 98747.172 | G13: =+E13-F13 -> 126636.31 | H13: =+'📊 Agregados DAES'!H12+'🏦 Agregados CMF'!H13 -> 125549.16 | I13: =+F13/E13 -> 0.43812959 | J13: 262954000 | K13: =+(E13/J13)*100 -> 0.085712132
A14: 2023 | B14: =+'📊 Agregados DAES'!B13+'🏦 Agregados CMF'!B14 -> 29 | C14: =+'🏦 Agregados CMF'!C14+'📊 Agregados DAES'!C13 -> 385018.63 | D14: =0.3776*C14 -> 145383.03 | E14: =+C14-D14 -> 239635.59 | F14: =+'🏦 Agregados CMF'!F14+'📊 Agregados DAES'!F13 -> 105308.98 | G14: =+E14-F14 -> 134326.61 | H14: =+'📊 Agregados DAES'!H13+'🏦 Agregados CMF'!H14 -> 94575.858 | I14: =+F14/E14 -> 0.43945469 | J14: 282097000 | K14: =+(E14/J14)*100 -> 0.084947941
A15: 2024 | B15: =+'📊 Agregados DAES'!B14+'🏦 Agregados CMF'!B15 -> 18 | C15: =+'🏦 Agregados CMF'!C15+'📊 Agregados DAES'!C14 -> 422873.86 | D15: =0.3776*C15 -> 159677.17 | E15: =+C15-D15 -> 263196.69 | F15: =+'🏦 Agregados CMF'!F15+'📊 Agregados DAES'!F14 -> 117579.45 | G15: =+E15-F15 -> 145617.24 | H15: =+'📊 Agregados DAES'!H14+'🏦 Agregados CMF'!H15 -> 104220.72 | I15: =+F15/E15 -> 0.44673604 | J15: 310681000 | K15: =+(E15/J15)*100 -> 0.084716056
A16: 2025 | B16: =+'📊 Agregados DAES'!B15+'🏦 Agregados CMF'!B16 -> 7 | C16: =+'🏦 Agregados CMF'!C16+'📊 Agregados DAES'!C15 -> 577398.59 | D16: =0.3776*C16 -> 218025.71 | E16: =+C16-D16 -> 359372.88 | F16: =+'🏦 Agregados CMF'!F16+'📊 Agregados DAES'!F15 -> 167736.1 | G16: =+E16-F16 -> 191636.78 | H16: =+'📊 Agregados DAES'!H15+'🏦 Agregados CMF'!H16 -> 113142.24 | I16: =+F16/E16 -> 0.46674669 | J16: 339978000 | K16: =+(E16/J16)*100 -> 0.10570475
A17: TOTAL PERÍODO | C17: =+SUM(C4:C16) -> 4145818.2 | D17: =+SUM(D4:D16) -> 1565460.9 | E17: =+SUM(E4:E16) -> 2580357.2 | F17: =+SUM(F4:F16) -> 1170980.3 | G17: =+SUM(G4:G16) -> 1409376.9 | H17: =+SUM(H4:H16) -> 958982.29 | I17: — | J17: —
A20: CUENTA FINANCIERA — BALANCE GENERAL TOTAL
A21: F2 = Depósitos captados (vista + plazo) | F4 = Colocaciones netas (total − provisiones)
A22: Año | B22: N | C22: Activos (MM$) | D22: Patrimonio (MM$) | E22: F2 Depósitos (MM$) | F22: F4 Colocaciones (MM$) | G22: F4/Activos | H22: F2/Activos
A23: 2013 | B23: =+'🏦 Agregados CMF'!B24 -> 7 | C23: =+'🏦 Agregados CMF'!C24 -> 1434093.4 | D23: =+'🏦 Agregados CMF'!D24 -> 439510.7 | E23: =+'🏦 Agregados CMF'!E24 -> 709177.9 | F23: =+'🏦 Agregados CMF'!F24 -> 1274441.1 | G23: =+F23/C23 -> 0.88867371 | H23: =+E23/C23 -> 0.49451305
A24: 2014 | B24: =+'📊 Agregados DAES'!B20+'🏦 Agregados CMF'!B25 -> 9 | C24: =+'📊 Agregados DAES'!C20+'🏦 Agregados CMF'!C25 -> 1433274.6 | D24: =+'📊 Agregados DAES'!D20+'🏦 Agregados CMF'!D25 -> 450855.22 | E24: =+'📊 Agregados DAES'!E20+'🏦 Agregados CMF'!E25 -> 716197.52 | F24: =+'📊 Agregados DAES'!F20+'🏦 Agregados CMF'!F25 -> 1267625.9 | G24: =+F24/C24 -> 0.88442637 | H24: =+E24/C24 -> 0.49969317
A25: 2015 | B25: =+COUNTIF('📁 Panel CMF'!$D$3:$D$93,'🏦 Agregados CMF'!A25) -> 7 | C25: =+'📊 Agregados DAES'!C21+'🏦 Agregados CMF'!C26 -> 1561464.4 | D25: =+'📊 Agregados DAES'!D21+'🏦 Agregados CMF'!D26 -> 518169.31 | E25: =+'📊 Agregados DAES'!E21+'🏦 Agregados CMF'!E26 -> 747250.56 | F25: =+'📊 Agregados DAES'!F21+'🏦 Agregados CMF'!F26 -> 1354989.9 | G25: =+F25/C25 -> 0.8677687 | H25: =+E25/C25 -> 0.47855755
A26: 2016 | B26: =+COUNTIF('📁 Panel CMF'!$D$3:$D$93,'🏦 Agregados CMF'!A26) -> 7 | C26: =+'📊 Agregados DAES'!C22+'🏦 Agregados CMF'!C27 -> 1676817.7 | D26: =+'📊 Agregados DAES'!D22+'🏦 Agregados CMF'!D27 -> 538454 | E26: =+'📊 Agregados DAES'!E22+'🏦 Agregados CMF'!E27 -> 850229.57 | F26: =+'📊 Agregados DAES'!F22+'🏦 Agregados CMF'!F27 -> 1424771.8 | G26: =+F26/C26 -> 0.84968795 | H26: =+E26/C26 -> 0.5070495
A27: 2017 | B27: =+COUNTIF('📁 Panel CMF'!$D$3:$D$93,'🏦 Agregados CMF'!A27) -> 7 | C27: =+'📊 Agregados DAES'!C23+'🏦 Agregados CMF'!C28 -> 1843430.6 | D27: =+'📊 Agregados DAES'!D23+'🏦 Agregados CMF'!D28 -> 527343.13 | E27: =+'📊 Agregados DAES'!E23+'🏦 Agregados CMF'!E28 -> 858659.34 | F27: =+'📊 Agregados DAES'!F23+'🏦 Agregados CMF'!F28 -> 1578414.4 | G27: =+F27/C27 -> 0.85623748 | H27: =+E27/C27 -> 0.46579423
A28: 2018 | B28: =+COUNTIF('📁 Panel CMF'!$D$3:$D$93,'🏦 Agregados CMF'!A28) -> 7 | C28: =+'📊 Agregados DAES'!C24+'🏦 Agregados CMF'!C29 -> 2033489.7 | D28: =+'📊 Agregados DAES'!D24+'🏦 Agregados CMF'!D29 -> 558139.34 | E28: =+'📊 Agregados DAES'!E24+'🏦 Agregados CMF'!E29 -> 938557.89 | F28: =+'📊 Agregados DAES'!F24+'🏦 Agregados CMF'!F29 -> 1699568.9 | G28: =+F28/C28 -> 0.83578931 | H28: =+E28/C28 -> 0.46155036
A29: 2019 | B29: =+COUNTIF('📁 Panel CMF'!$D$3:$D$93,'🏦 Agregados CMF'!A29) -> 7 | C29: =+'📊 Agregados DAES'!C25+'🏦 Agregados CMF'!C30 -> 2229477.7 | D29: =+'📊 Agregados DAES'!D25+'🏦 Agregados CMF'!D30 -> 591968.6 | E29: =+'📊 Agregados DAES'!E25+'🏦 Agregados CMF'!E30 -> 1062063.1 | F29: =+'📊 Agregados DAES'!F25+'🏦 Agregados CMF'!F30 -> 1840175.1 | G29: =+F29/C29 -> 0.82538393 | H29: =+E29/C29 -> 0.47637305
A30: 2020 | B30: =+COUNTIF('📁 Panel CMF'!$D$3:$D$93,'🏦 Agregados CMF'!A30) -> 7 | C30: =+'📊 Agregados DAES'!C26+'🏦 Agregados CMF'!C31 -> 2586910.7 | D30: =+'📊 Agregados DAES'!D26+'🏦 Agregados CMF'!D31 -> 645841.69 | E30: =+'📊 Agregados DAES'!E26+'🏦 Agregados CMF'!E31 -> 1357193.1 | F30: =+'📊 Agregados DAES'!F26+'🏦 Agregados CMF'!F31 -> 1873316.1 | G30: =+F30/C30 -> 0.72415181 | H30: =+E30/C30 -> 0.52463854
A31: 2021 | B31: =+COUNTIF('📁 Panel CMF'!$D$3:$D$93,'🏦 Agregados CMF'!A31) -> 7 | C31: =+'📊 Agregados DAES'!C27+'🏦 Agregados CMF'!C32 -> 2886670 | D31: =+'📊 Agregados DAES'!D27+'🏦 Agregados CMF'!D32 -> 687708.64 | E31: =+'📊 Agregados DAES'!E27+'🏦 Agregados CMF'!E32 -> 1692111.5 | F31: =+'📊 Agregados DAES'!F27+'🏦 Agregados CMF'!F32 -> 1955032.9 | G31: =+F31/C31 -> 0.67726234 | H31: =+E31/C31 -> 0.58618112
A32: 2022 | B32: =+COUNTIF('📁 Panel CMF'!$D$3:$D$93,'🏦 Agregados CMF'!A32) -> 7 | C32: =+'📊 Agregados DAES'!C28+'🏦 Agregados CMF'!C33 -> 3233454.7 | D32: =+'📊 Agregados DAES'!D28+'🏦 Agregados CMF'!D33 -> 801186.42 | E32: =+'📊 Agregados DAES'!E28+'🏦 Agregados CMF'!E33 -> 1885462.4 | F32: =+'📊 Agregados DAES'!F28+'🏦 Agregados CMF'!F33 -> 2376704.3 | G32: =+F32/C32 -> 0.73503559 | H32: =+E32/C32 -> 0.58311083
A33: 2023 | B33: =+COUNTIF('📁 Panel CMF'!$D$3:$D$93,'🏦 Agregados CMF'!A33) -> 7 | C33: =+'📊 Agregados DAES'!C29+'🏦 Agregados CMF'!C34 -> 3736816.3 | D33: =+'📊 Agregados DAES'!D29+'🏦 Agregados CMF'!D34 -> 852393.96 | E33: =+'📊 Agregados DAES'!E29+'🏦 Agregados CMF'!E34 -> 2314442.1 | F33: =+'📊 Agregados DAES'!F29+'🏦 Agregados CMF'!F34 -> 2823975.3 | G33: =+F33/C33 -> 0.75571691 | H33: =+E33/C33 -> 0.61936203
A34: 2024 | B34: =+COUNTIF('📁 Panel CMF'!$D$3:$D$93,'🏦 Agregados CMF'!A34) -> 7 | C34: =+'📊 Agregados DAES'!C30+'🏦 Agregados CMF'!C35 -> 4164706.7 | D34: =+'📊 Agregados DAES'!D30+'🏦 Agregados CMF'!D35 -> 906843.96 | E34: =+'📊 Agregados DAES'!E30+'🏦 Agregados CMF'!E35 -> 2596172.9 | F34: =+'📊 Agregados DAES'!F30+'🏦 Agregados CMF'!F35 -> 3123457 | G34: =+F34/C34 -> 0.74998247 | H34: =+E34/C34 -> 0.62337473
A35: 2025 | B35: =+COUNTIF('📁 Panel CMF'!$D$3:$D$93,'🏦 Agregados CMF'!A35) -> 7 | C35: =+'🏦 Agregados CMF'!C36 -> 4481909 | D35: =+'🏦 Agregados CMF'!D36 -> 915240 | E35: =+'🏦 Agregados CMF'!E36 -> 2761339 | F35: =+'🏦 Agregados CMF'!F36 -> 3369182 | G35: =+F35/C35 -> 0.75172923 | H35: =+E35/C35 -> 0.61610778
A36: TOTAL PERÍODO | C36: =+SUM(C23:C35) -> 33302515 | D36: =+SUM(D23:D35) -> 8433655 | E36: =+SUM(E23:E35) -> 18488857 | F36: =+SUM(F23:F35) -> 25961655 | G36: — | H36: —

Sheet 📁 Panel DAES
A1: PANEL DE DATOS — UNA FILA POR COOPERATIVA × AÑO
A2: Segmento | B2: Entidad | C2: RUT | D2: Año | E2: P1 (MM$) | F2: P2 (MM$) | G2: B1g (MM$) | H2: D1 (MM$) | I2: B2g (MM$) | J2: Rem (MM$) | K2: Activos (MM$) | L2: Patrimonio (MM$) | M2: F2 (MM$) | N2: F4 (MM$) | O2: PIB_MM | P2: Aporte (%)
A3: DAES | B3: Andescoop Ltda. | C3: 70009770-6 | D3: 2020 | E3: 1261.9174 | F3: =0.3776*E3 -> 476.50001 | G3: =+E3-F3 -> 785.41739 | H3: 644.20884 | I3: =+G3-H3 -> 141.20854 | J3: -311.96317 | K3: 12536.77 | L3: 6030.0445 | M3: 6454.2873 | N3: 4893.8679 | O3: 201307000 | P3: =+(G3/O3)*100 -> 0.000390159
A4: DAES | B4: Andescoop Ltda. | C4: 70009770-6 | D4: 2022 | E4: 1688.6546 | F4: =0.3776*E4 -> 637.63597 | G4: =+E4-F4 -> 1051.0186 | H4: 697.54668 | I4: =+G4-H4 -> 353.47193 | J4: -637.8462 | O4: 262954000 | P4: =+(G4/O4)*100 -> 0.00039969676
A5: DAES | B5: Andescoop Ltda. | C5: 70009770-6 | D5: 2023 | E5: 1972.1403 | F5: =0.3776*E5 -> 744.68018 | G5: =+E5-F5 -> 1227.4601 | H5: 774.03059 | I5: =+G5-H5 -> 453.42954 | J5: -144.99542 | O5: 282097000 | P5: =+(G5/O5)*100 -> 0.00043511988
A6: DAES | B6: Andescoop Ltda. | C6: 70009770-6 | D6: 2024 | E6: 1682.2219 | F6: =0.3776*E6 -> 635.20697 | G6: =+E6-F6 -> 1047.0149 | H6: 788.54711 | I6: =+G6-H6 -> 258.46777 | J6: 165.01095 | K6: 10789.782 | L6: 6508.7668 | M6: 4150.5813 | N6: 6057.262 | O6: 310681000 | P6: =+(G6/O6)*100 -> 0.00033700641
A7: DAES | B7: Coop. de Ahorro y Crédito Lautaro Rosas | C7: 70286300-7 | D7: 2016 | E7: 3715.6684 | F7: =0.3776*E7 -> 1403.0364 | G7: =+E7-F7 -> 2312.632 | H7: 1094.6625 | I7: =+G7-H7 -> 1217.9696 | J7: 244.33893 | O7: 168765000 | P7: =+(G7/O7)*100 -> 0.0013703268
A8: DAES | B8: Coop. de Ahorro, Crédito y Servicios Financie | C8: 85303300-6 | D8: 2023 | E8: 526.98993 | F8: =0.3776*E8 -> 198.9914 | G8: =+E8-F8 -> 327.99854 | I8: =+G8-H8 -> 327.99854 | J8: 273.25852 | K8: 3202.3398 | L8: 3126.2303 | N8: 2556.531 | O8: 282097000 | P8: =+(G8/O8)*100 -> 0.00011627154
A9: DAES | B9: Coop. de Ahorro, Crédito y Servicios Financie | C9: 85303300-6 | D9: 2024 | E9: 606.99092 | F9: =0.3776*E9 -> 229.19977 | G9: =+E9-F9 -> 377.79115 | I9: =+G9-H9 -> 377.79115 | J9: 312.94338 | K9: 3413.6621 | L9: 3347.5055 | N9: 2672.864 | O9: 310681000 | P9: =+(G9/O9)*100 -> 0.00012160098
A10: DAES | B10: Cooperativa de Ahorro y Crédito Ahorro Maule | C10: 83908800-0 | D10: 2016 | E10: 186.92499 | F10: =0.3776*E10 -> 70.582875 | G10: =+E10-F10 -> 116.34211 | H10: 114.67537 | I10: =+G10-H10 -> 1.6667395 | J10: 11.741258 | K10: 835.29859 | L10: 637.39627 | M10: 194.09069 | N10: 604.02813 | O10: 168765000 | P10: =+(G10/O10)*100 -> 6.8937346e-05
A11: DAES | B11: Cooperativa de Ahorro y Crédito Ahorro Maule | C11: 83908800-0 | D11: 2017 | E11: 200.52856 | F11: =0.3776*E11 -> 75.719585 | G11: =+E11-F11 -> 124.80898 | H11: 125.4804 | I11: =+G11-H11 -> -0.67142101 | J11: 15.889036 | K11: 897.25446 | L11: 671.75859 | M11: 219.71958 | N11: 672.72419 | O11: 179315000 | P11: =+(G11/O11)*100 -> 6.9603199e-05
A12: DAES | B12: Cooperativa de Ahorro y Crédito Ahorro Maule | C12: 83908800-0 | D12: 2018 | E12: 204.64546 | F12: =0.3776*E12 -> 77.274126 | G12: =+E12-F12 -> 127.37133 | H12: 129.35863 | I12: =+G12-H12 -> -1.9872977 | J12: 8.767605 | K12: 935.7158 | L12: 680.78947 | M12: 251.15994 | N12: 706.55119 | O12: 189435000 | P12: =+(G12/O12)*100 -> 6.7237487e-05
A13: DAES | B13: Cooperativa de Ahorro y Crédito Araucaniacoop | C13: 76489600-9 | D13: 2020 | E13: 324.92926 | F13: =0.3776*E13 -> 122.69329 | G13: =+E13-F13 -> 202.23597 | H13: 72.29985 | I13: =+G13-H13 -> 129.93612 | J13: 116.58819 | K13: 2690.7596 | L13: 1607.4387 | M13: 982.23502 | N13: 1532.5048 | O13: 201307000 | P13: =+(G13/O13)*100 -> 0.00010046147
A14: DAES | B14: Cooperativa de Ahorro y Crédito Araucaniacoop | C14: 76489600-9 | D14: 2021 | E14: 293.79417 | F14: =0.3776*E14 -> 110.93668 | G14: =+E14-F14 -> 182.85749 | H14: 73.823908 | I14: =+G14-H14 -> 109.03358 | J14: 6.158815 | K14: 3268.7477 | L14: 1681.1529 | M14: 1498.3962 | N14: 1187.013 | O14: 239556000 | P14: =+(G14/O14)*100 -> 7.6331835e-05
A15: DAES | B15: Cooperativa de Ahorro y Crédito Araucaniacoop | C15: 76489600-9 | D15: 2022 | E15: 349.90696 | F15: =0.3776*E15 -> 132.12487 | G15: =+E15-F15 -> 217.78209 | H15: 103.49862 | I15: =+G15-H15 -> 114.28347 | J15: -28.267172 | K15: 2819.4288 | L15: 1879.5437 | M15: 860.00942 | N15: 1929.4592 | O15: 262954000 | P15: =+(G15/O15)*100 -> 8.2821365e-05
A16: DAES | B16: Cooperativa de Ahorro y Crédito Araucaniacoop | C16: 76489600-9 | D16: 2022 | E16: 366.70249 | F16: =0.3776*E16 -> 138.46686 | G16: =+E16-F16 -> 228.23563 | H16: 108.46655 | I16: =+G16-H16 -> 119.76908 | J16: -29.623996 | K16: 2819.4288 | L16: 1879.5437 | M16: 860.00942 | N16: 1929.4592 | O16: 262954000 | P16: =+(G16/O16)*100 -> 8.679679e-05
A17: DAES | B17: Cooperativa de Ahorro y Crédito Araucaniacoop | C17: 76489600-9 | D17: 2023 | E17: 401.28502 | F17: =0.3776*E17 -> 151.52522 | G17: =+E17-F17 -> 249.7598 | H17: 133.80551 | I17: =+G17-H17 -> 115.95429 | J17: 57.804792 | O17: 282097000 | P17: =+(G17/O17)*100 -> 8.853685e-05
A18: DAES | B18: Cooperativa de Ahorro y Crédito Araucaniacoop | C18: 76489600-9 | D18: 2024 | E18: 418.51746 | F18: =0.3776*E18 -> 158.03219 | G18: =+E18-F18 -> 260.48527 | H18: 133.1766 | I18: =+G18-H18 -> 127.30867 | J18: 53.358415 | K18: 2970.091 | L18: 2139.1695 | M18: 783.46419 | N18: 1961.4377 | O18: 310681000 | P18: =+(G18/O18)*100 -> 8.3843321e-05
A19: DAES | B19: Cooperativa de Ahorro y Crédito Bancrece | C19: 65144029-7 | D19: 2021 | E19: 1.694809 | F19: =0.3776*E19 -> 0.63995988 | G19: =+E19-F19 -> 1.0548491 | I19: =+G19-H19 -> 1.0548491 | J19: -0.213368 | O19: 239556000 | P19: =+(G19/O19)*100 -> 4.4033509e-07
A20: DAES | B20: Cooperativa de Ahorro y Crédito Bancrece | C20: 65144029-7 | D20: 2022 | E20: 2.92309 | F20: =0.3776*E20 -> 1.1037588 | G20: =+E20-F20 -> 1.8193312 | H20: 1.282661 | I20: =+G20-H20 -> 0.53667022 | J20: -0.394412 | K20: 17.197674 | L20: 1.71025 | M20: 13.332883 | N20: 11.047155 | O20: 262954000 | P20: =+(G20/O20)*100 -> 6.9188193e-07
A21: DAES | B21: Cooperativa de Ahorro y Crédito Bancrece | C21: 65144029-7 | D21: 2023 | E21: 5.0178 | F21: =0.3776*E21 -> 1.8947213 | G21: =+E21-F21 -> 3.1230787 | H21: 1.543726 | I21: =+G21-H21 -> 1.5793527 | J21: 0.245738 | K21: 26.55487 | L21: 2.446476 | M21: 21.496 | N21: 18.202446 | O21: 282097000 | P21: =+(G21/O21)*100 -> 1.1070939e-06
A22: DAES | B22: Cooperativa de Ahorro y Crédito Bancrece | C22: 65144029-7 | D22: 2024 | E22: 8.197293 | F22: =0.3776*E22 -> 3.0952978 | G22: =+E22-F22 -> 5.1019952 | H22: 2.45793 | I22: =+G22-H22 -> 2.6440652 | J22: 1.167724 | K22: 42.551814 | L22: 4.076304 | M22: 37.214514 | N22: 32.154974 | O22: 310681000 | P22: =+(G22/O22)*100 -> 1.6421974e-06
A23: DAES | B23: Cooperativa de Ahorro y Crédito Bansur | C23: 65002821-K | D23: 2019 | E23: 1089.4257 | F23: =0.3776*E23 -> 411.36715 | G23: =+E23-F23 -> 678.05857 | H23: 352.76535 | I23: =+G23-H23 -> 325.29322 | J23: 116.46968 | K23: 6882.5332 | L23: 1073.0998 | M23: 5168.469 | N23: 5329.1546 | O23: 195548000 | P23: =+(G23/O23)*100 -> 0.00034674789
A24: DAES | B24: Cooperativa de Ahorro y Crédito Bansur | C24: 65002821-K | D24: 2020 | E24: 1039.6192 | F24: =0.3776*E24 -> 392.56021 | G24: =+E24-F24 -> 647.05899 | H24: 345.74504 | I24: =+G24-H24 -> 301.31394 | J24: 6.20403 | K24: 7186.0343 | L24: 1113.4539 | M24: 6029.6582 | N24: 4497.5351 | O24: 201307000 | P24: =+(G24/O24)*100 -> 0.00032142895
A25: DAES | B25: Cooperativa de Ahorro y Crédito Bansur | C25: 65002821-K | D25: 2021 | E25: 1117.9335 | F25: =0.3776*E25 -> 422.13168 | G25: =+E25-F25 -> 695.80179 | H25: 327.75752 | I25: =+G25-H25 -> 368.04427 | J25: 105.1855 | K25: 7292.0895 | L25: 1336.7627 | M25: 5902.8012 | N25: 4979.9877 | O25: 239556000 | P25: =+(G25/O25)*100 -> 0.00029045475
A26: DAES | B26: Cooperativa de Ahorro y Crédito Bansur | C26: 65002821-K | D26: 2022 | E26: 1485.3753 | F26: =0.3776*E26 -> 560.87772 | G26: =+E26-F26 -> 924.49761 | H26: 391.89795 | I26: =+G26-H26 -> 532.59966 | J26: 42.594128 | K26: 8250.3409 | L26: 1765.2139 | M26: 6405.6976 | N26: 6453.6491 | O26: 262954000 | P26: =+(G26/O26)*100 -> 0.0003515815
A27: DAES | B27: Cooperativa de Ahorro y Crédito Bansur | C27: 65002821-K | D27: 2023 | E27: 1740.0087 | F27: =0.3776*E27 -> 657.0273 | G27: =+E27-F27 -> 1082.9814 | H27: 416.08872 | I27: =+G27-H27 -> 666.89272 | J27: 40.183435 | K27: 10172.81 | L27: 1853.6455 | M27: 8143.1628 | N27: 7006.3356 | O27: 282097000 | P27: =+(G27/O27)*100 -> 0.00038390392
A28: DAES | B28: Cooperativa de Ahorro y Crédito Cajanova | C28: 65461730-9 | D28: 2020 | E28: 259.09107 | F28: =0.3776*E28 -> 97.832787 | G28: =+E28-F28 -> 161.25828 | H28: 94.295685 | I28: =+G28-H28 -> 66.962594 | J28: 23.530015 | K28: 2384.8037 | L28: 1188.517 | M28: 1129.6605 | N28: 2069.955 | O28: 201307000 | P28: =+(G28/O28)*100 -> 8.0105649e-05
A29: DAES | B29: Cooperativa de Ahorro y Crédito Cajanova | C29: 65461730-9 | D29: 2021 | E29: 237.66831 | F29: =0.3776*E29 -> 89.743553 | G29: =+E29-F29 -> 147.92476 | H29: 87.097456 | I29: =+G29-H29 -> 60.8273 | J29: 16.322393 | K29: 1941.5712 | L29: 1214.5392 | M29: 710.68891 | N29: 1560.2638 | O29: 239556000 | P29: =+(G29/O29)*100 -> 6.1749551e-05
A30: DAES | B30: Cooperativa de Ahorro y Crédito Cajanova | C30: 65461730-9 | D30: 2022 | E30: 510.6114 | F30: =0.3776*E30 -> 192.80686 | G30: =+E30-F30 -> 317.80453 | H30: 82.871102 | I30: =+G30-H30 -> 234.93343 | J30: 34.302946 | K30: 2055.2634 | L30: 1395.8106 | M30: 217.98501 | N30: 1848.8221 | O30: 262954000 | P30: =+(G30/O30)*100 -> 0.00012085936
A31: DAES | B31: Cooperativa de Ahorro y Crédito Cajanova | C31: 65461730-9 | D31: 2023 | E31: 286.65637 | F31: =0.3776*E31 -> 108.24144 | G31: =+E31-F31 -> 178.41492 | H31: 104.31564 | I31: =+G31-H31 -> 74.099286 | J31: -183.41869 | K31: 6665.4839 | L31: 1327.8182 | M31: 5247.9737 | N31: 1217.8318 | O31: 282097000 | P31: =+(G31/O31)*100 -> 6.3245949e-05
... A33: DAES | B33: Cooperativa de Ahorro y Crédito Coosagro Ltda | C33: 70022600-K | D33: 2023 | E33: 88.925671 | F33: =0.3776*E33 -> 33.578333 | G33: =+E33-F33 -> 55.347338 | H33: 34.868674 | I33: =+G33-H33 -> 20.478664 | J33: 9.077125 | K33: 632.05359 | L33: 579.28116 | M33: 7.546419 | N33: 318.53043 | O33: 282097000 | P33: =+(G33/O33)*100 -> 1.9619967e-05
A34: DAES | B34: Cooperativa de Ahorro y Crédito de Educadores | C34: 70350700-K | D34: 2017 | E34: 370.30518 | F34: =0.3776*E34 -> 139.82724 | G34: =+E34-F34 -> 230.47794 | H34: 343.64814 | I34: =+G34-H34 -> -113.1702 | J34: -267.82745 | K34: 1331.7833 | L34: 1180.9397 | N34: 766.8104 | O34: 179315000 | P34: =+(G34/O34)*100 -> 0.00012853244
A35: DAES | B35: Cooperativa de Ahorro y Crédito de Educadores | C35: 70350700-K | D35: 2018 | E35: 275.19539 | F35: =0.3776*E35 -> 103.91378 | G35: =+E35-F35 -> 171.28161 | H35: 285.65081 | I35: =+G35-H35 -> -114.3692 | J35: -158.69278 | K35: 1119.831 | L35: 1024.0861 | N35: 580.33956 | O35: 189435000 | P35: =+(G35/O35)*100 -> 9.0417087e-05
A36: DAES | B36: Cooperativa de Ahorro y Crédito Dreves Limita | C36: 83990500-9 | D36: 2017 | F36: =0.3776*E36 -> 0 | G36: =+E36-F36 -> 0 | H36: 86.666 | I36: =+G36-H36 -> -86.666 | J36: -96.234 | K36: 183.104 | L36: 94.413 | O36: 179315000 | P36: =+(G36/O36)*100 -> 0
A37: DAES | B37: Cooperativa de Ahorro y Crédito Dreves Limita | C37: 83990500-9 | D37: 2018 | F37: =0.3776*E37 -> 0 | G37: =+E37-F37 -> 0 | H37: 70.504 | I37: =+G37-H37 -> -70.504 | J37: -66.778 | K37: 98.651 | L37: 12.057 | O37: 189435000 | P37: =+(G37/O37)*100 -> 0
A38: DAES | B38: Cooperativa de Ahorro y Crédito Endógena Mapu | C38: 65111485-3 | D38: 2015 | E38: 0 | F38: =0.3776*E38 -> 0 | G38: =+E38-F38 -> 0 | I38: =+G38-H38 -> 0 | J38: -0.000112 | K38: 0.02802 | L38: 0.02802 | M38: 0 | N38: 0 | O38: 158623000 | P38: =+(G38/O38)*100 -> 0
A39: DAES | B39: Cooperativa de Ahorro y Crédito Endógena Mapu | C39: 65111485-3 | D39: 2016 | E39: 0.002191 | F39: =0.3776*E39 -> 0.0008273216 | G39: =+E39-F39 -> 0.0013636784 | I39: =+G39-H39 -> 0.0013636784 | J39: -0.017597 | K39: 0.026606 | L39: 0.023667 | M39: 0 | N39: 0.011761 | O39: 168765000 | P39: =+(G39/O39)*100 -> 8.0803389e-10
A40: DAES | B40: Cooperativa de Ahorro y Crédito Endógena Mapu | C40: 65111485-3 | D40: 2017 | F40: =0.3776*E40 -> 0 | G40: =+E40-F40 -> 0 | H40: 11.793 | I40: =+G40-H40 -> -11.793 | J40: 1.686 | K40: 47.656 | L40: 43.527 | O40: 179315000 | P40: =+(G40/O40)*100 -> 0
A41: DAES | B41: Cooperativa de Ahorro y Crédito Endógena Mapu | C41: 65111485-3 | D41: 2018 | F41: =0.3776*E41 -> 0 | G41: =+E41-F41 -> 0 | H41: 19.603 | I41: =+G41-H41 -> -19.603 | J41: -5.171 | K41: 62.722 | L41: 58.197 | O41: 189435000 | P41: =+(G41/O41)*100 -> 0
A42: DAES | B42: Cooperativa de Ahorro y Crédito Financiera Ag | C42: 76177376-3 | D42: 2016 | E42: 0.852054 | F42: =0.3776*E42 -> 0.32173559 | G42: =+E42-F42 -> 0.53031841 | H42: 0.167966 | I42: =+G42-H42 -> 0.36235241 | J42: 0.281987 | K42: 5.493493 | L42: 2.213466 | M42: 3.261645 | N42: 4.964012 | O42: 168765000 | P42: =+(G42/O42)*100 -> 3.1423483e-07
A43: DAES | B43: Cooperativa de Ahorro y Crédito Financiera Ag | C43: 76177376-3 | D43: 2017 | E43: 1160.472 | F43: =0.3776*E43 -> 438.19423 | G43: =+E43-F43 -> 722.27777 | H43: 202.545 | I43: =+G43-H43 -> 519.73277 | J43: 392.78 | K43: 7092.565 | L43: 2914.728 | M43: 4177.837 | O43: 179315000 | P43: =+(G43/O43)*100 -> 0.0004027983
A44: DAES | B44: Cooperativa de Ahorro y Crédito Financiera Ag | C44: 76177376-3 | D44: 2018 | E44: 1249.561 | F44: =0.3776*E44 -> 471.83423 | G44: =+E44-F44 -> 777.72677 | H44: 217.369 | I44: =+G44-H44 -> 560.35777 | J44: 410.926 | K44: 7640.811 | L44: 4095.287 | M44: 3545.524 | O44: 189435000 | P44: =+(G44/O44)*100 -> 0.00041055073
A45: DAES | B45: Cooperativa de Ahorro y Crédito Isla de Maipo | C45: 70000770-7 | D45: 2019 | E45: 786.22556 | F45: =0.3776*E45 -> 296.87877 | G45: =+E45-F45 -> 489.34679 | H45: 470.664 | I45: =+G45-H45 -> 18.682787 | J45: 23.657494 | K45: 6787.0129 | L45: 6660.1537 | M45: 64.254894 | N45: 4672.081 | O45: 195548000 | P45: =+(G45/O45)*100 -> 0.00025024382
A46: DAES | B46: Cooperativa de Ahorro y Crédito Isla de Maipo | C46: 70000770-7 | D46: 2020 | E46: 678.075 | F46: =0.3776*E46 -> 256.04112 | G46: =+E46-F46 -> 422.03388 | H46: 414.222 | I46: =+G46-H46 -> 7.81188 | J46: 33.212 | K46: 6891.819 | L46: 6783.906 | M46: 51.908 | N46: 3613.373 | O46: 201307000 | P46: =+(G46/O46)*100 -> 0.0002096469
A47: DAES | B47: Cooperativa de Ahorro y Crédito Isla de Maipo | C47: 70000770-7 | D47: 2021 | E47: 681.913 | F47: =0.3776*E47 -> 257.49035 | G47: =+E47-F47 -> 424.42265 | H47: 250.283 | I47: =+G47-H47 -> 174.13965 | J47: -166.149 | K47: 7517.031 | L47: 7440.152 | M47: 43.03 | N47: 3188.84 | O47: 239556000 | P47: =+(G47/O47)*100 -> 0.00017717054
A48: DAES | B48: Cooperativa de Ahorro y Crédito Isla de Maipo | C48: 70000770-7 | D48: 2022 | E48: 1101.0468 | F48: =0.3776*E48 -> 415.75526 | G48: =+E48-F48 -> 685.29152 | H48: 541.575 | I48: =+G48-H48 -> 143.71652 | J48: -412.35342 | K48: 8475.0101 | L48: 8289.0517 | M48: 156.13162 | N48: 4272.1134 | O48: 262954000 | P48: =+(G48/O48)*100 -> 0.0002606127
A49: DAES | B49: Cooperativa de Ahorro y Crédito Isla de Maipo | C49: 70000770-7 | D49: 2023 | E49: 1270.0178 | F49: =0.3776*E49 -> 479.55872 | G49: =+E49-F49 -> 790.45908 | H49: 609.568 | I49: =+G49-H49 -> 180.89108 | J49: 170.64343 | K49: 8374.3542 | L49: 8133.9973 | M49: 177.32182 | N49: 4230.3691 | O49: 282097000 | P49: =+(G49/O49)*100 -> 0.00028020825
A50: DAES | B50: Cooperativa de Ahorro y Crédito Lautaro Rosas | C50: 70286300-7 | D50: 2015 | E50: 3368.8769 | F50: =0.3776*E50 -> 1272.0879 | G50: =+E50-F50 -> 2096.789 | H50: 984.36359 | I50: =+G50-H50 -> 1112.4254 | J50: 582.30361 | K50: 28146.628 | L50: 23719.671 | M50: 4202.1048 | N50: 21229.854 | O50: 158623000 | P50: =+(G50/O50)*100 -> 0.0013218695
A51: DAES | B51: Cooperativa de Ahorro y Crédito Libercoop Lim | C51: 83380000-0 | D51: 2015 | E51: 553.03836 | F51: =0.3776*E51 -> 208.82729 | G51: =+E51-F51 -> 344.21108 | H51: 164.46856 | I51: =+G51-H51 -> 179.74252 | O51: 158623000 | P51: =+(G51/O51)*100 -> 0.00021699947
A52: DAES | B52: Cooperativa de Ahorro y Crédito Libercoop Lim | C52: 83380000-0 | D52: 2016 | E52: 560.69058 | F52: =0.3776*E52 -> 211.71676 | G52: =+E52-F52 -> 348.97382 | H52: 202.41414 | I52: =+G52-H52 -> 146.55968 | O52: 168765000 | P52: =+(G52/O52)*100 -> 0.00020678092
A53: DAES | B53: Cooperativa de Ahorro y Crédito Libercoop Lim | C53: 83380000-0 | D53: 2017 | E53: 638.42819 | F53: =0.3776*E53 -> 241.07048 | G53: =+E53-F53 -> 397.3577 | H53: 198.85575 | I53: =+G53-H53 -> 198.50195 | O53: 179315000 | P53: =+(G53/O53)*100 -> 0.00022159758
A54: DAES | B54: Cooperativa de Ahorro y Crédito Libercoop Lim | C54: 83380000-0 | D54: 2018 | E54: 657.18569 | F54: =0.3776*E54 -> 248.15332 | G54: =+E54-F54 -> 409.03237 | H54: 224.94058 | I54: =+G54-H54 -> 184.09179 | J54: 12.754144 | K54: 4801.5266 | L54: 618.55327 | M54: 4014.9295 | N54: 3252.1376 | O54: 189435000 | P54: =+(G54/O54)*100 -> 0.00021592228
A55: DAES | B55: Cooperativa de Ahorro y Crédito Libercoop Lim | C55: 83380000-0 | D55: 2019 | E55: 757.91552 | F55: =0.3776*E55 -> 286.1889 | G55: =+E55-F55 -> 471.72662 | H55: 263.38931 | I55: =+G55-H55 -> 208.33731 | J55: 11.276717 | K55: 5578.4891 | L55: 657.59011 | M55: 4485.6803 | N55: 3682.6677 | O55: 195548000 | P55: =+(G55/O55)*100 -> 0.00024123316
A56: DAES | B56: Cooperativa de Ahorro y Crédito Libercoop Lim | C56: 83380000-0 | D56: 2022 | E56: 968.55349 | F56: =0.3776*E56 -> 365.7258 | G56: =+E56-F56 -> 602.82769 | H56: 392.92979 | I56: =+G56-H56 -> 209.89791 | J56: 10.828047 | O56: 262954000 | P56: =+(G56/O56)*100 -> 0.00022925215
A57: DAES | B57: Cooperativa de Ahorro y Crédito Libercoop Lim | C57: 83380000-0 | D57: 2023 | E57: 5438.8511 | F57: =0.3776*E57 -> 2053.7102 | G57: =+E57-F57 -> 3385.1409 | H57: 1094.0333 | I57: =+G57-H57 -> 2291.1076 | J57: 619.40968 | K57: 19732.573 | L57: 6512.7474 | M57: 13009.668 | N57: 15456.547 | O57: 282097000 | P57: =+(G57/O57)*100 -> 0.0011999918
A58: DAES | B58: Cooperativa de Ahorro y Crédito Libercoop Lim | C58: 83380000-0 | D58: 2023 | E58: 5438.8511 | F58: =0.3776*E58 -> 2053.7102 | G58: =+E58-F58 -> 3385.1409 | H58: 1094.0333 | I58: =+G58-H58 -> 2291.1076 | J58: 619.40968 | K58: 8943.7205 | L58: 906.81991 | M58: 7940.5407 | O58: 282097000 | P58: =+(G58/O58)*100 -> 0.0011999918
A59: DAES | B59: Cooperativa de Ahorro y Crédito Limarí Limita | C59: 76005094-6 | D59: 2016 | E59: 0.139838 | F59: =0.3776*E59 -> 0.052802829 | G59: =+E59-F59 -> 0.087035171 | H59: 0.071817 | I59: =+G59-H59 -> 0.015218171 | J59: 0.01607 | K59: 0.728656 | L59: 0.083831 | M59: 0.642418 | N59: 0.475309 | O59: 168765000 | P59: =+(G59/O59)*100 -> 5.1571814e-08
A60: DAES | B60: Cooperativa de Ahorro y Crédito Limarí Limita | C60: 76005094-6 | D60: 2017 | E60: 0.131367 | F60: =0.3776*E60 -> 0.049604179 | G60: =+E60-F60 -> 0.081762821 | H60: 0.083293 | I60: =+G60-H60 -> -0.0015301792 | J60: 0.009038 | K60: 0.791165 | L60: 0.081389 | M60: 0.701638 | N60: 0.645703 | O60: 179315000 | P60: =+(G60/O60)*100 -> 4.5597312e-08
A61: DAES | B61: Cooperativa de Ahorro y Crédito Mujercoop | C61: 70689800-K | D61: 2014 | E61: 247.13324 | F61: =0.3776*E61 -> 93.317513 | G61: =+E61-F61 -> 153.81573 | H61: 74.356209 | I61: =+G61-H61 -> 79.459521 | K61: 1172.6335 | L61: 1113.4527 | M61: 39.610346 | N61: 821.23124 | O61: 144706000 | P61: =+(G61/O61)*100 -> 0.00010629534
A62: DAES | B62: Cooperativa de Ahorro y Crédito Mujercoop | C62: 70689800-K | D62: 2015 | E62: 251.80491 | F62: =0.3776*E62 -> 95.081536 | G62: =+E62-F62 -> 156.72338 | H62: 86.255316 | I62: =+G62-H62 -> 70.468062 | K62: 1286.8455 | L62: 1214.823 | M62: 57.722889 | N62: 903.23929 | O62: 158623000 | P62: =+(G62/O62)*100 -> 9.880243e-05
A63: DAES | B63: Cooperativa de Ahorro y Crédito Mujercoop | C63: 70689800-K | D63: 2016 | E63: 235.77157 | F63: =0.3776*E63 -> 89.027345 | G63: =+E63-F63 -> 146.74423 | H63: 93.099451 | I63: =+G63-H63 -> 53.644775 | K63: 1369.7303 | L63: 1282.1932 | M63: 68.492949 | N63: 920.28239 | O63: 168765000 | P63: =+(G63/O63)*100 -> 8.6951812e-05
A64: DAES | B64: Cooperativa de Ahorro y Crédito Mujercoop | C64: 70689800-K | D64: 2017 | E64: 227.74724 | F64: =0.3776*E64 -> 85.997358 | G64: =+E64-F64 -> 141.74988 | H64: 101.49446 | I64: =+G64-H64 -> 40.255427 | J64: 33.685507 | K64: 1400.7103 | L64: 1345.561 | M64: 25.387311 | N64: 886.95895 | O64: 179315000 | P64: =+(G64/O64)*100 -> 7.9050767e-05
A65: DAES | B65: Cooperativa de Ahorro y Crédito Mujercoop | C65: 70689800-K | D65: 2018 | E65: 226.5674 | F65: =0.3776*E65 -> 85.55185 | G65: =+E65-F65 -> 141.01555 | H65: 106.0604 | I65: =+G65-H65 -> 34.955152 | J65: -19.197058 | K65: 1397.1998 | L65: 1347.6148 | M65: 13.917498 | N65: 934.97535 | O65: 189435000 | P65: =+(G65/O65)*100 -> 7.4440071e-05
A66: DAES | B66: Cooperativa de Ahorro y Crédito Mujercoop | C66: 70689800-K | D66: 2022 | E66: 207.97096 | F66: =0.3776*E66 -> 78.529835 | G66: =+E66-F66 -> 129.44113 | I66: =+G66-H66 -> 129.44113 | J66: -94.272581 | K66: 1621.8757 | L66: 1558.5544 | N66: 809.59618 | O66: 262954000 | P66: =+(G66/O66)*100 -> 4.9225768e-05
A67: DAES | B67: Cooperativa de Ahorro y Crédito Mujercoop | C67: 70689800-K | D67: 2023 | E67: 259.49953 | F67: =0.3776*E67 -> 97.987022 | G67: =+E67-F67 -> 161.51251 | I67: =+G67-H67 -> 161.51251 | J67: 22.827034 | K67: 1613.1585 | L67: 1540.3397 | N67: 907.73819 | O67: 282097000 | P67: =+(G67/O67)*100 -> 5.7254245e-05
A68: DAES | B68: Cooperativa de Ahorro y Crédito Norte Grande | C68: 81863900-7 | D68: 2017 | E68: 2207.2309 | F68: =0.3776*E68 -> 833.45039 | G68: =+E68-F68 -> 1373.7805 | H68: 942.66384 | I68: =+G68-H68 -> 431.11668 | J68: 20.684132 | K68: 15720.697 | L68: 8261.1877 | M68: 1537.7548 | N68: 8472.8268 | O68: 179315000 | P68: =+(G68/O68)*100 -> 0.00076612694
A69: DAES | B69: Cooperativa de Ahorro y Crédito Norte Grande | C69: 81863900-7 | D69: 2018 | E69: 2218.9246 | F69: =0.3776*E69 -> 837.86595 | G69: =+E69-F69 -> 1381.0587 | H69: 1353.3568 | I69: =+G69-H69 -> 27.7019 | J69: 169.18852 | K69: 15924.49 | L69: 8477.3638 | M69: 1401.4293 | N69: 8188.5405 | O69: 189435000 | P69: =+(G69/O69)*100 -> 0.00072904094
A70: DAES | B70: Cooperativa de Ahorro y Crédito O'Higgins Ltd | C70: 84150700-2 | D70: 2022 | E70: 394.29883 | F70: =0.3776*E70 -> 148.88724 | G70: =+E70-F70 -> 245.41159 | H70: 211.76087 | I70: =+G70-H70 -> 33.650723 | J70: 1.45852 | K70: 3552.3873 | L70: 1012.9425 | M70: 2529.2419 | N70: 1831.2424 | O70: 262954000 | P70: =+(G70/O70)*100 -> 9.3328716e-05
A71: DAES | B71: Cooperativa de Ahorro y Crédito O'Higgins Ltd | C71: 84150700-2 | D71: 2023 | E71: 327.32966 | F71: =0.3776*E71 -> 123.59968 | G71: =+E71-F71 -> 203.72998 | H71: 242.26779 | I71: =+G71-H71 -> -38.537814 | J71: 3.073919 | K71: 3579.5949 | L71: 995.51474 | M71: 2278.9391 | N71: 1565.7438 | O71: 282097000 | P71: =+(G71/O71)*100 -> 7.2219831e-05
A72: DAES | B72: Cooperativa de Ahorro y Crédito para el Desar | C72: 65677500-9 | D72: 2020 | E72: 4.761814 | F72: =0.3776*E72 -> 1.798061 | G72: =+E72-F72 -> 2.963753 | H72: 1.668205 | I72: =+G72-H72 -> 1.295548 | J72: 1.120719 | K72: 31.262546 | L72: 6.924262 | M72: 18.930191 | N72: 26.845703 | O72: 201307000 | P72: =+(G72/O72)*100 -> 1.4722553e-06
A73: DAES | B73: Cooperativa de Ahorro y Crédito para el Desar | C73: 65677500-9 | D73: 2021 | E73: 6.951688 | F73: =0.3776*E73 -> 2.6249574 | G73: =+E73-F73 -> 4.3267306 | H73: 2.753337 | I73: =+G73-H73 -> 1.5733936 | J73: 1.211909 | K73: 28.152536 | L73: 8.397029 | M73: 16.970947 | N73: 25.760278 | O73: 239556000 | P73: =+(G73/O73)*100 -> 1.8061458e-06
A74: DAES | B74: Cooperativa de Ahorro y Crédito para el Desar | C74: 65677500-9 | D74: 2022 | E74: 7.36768 | F74: =0.3776*E74 -> 2.782036 | G74: =+E74-F74 -> 4.585644 | H74: 3.566799 | I74: =+G74-H74 -> 1.018845 | J74: -1.55902 | K74: 33.988987 | L74: 8.309169 | M74: 21.550511 | N74: 31.136392 | O74: 262954000 | P74: =+(G74/O74)*100 -> 1.7438959e-06
A75: DAES | B75: Cooperativa de Ahorro y Crédito para el Desar | C75: 65677500-9 | D75: 2023 | E75: 9903.39 | F75: =0.3776*E75 -> 3739.5201 | G75: =+E75-F75 -> 6163.8699 | H75: 3648.234 | I75: =+G75-H75 -> 2515.6359 | J75: 8.864 | K75: 40048.604 | L75: 9413.563 | M75: 26433.091 | N75: 36951.95 | O75: 282097000 | P75: =+(G75/O75)*100 -> 0.0021850179
A76: DAES | B76: Cooperativa de Ahorro y Crédito para el Desar | C76: 65677500-9 | D76: 2024 | E76: 10773.726 | F76: =0.3776*E76 -> 4068.1589 | G76: =+E76-F76 -> 6705.5671 | H76: 3985.462 | I76: =+G76-H76 -> 2720.1051 | J76: 397.145 | K76: 41370.8 | L76: 10163.465 | M76: 28369.726 | N76: 37253.149 | O76: 310681000 | P76: =+(G76/O76)*100 -> 0.0021583448
A77: DAES | B77: Cooperativa de Ahorro y Crédito Parinacoop Lt | C77: 65443640-1 | D77: 2017 | E77: 600.23495 | F77: =0.3776*E77 -> 226.64872 | G77: =+E77-F77 -> 373.58623 | H77: 221.11673 | I77: =+G77-H77 -> 152.4695 | J77: 80.089242 | K77: 4021.7865 | L77: 1242.8997 | M77: 2622.0789 | N77: 3124.2481 | O77: 179315000 | P77: =+(G77/O77)*100 -> 0.00020834076
A78: DAES | B78: Cooperativa de Ahorro y Crédito Parinacoop Lt | C78: 65443640-1 | D78: 2018 | E78: 595.6958 | F78: =0.3776*E78 -> 224.93473 | G78: =+E78-F78 -> 370.76106 | H78: 239.34734 | I78: =+G78-H78 -> 131.41373 | J78: 55.039586 | K78: 4078.931 | L78: 1349.3245 | M78: 2606.5928 | N78: 2860.2709 | O78: 189435000 | P78: =+(G78/O78)*100 -> 0.00019571941
A79: DAES | B79: Cooperativa de Ahorro y Crédito Parinacoop Lt | C79: 65443640-1 | D79: 2022 | E79: 557.86332 | F79: =0.3776*E79 -> 210.64919 | G79: =+E79-F79 -> 347.21413 | H79: 304.89667 | I79: =+G79-H79 -> 42.317456 | J79: 26.759331 | K79: 4649.9056 | L79: 1506.7359 | M79: 3129.8084 | N79: 3687.9281 | O79: 262954000 | P79: =+(G79/O79)*100 -> 0.00013204368
... A90: DAES | B90: Cooperativa de Ahorro y Crédito Solidaridad / | C90: 65085321-0 | D90: 2015 | E90: 17.866682 | F90: =0.3776*E90 -> 6.7464591 | G90: =+E90-F90 -> 11.120223 | H90: 12.108712 | I90: =+G90-H90 -> -0.98848912 | J90: -39.372531 | K90: 125.05902 | L90: 9.192584 | M90: 114.95387 | N90: 102.56495 | O90: 158623000 | P90: =+(G90/O90)*100 -> 7.0104732e-06
A91: DAES | B91: Cooperativa de Ahorro y Crédito Solidaridad / | C91: 65085321-0 | D91: 2016 | E91: 45.560436 | F91: =0.3776*E91 -> 17.203621 | G91: =+E91-F91 -> 28.356815 | H91: 25.143662 | I91: =+G91-H91 -> 3.2131534 | J91: -33.583428 | O91: 168765000 | P91: =+(G91/O91)*100 -> 1.6802545e-05
A92: DAES | B92: Cooperativa de Ahorro y Crédito Solidaridad / | C92: 65085321-0 | D92: 2017 | E92: 61.948441 | F92: =0.3776*E92 -> 23.391731 | G92: =+E92-F92 -> 38.55671 | H92: 32.888181 | I92: =+G92-H92 -> 5.6685287 | J92: -24.558802 | O92: 179315000 | P92: =+(G92/O92)*100 -> 2.1502222e-05
A93: DAES | B93: Cooperativa de Ahorro y Crédito Solidaridad / | C93: 65085321-0 | D93: 2023 | E93: 452.21339 | F93: =0.3776*E93 -> 170.75578 | G93: =+E93-F93 -> 281.45762 | H93: 201.0581 | I93: =+G93-H93 -> 80.39952 | J93: 54.090326 | K93: 1337.9666 | L93: 601.06946 | M93: 646.10522 | N93: 1234.66 | O93: 282097000 | P93: =+(G93/O93)*100 -> 9.9773346e-05
A94: DAES | B94: Cooperativa de Ahorro y Crédito Solidaridad / | C94: 65085321-0 | D94: 2024 | E94: 524.46467 | F94: =0.3776*E94 -> 198.03786 | G94: =+E94-F94 -> 326.42681 | H94: 230.39644 | I94: =+G94-H94 -> 96.030375 | J94: 87.44513 | K94: 1564.5809 | L94: 785.34231 | M94: 572.68151 | N94: 1473.8919 | O94: 310681000 | P94: =+(G94/O94)*100 -> 0.00010506816
A95: DAES | B95: Cooperativa de Ahorro y Crédito Talcahuano Lt | C95: 70013720-1 | D95: 2017 | E95: 273.17733 | F95: =0.3776*E95 -> 103.15176 | G95: =+E95-F95 -> 170.02557 | H95: 78.846155 | I95: =+G95-H95 -> 91.179416 | J95: 88.185051 | K95: 1535.064 | L95: 1501.9467 | M95: 1.748325 | N95: 1155.9157 | O95: 179315000 | P95: =+(G95/O95)*100 -> 9.4819492e-05
A96: DAES | B96: Cooperativa de Ahorro y Crédito Talcahuano Lt | C96: 70013720-1 | D96: 2023 | E96: 677.23194 | F96: =0.3776*E96 -> 255.72278 | G96: =+E96-F96 -> 421.50916 | H96: 108.19999 | I96: =+G96-H96 -> 313.30917 | J96: 277.95685 | K96: 3804.4688 | L96: 3746.9455 | M96: 0 | N96: 3420.1259 | O96: 282097000 | P96: =+(G96/O96)*100 -> 0.00014941994
A97: DAES | B97: Cooperativa de Ahorro y Crédito Talcahuano Lt | C97: 70013720-1 | D97: 2024 | E97: 722.32978 | F97: =0.3776*E97 -> 272.75172 | G97: =+E97-F97 -> 449.57805 | H97: 138.7573 | I97: =+G97-H97 -> 310.82075 | J97: 219.94931 | K97: 4210.4794 | L97: 3409.976 | M97: 756.57864 | N97: 3393.4499 | O97: 310681000 | P97: =+(G97/O97)*100 -> 0.00014470729
A98: DAES | B98: Cooperativa de Ahorro y Crédito Valles de Chi | C98: 65624290-6 | D98: 2018 | E98: 0.308227 | F98: =0.3776*E98 -> 0.11638652 | G98: =+E98-F98 -> 0.19184048 | H98: 0.112391 | I98: =+G98-H98 -> 0.079449485 | J98: 0.061937 | K98: 3.319625 | L98: 1.281879 | M98: 1.412597 | N98: 3.075634 | O98: 189435000 | P98: =+(G98/O98)*100 -> 1.0126982e-07
A99: DAES | B99: Cooperativa de Ahorro y Crédito Valles de Chi | C99: 65624290-6 | D99: 2019 | E99: 0.351286 | F99: =0.3776*E99 -> 0.13264559 | G99: =+E99-F99 -> 0.21864041 | H99: 0.126394 | I99: =+G99-H99 -> 0.092246406 | J99: 0.073942 | K99: 3.317151 | L99: 1.388231 | M99: 1.246578 | N99: 2.805438 | O99: 195548000 | P99: =+(G99/O99)*100 -> 1.1180907e-07
A100: DAES | B100: Cooperativa de Ahorro y Crédito Valles de Chi | C100: 65624290-6 | D100: 2020 | E100: 0.244807 | F100: =0.3776*E100 -> 0.092439123 | G100: =+E100-F100 -> 0.15236788 | H100: 0.125367 | I100: =+G100-H100 -> 0.027000877 | J100: 0.063537 | K100: 3.329772 | L100: 1.443248 | M100: 1.343456 | N100: 2.51964 | O100: 201307000 | P100: =+(G100/O100)*100 -> 7.5689309e-08
A101: DAES | B101: Cooperativa de Ahorro y Crédito Valles de Chi | C101: 65624290-6 | D101: 2021 | E101: 0.261336 | F101: =0.3776*E101 -> 0.098680474 | G101: =+E101-F101 -> 0.16265553 | H101: 0.133767 | I101: =+G101-H101 -> 0.028888526 | J101: 0.046878 | K101: 3.5809 | L101: 1.590547 | M101: 1.55537 | O101: 239556000 | P101: =+(G101/O101)*100 -> 6.7898749e-08
A102: DAES | B102: Cooperativa de Ahorro y Crédito Valles de Chi | C102: 65624290-6 | D102: 2022 | E102: 611.017 | F102: =0.3776*E102 -> 230.72002 | G102: =+E102-F102 -> 380.29698 | H102: 143.923 | I102: =+G102-H102 -> 236.37398 | J102: 7.701 | K102: 3455.324 | L102: 1903.929 | M102: 1350.662 | O102: 262954000 | P102: =+(G102/O102)*100 -> 0.00014462491
A103: DAES | B103: Cooperativa de Ahorro y Crédito Valles de Chi | C103: 65624290-6 | D103: 2023 | E103: 448.933 | F103: =0.3776*E103 -> 169.5171 | G103: =+E103-F103 -> 279.4159 | H103: 253.252 | I103: =+G103-H103 -> 26.163899 | J103: -223.799 | K103: 3312.891 | L103: 1686.759 | M103: 1420.897 | O103: 282097000 | P103: =+(G103/O103)*100 -> 9.9049582e-05
A104: DAES | B104: Cooperativa Macul Limitada | C104: 70777900-4 | D104: 2018 | E104: 101.41183 | F104: =0.3776*E104 -> 38.293107 | G104: =+E104-F104 -> 63.118724 | H104: 43.011158 | I104: =+G104-H104 -> 20.107566 | J104: -12.133134 | K104: 515.32727 | L104: 62.661435 | M104: 433.31794 | N104: 457.9254 | O104: 189435000 | P104: =+(G104/O104)*100 -> 3.3319462e-05
A105: DAES | B105: Cooperativa Unión y Patria | C105: 82835000-5 | D105: 2018 | E105: 2617.4222 | F105: =0.3776*E105 -> 988.33863 | G105: =+E105-F105 -> 1629.0836 | H105: 1127.8541 | I105: =+G105-H105 -> 501.22951 | J105: 276.86881 | K105: 13206.215 | N105: 11600.089 | O105: 189435000 | P105: =+(G105/O105)*100 -> 0.00085996969
A106: DAES | B106: Cooperativa Unión y Patria | C106: 82835000-5 | D106: 2022 | E106: 2631.3679 | F106: =0.3776*E106 -> 993.60452 | G106: =+E106-F106 -> 1637.7634 | H106: 1596.0623 | I106: =+G106-H106 -> 41.701072 | J106: -1269.9377 | K106: 13905.149 | L106: 6571.0612 | M106: 5127.6093 | N106: 11651.74 | O106: 262954000 | P106: =+(G106/O106)*100 -> 0.00062283266
A107: DAES | B107: Cooperativa Unión y Patria | C107: 82835000-5 | D107: 2023 | E107: 4050.8598 | F107: =0.3776*E107 -> 1529.6047 | G107: =+E107-F107 -> 2521.2552 | H107: 1590.6102 | I107: =+G107-H107 -> 930.64494 | J107: 139.98413 | K107: 16601.979 | L107: 7406.6066 | M107: 8892.5317 | N107: 13754.827 | O107: 282097000 | P107: =+(G107/O107)*100 -> 0.00089375469
A108: DAES | B108: Cooperativa Unión y Patria | C108: 82835000-5 | D108: 2024 | E108: 96.950816 | F108: =0.3776*E108 -> 36.608628 | G108: =+E108-F108 -> 60.342188 | H108: 1721.5857 | I108: =+G108-H108 -> -1661.2435 | J108: 554.22639 | K108: 17121.34 | L108: 7637.0951 | M108: 9371.5784 | N108: 14511.342 | O108: 310681000 | P108: =+(G108/O108)*100 -> 1.9422555e-05
A109: DAES | B109: Cooperlacar Ltda. | C109: 81189600-4 | D109: 2018 | E109: 267.82775 | F109: =0.3776*E109 -> 101.13176 | G109: =+E109-F109 -> 166.69599 | H109: 230.79574 | I109: =+G109-H109 -> -64.09975 | J109: -12.99656 | K109: 1227.9936 | L109: 1153.8 | M109: 52.136125 | N109: 628.99059 | O109: 189435000 | P109: =+(G109/O109)*100 -> 8.7996405e-05
A110: DAES | B110: Cooperlacar Ltda. | C110: 81189600-4 | D110: 2019 | E110: 277.1842 | F110: =0.3776*E110 -> 104.66475 | G110: =+E110-F110 -> 172.51945 | H110: 238.77118 | I110: =+G110-H110 -> -66.251738 | J110: 21.773688 | K110: 1299.2601 | L110: 1193.3909 | M110: 49.207566 | N110: 732.22318 | O110: 195548000 | P110: =+(G110/O110)*100 -> 8.822358e-05
A111: DAES | B111: Cooperlacar Ltda. | C111: 81189600-4 | D111: 2020 | E111: 295.69122 | F111: =0.3776*E111 -> 111.653 | G111: =+E111-F111 -> 184.03821 | H111: 213.26956 | I111: =+G111-H111 -> -29.231347 | J111: 25.565755 | K111: 1360.8137 | L111: 1263.1313 | M111: 47.910406 | N111: 795.74331 | O111: 201307000 | P111: =+(G111/O111)*100 -> 9.1421666e-05
...

Sheet 📁 Panel CMF
A1: PANEL DE DATOS — UNA FILA POR COOPERATIVA × AÑO
A2: Segmento | B2: Entidad | C2: RUT | D2: Año | E2: P1 (MM$) | F2: P2 (MM$) | G2: B1g (MM$) | H2: D1 (MM$) | I2: B2g (MM$) | J2: Rem (MM$) | K2: F2 (MM$) | L2: F4 (MM$) | M2: Activos (MM$) | N2: Patrimonio (MM$) | O2: PIB_MM | P2: Aporte (%)
A3: CMF | B3: AHORROCOOP | C3: 70.014.500-0 | D3: 2013 | E3: 6948.1 | F3: =0.3776*E3 -> 2623.6026 | G3: =+E3-F3 -> 4324.4974 | H3: 3146.5 | I3: =+G3-H3 -> 1177.9974 | J3: -1580.6 | K3: 20566.8 | L3: 25922 | M3: 32276.2 | N3: 11120.3 | O3: 136003000 | P3: =+(G3/O3)*100 -> 0.0031797074
A4: CMF | B4: AHORROCOOP | C4: 70.014.500-0 | D4: 2014 | E4: 5701.9 | F4: =0.3776*E4 -> 2153.0374 | G4: =+E4-F4 -> 3548.8626 | H4: 2930.6 | I4: =+G4-H4 -> 618.26256 | J4: -4951.7 | K4: 20696.8 | L4: 19610.9 | M4: 27036.7 | N4: 5788.6 | O4: 144706000 | P4: =+(G4/O4)*100 -> 0.002452464
A5: CMF | B5: AHORROCOOP | C5: 70.014.500-0 | D5: 2015 | E5: 5838.4 | F5: =0.3776*E5 -> 2204.5798 | G5: =+E5-F5 -> 3633.8202 | H5: 2625.4 | I5: =+G5-H5 -> 1008.4202 | J5: -1295.7 | K5: 23133.7 | L5: 22045.1 | M5: 28433 | N5: 4742.8 | O5: 158623000 | P5: =+(G5/O5)*100 -> 0.0022908533
A6: CMF | B6: AHORROCOOP | C6: 70.014.500-0 | D6: 2016 | E6: 7215 | F6: =0.3776*E6 -> 2724.384 | G6: =+E6-F6 -> 4490.616 | H6: 2822.3 | I6: =+G6-H6 -> 1668.316 | J6: 360.1 | K6: 27470.5 | L6: 26592.6 | M6: 33393.5 | N6: 5265.1 | O6: 168765000 | P6: =+(G6/O6)*100 -> 0.0026608693
A7: CMF | B7: AHORROCOOP | C7: 70.014.500-0 | D7: 2017 | E7: 5915 | F7: =0.3776*E7 -> 2233.504 | G7: =+E7-F7 -> 3681.496 | H7: 2687 | I7: =+G7-H7 -> 994.496 | J7: 488 | K7: 29778 | L7: 35242 | M7: 37342 | N7: 4357 | O7: 179315000 | P7: =+(G7/O7)*100 -> 0.0020530887
A8: CMF | B8: AHORROCOOP | C8: 70.014.500-0 | D8: 2018 | E8: 7611 | F8: =0.3776*E8 -> 2873.9136 | G8: =+E8-F8 -> 4737.0864 | H8: 3158 | I8: =+G8-H8 -> 1579.0864 | J8: 1661 | K8: 35345 | L8: 29764 | M8: 42902 | N8: 6131 | O8: 189435000 | P8: =+(G8/O8)*100 -> 0.0025006395
A9: CMF | B9: AHORROCOOP | C9: 70.014.500-0 | D9: 2019 | E9: 8768 | F9: =0.3776*E9 -> 3310.7968 | G9: =+E9-F9 -> 5457.2032 | H9: 3350 | I9: =+G9-H9 -> 2107.2032 | J9: 2112 | K9: 40476 | L9: 40909 | M9: 50812 | N9: 8617 | O9: 195548000 | P9: =+(G9/O9)*100 -> 0.0027907231
A10: CMF | B10: AHORROCOOP | C10: 70.014.500-0 | D10: 2020 | E10: 8612 | F10: =0.3776*E10 -> 3251.8912 | G10: =+E10-F10 -> 5360.1088 | H10: 3550 | I10: =+G10-H10 -> 1810.1088 | J10: 1538 | K10: 44291 | L10: 40506 | M10: 54171 | N10: 10150 | O10: 201307000 | P10: =+(G10/O10)*100 -> 0.002662654
A11: CMF | B11: AHORROCOOP | C11: 70.014.500-0 | D11: 2021 | E11: 9254 | F11: =0.3776*E11 -> 3494.3104 | G11: =+E11-F11 -> 5759.6896 | H11: 3836 | I11: =+G11-H11 -> 1923.6896 | J11: 3542 | K11: 42108 | L11: 48654 | M11: 58971 | N11: 12549 | O11: 239556000 | P11: =+(G11/O11)*100 -> 0.0024043187
A12: CMF | B12: AHORROCOOP | C12: 70.014.500-0 | D12: 2022 | E12: 11783 | F12: =0.3776*E12 -> 4449.2608 | G12: =+E12-F12 -> 7333.7392 | H12: 4794 | I12: =+G12-H12 -> 2539.7392 | J12: 3552 | K12: 48169 | L12: 60155 | M12: 68830 | N12: 15234 | O12: 262954000 | P12: =+(G12/O12)*100 -> 0.0027889818
A13: CMF | B13: AHORROCOOP | C13: 70.014.500-0 | D13: 2023 | E13: 11267 | F13: =0.3776*E13 -> 4254.4192 | G13: =+E13-F13 -> 7012.5808 | H13: 5515 | I13: =+G13-H13 -> 1497.5808 | J13: 1623 | K13: 56129 | L13: 70304 | M13: 77988 | N13: 17876 | O13: 282097000 | P13: =+(G13/O13)*100 -> 0.0024858757
A14: CMF | B14: AHORROCOOP | C14: 70.014.500-0 | D14: 2024 | E14: 13928 | F14: =0.3776*E14 -> 5259.2128 | G14: =+E14-F14 -> 8668.7872 | H14: 6309 | I14: =+G14-H14 -> 2359.7872 | J14: 1702 | K14: 67995 | L14: 79312 | M14: 91740 | N14: 19676 | O14: 310681000 | P14: =+(G14/O14)*100 -> 0.0027902534
... A23: CMF | B23: CAPUAL | C23: 70.013.730-9 | D23: 2020 | E23: 11712 | F23: =0.3776*E23 -> 4422.4512 | G23: =+E23-F23 -> 7289.5488 | H23: 4386 | I23: =+G23-H23 -> 2903.5488 | J23: 1751 | K23: 79756 | L23: 77555 | M23: 108301 | N23: 22393 | O23: 201307000 | P23: =+(G23/O23)*100 -> 0.0036211104
A24: CMF | B24: CAPUAL | C24: 70.013.730-9 | D24: 2021 | E24: 11712 | F24: =0.3776*E24 -> 4422.4512 | G24: =+E24-F24 -> 7289.5488 | H24: 4386 | I24: =+G24-H24 -> 2903.5488 | J24: 1751 | K24: =3638+75342 -> 78980 | L24: 71597 | M24: 111602 | N24: 25353 | O24: 239556000 | P24: =+(G24/O24)*100 -> 0.0030429414
A25: CMF | B25: CAPUAL | C25: 70.013.730-9 | D25: 2022 | E25: 12492 | F25: =0.3776*E25 -> 4716.9792 | G25: =+E25-F25 -> 7775.0208 | H25: 4485 | I25: =+G25-H25 -> 3290.0208 | J25: 3725 | K25: 61270 | L25: 78901 | M25: 95214 | N25: 25987 | O25: 262954000 | P25: =+(G25/O25)*100 -> 0.0029567988
A26: CMF | B26: CAPUAL | C26: 70.013.730-9 | D26: 2023 | E26: 14238 | F26: =0.3776*E26 -> 5376.2688 | G26: =+E26-F26 -> 8861.7312 | H26: 4961 | I26: =+G26-H26 -> 3900.7312 | J26: 4496 | K26: 65955 | L26: 82462 | M26: 100368 | N26: 28864 | O26: 282097000 | P26: =+(G26/O26)*100 -> 0.0031413773
A27: CMF | B27: CAPUAL | C27: 70.013.730-9 | D27: 2024 | E27: 15425 | F27: =0.3776*E27 -> 5824.48 | G27: =+E27-F27 -> 9600.52 | H27: 5027 | I27: =+G27-H27 -> 4573.52 | J27: 4017 | K27: 68531 | L27: 88322 | M27: 106851 | N27: 31435 | O27: 310681000 | P27: =+(G27/O27)*100 -> 0.0030901536
A28: CMF | B28: CAPUAL | C28: 70.013.730-9 | D28: 2025 | E28: 17134 | F28: =0.3776*E28 -> 6469.7984 | G28: =+E28-F28 -> 10664.202 | H28: 5299 | I28: =+G28-H28 -> 5365.2016 | J28: 4569 | K28: 72744 | L28: 95212 | M28: 113551 | N28: 33591 | O28: 339978000 | P28: =+(G28/O28)*100 -> 0.0031367328
A29: CMF | B29: CONFIA Ltda. | C29: 70.032.300-0 | D29: 2013 | E29: 3166.3 | F29: =0.3776*E29 -> 1195.5949 | G29: =+E29-F29 -> 1970.7051 | H29: 685.6 | I29: =+G29-H29 -> 1285.1051 | J29: 944.3 | K29: 1857.8 | L29: 16447.2 | M29: 19787.8 | N29: 17582 | O29: 136003000 | P29: =+(G29/O29)*100 -> 0.0014490159
A30: CMF | B30: CONFIA Ltda. | C30: 70.032.300-0 | D30: 2014 | E30: 3119.1 | F30: =0.3776*E30 -> 1177.7722 | G30: =+E30-F30 -> 1941.3278 | H30: 816.6 | I30: =+G30-H30 -> 1124.7278 | J30: 511.6 | K30: 2328.6 | L30: 16576 | M30: 22495.3 | N30: 19900.4 | O30: 144706000 | P30: =+(G30/O30)*100 -> 0.0013415669
A31: CMF | B31: CONFIA Ltda. | C31: 70.032.300-0 | D31: 2015 | E31: 3273.9 | F31: =0.3776*E31 -> 1236.2246 | G31: =+E31-F31 -> 2037.6754 | H31: 956.6 | I31: =+G31-H31 -> 1081.0754 | J31: 565.9 | K31: 4083.7 | L31: 20631.5 | M31: 27353.4 | N31: 23051.2 | O31: 158623000 | P31: =+(G31/O31)*100 -> 0.0012846027
A32: CMF | B32: CONFIA Ltda. | C32: 70.032.300-0 | D32: 2016 | E32: 3715.7 | F32: =0.3776*E32 -> 1403.0483 | G32: =+E32-F32 -> 2312.6517 | H32: 1094.7 | I32: =+G32-H32 -> 1217.9517 | J32: 244.3 | K32: 4495.6 | L32: 23207.8 | M32: 30954.9 | N32: 26236.8 | O32: 168765000 | P32: =+(G32/O32)*100 -> 0.0013703384
A33: CMF | B33: CONFIA Ltda. | C33: 70.032.300-0 | D33: 2017 | E33: 4089 | F33: =0.3776*E33 -> 1544.0064 | G33: =+E33-F33 -> 2544.9936 | H33: 1225 | I33: =+G33-H33 -> 1319.9936 | J33: 1314 | K33: 6480 | L33: 29089 | M33: 34005 | N33: 26543 | O33: 179315000 | P33: =+(G33/O33)*100 -> 0.0014192865
A34: CMF | B34: CONFIA Ltda. | C34: 70.032.300-0 | D34: 2018 | E34: 4045 | F34: =0.3776*E34 -> 1527.392 | G34: =+E34-F34 -> 2517.608 | H34: 1281 | I34: =+G34-H34 -> 1236.608 | J34: 1378 | K34: 9665 | L34: 25865 | M34: 39059 | N34: 27097 | O34: 189435000 | P34: =+(G34/O34)*100 -> 0.0013290089
A35: CMF | B35: CONFIA Ltda. | C35: 70.032.300-0 | D35: 2019 | E35: 8347 | F35: =0.3776*E35 -> 3151.8272 | G35: =+E35-F35 -> 5195.1728 | H35: 1434 | I35: =+G35-H35 -> 3761.1728 | J35: 1374 | K35: 13010 | L35: 28952 | M35: 40357 | N35: 27770 | O35: 195548000 | P35: =+(G35/O35)*100 -> 0.0026567251
A36: CMF | B36: CONFIA Ltda. | C36: 70.032.300-0 | D36: 2020 | E36: 11592 | F36: =0.3776*E36 -> 4377.1392 | G36: =+E36-F36 -> 7214.8608 | H36: 4165 | I36: =+G36-H36 -> 3049.8608 | J36: 1642 | K36: 14504 | L36: 29978 | M36: 42356 | N36: 28911 | O36: 201307000 | P36: =+(G36/O36)*100 -> 0.0035840089
A37: CMF | B37: CONFIA Ltda. | C37: 70.032.300-0 | D37: 2021 | E37: 3067 | F37: =0.3776*E37 -> 1158.0992 | G37: =+E37-F37 -> 1908.9008 | H37: 1368 | I37: =+G37-H37 -> 540.9008 | J37: 222 | K37: =13086+222 -> 13308 | L37: 29278 | M37: 42374 | N37: 28679 | O37: 239556000 | P37: =+(G37/O37)*100 -> 0.0007968495
A38: CMF | B38: CONFIA Ltda. | C38: 70.032.300-0 | D38: 2022 | E38: 3573 | F38: =0.3776*E38 -> 1349.1648 | G38: =+E38-F38 -> 2223.8352 | H38: 1423.8 | I38: =+G38-H38 -> 800.0352 | J38: 547 | K38: 10728 | L38: 35104 | M38: 40571 | N38: 32934 | O38: 262954000 | P38: =+(G38/O38)*100 -> 0.00084571263
A39: CMF | B39: CONFIA Ltda. | C39: 70.032.300-0 | D39: 2023 | E39: 4201 | F39: =0.3776*E39 -> 1586.2976 | G39: =+E39-F39 -> 2614.7024 | H39: 1710.6 | I39: =+G39-H39 -> 904.1024 | J39: 416 | K39: 13222 | L39: 38650 | M39: 49796 | N39: 31082 | O39: 282097000 | P39: =+(G39/O39)*100 -> 0.00092688061
A40: CMF | B40: CONFIA Ltda. | C40: 70.032.300-0 | D40: 2024 | E40: 5930 | F40: =0.3776*E40 -> 2239.168 | G40: =+E40-F40 -> 3690.832 | H40: 3030 | I40: =+G40-H40 -> 660.832 | J40: -828 | K40: 15822 | L40: 52786 | M40: 58304 | N40: 31289 | O40: 310681000 | P40: =+(G40/O40)*100 -> 0.0011879812
A41: CMF | B41: CONFIA Ltda. | C41: 70.032.300-0 | D41: 2025 | E41: 7250 | F41: =0.3776*E41 -> 2737.6 | G41: =+E41-F41 -> 4512.4 | H41: 2848.2 | I41: =+G41-H41 -> 1664.2 | J41: 853 | K41: 23316 | L41: 57185 | M41: 62695 | N41: 31905 | O41: 339978000 | P41: =+(G41/O41)*100 -> 0.0013272624
A42: CMF | B42: Coocretal | C42: 70.011.650-5 | D42: 2013 | E42: 3819.8 | F42: =0.3776*E42 -> 1442.3565 | G42: =+E42-F42 -> 2377.4435 | H42: 1771.9 | I42: =+G42-H42 -> 605.54352 | J42: -446.8 | K42: 7217.6 | L42: 13354.8 | M42: 16980.1 | N42: 7794.1 | O42: 136003000 | P42: =+(G42/O42)*100 -> 0.0017480817
A43: CMF | B43: Coocretal | C43: 70.011.650-5 | D43: 2014 | E43: 3415.5 | F43: =0.3776*E43 -> 1289.6928 | G43: =+E43-F43 -> 2125.8072 | H43: 1605.6 | I43: =+G43-H43 -> 520.2072 | J43: -267.8 | K43: 7728.9 | L43: 12100.4 | M43: 15653.3 | N43: 7501.2 | O43: 144706000 | P43: =+(G43/O43)*100 -> 0.0014690526
A44: CMF | B44: Coocretal | C44: 70.011.650-5 | D44: 2015 | E44: 3276.4 | F44: =0.3776*E44 -> 1237.1686 | G44: =+E44-F44 -> 2039.2314 | H44: 1827.3 | I44: =+G44-H44 -> 211.93136 | J44: -424.1 | K44: 7292.3 | L44: 12456.7 | M44: 14763.8 | N44: 7272.6 | O44: 158623000 | P44: =+(G44/O44)*100 -> 0.0012855837
A45: CMF | B45: Coocretal | C45: 70.011.650-5 | D45: 2016 | E45: 3389.2 | F45: =0.3776*E45 -> 1279.7619 | G45: =+E45-F45 -> 2109.4381 | H45: 1658 | I45: =+G45-H45 -> 451.43808 | J45: 123.3 | K45: 7939.6 | L45: 13557.6 | M45: 15715.4 | N45: 7590.4 | O45: 168765000 | P45: =+(G45/O45)*100 -> 0.0012499263
A46: CMF | B46: Coocretal | C46: 70.011.650-5 | D46: 2017 | E46: 3458 | F46: =0.3776*E46 -> 1305.7408 | G46: =+E46-F46 -> 2152.2592 | H46: 1664 | I46: =+G46-H46 -> 488.2592 | J46: 145 | K46: 8045 | L46: 13864 | M46: 17021 | N46: 8617 | O46: 179315000 | P46: =+(G46/O46)*100 -> 0.0012002672
A47: CMF | B47: Coocretal | C47: 70.011.650-5 | D47: 2018 | E47: 3218 | F47: =0.3776*E47 -> 1215.1168 | G47: =+E47-F47 -> 2002.8832 | H47: 1736 | I47: =+G47-H47 -> 266.8832 | J47: -833 | K47: 8359 | L47: 12566 | M47: 16872 | N47: 7764 | O47: 189435000 | P47: =+(G47/O47)*100 -> 0.0010572931
A48: CMF | B48: Coocretal | C48: 70.011.650-5 | D48: 2019 | E48: 2805 | F48: =0.3776*E48 -> 1059.168 | G48: =+E48-F48 -> 1745.832 | H48: 1803 | I48: =+G48-H48 -> -57.168 | J48: -628 | K48: 8203 | L48: 11034 | M48: 16086 | N48: 7115 | O48: 195548000 | P48: =+(G48/O48)*100 -> 0.00089278949
A49: CMF | B49: Coocretal | C49: 70.011.650-5 | D49: 2020 | E49: 1915 | F49: =0.3776*E49 -> 723.104 | G49: =+E49-F49 -> 1191.896 | H49: 1831 | I49: =+G49-H49 -> -639.104 | J49: -1361 | K49: 6067 | L49: 8931 | M49: 15029 | N49: 6480 | O49: 201307000 | P49: =+(G49/O49)*100 -> 0.00059207877
... A93: CMF | B93: Oriencoop Ltda. | C93: 70.017.640-3 | D93: 2025 | E93: 27346 | F93: =0.3776*E93 -> 10325.85 | G93: =+E93-F93 -> 17020.15 | H93: 9456 | I93: =+G93-H93 -> 7564.1504 | J93: 5114 | K93: 105272 | L93: 118724 | M93: 147185 | N93: 36311 | O93: 339978000 | P93: =+(G93/O93)*100 -> 0.0050062505

Sheet 🗺️ Registro CAC
A1: REGISTRO UNIVERSO CAC — FUENTE: DAES + SII + CMF
A2: RUT | B2: Razón Social | C2: Región | D2: Estado | E2: Trabajadores SII | F2: Tramo Ventas SII | G2: Empleados CMF | H2: Oficinas CMF
A3: 82355700-0 | B3: COOPERATIVA AGRICOLA PROFESOR JUAN NOE CREVANI LTDA. | C3: REGIÓN DE ARICA Y PARINACOTA | D3: Vigente | E3: 7 | F3: 5
A4: 81569600-K | B4: FEDERACION NACIONAL DE COOPERATIVAS ELECTRICAS LTDA. FENACOPEL LTDA. | C4: REGIÓN METROPOLITANA | D4: Vigente | E4: 12 | F4: 7
A5: 70000760-K | B5: COOPERATIVA DE VIVIENDA Y SERVICIOS HABITACIONALES SIGLO VEINTE LTDA. | C5: REGIÓN METROPOLITANA | D5: Vigente | E5: 0 | F5: 1
A6: 82835000-5 | B6: COOPERATIVA DE AHORRO Y CREDITO UNION Y PATRIA LIMITADA | C6: REGIÓN METROPOLITANA | D6: Vigente | E6: 56 | F6: 10
A7: 70018260-6 | B7: COOPERATIVA DE INVERSIONES ELECTROCOOP TEMUCO LIMITADA | C7: REGIÓN DE LA ARAUCANÍA | D7: Vigente | E7: 0 | F7: 11
A8: 81935800-1 | B8: COOPERATIVA CAMPESINA CHOL CHOL LTDA. | C8: REGIÓN DE LA ARAUCANÍA | D8: Vigente | E8: 40 | F8: 3
A9: 82424000-0 | B9: INSTITUTO CHILENO DE EDUCACION COOPERATIVA | C9: REGIÓN METROPOLITANA | D9: Vigente | E9: 0 | F9: 2
A10: 70625000-K | B10: COOPERATIVA DE VIVIENDA Y SERVICIOS HABITACIONALES COLINA DE ORO LIMITADA | C10: REGIÓN DE VALPARAISO | D10: Vigente | E10: 1 | F10: 1
A11: 70002770-8 | B11: COOPERATIVA DE SERVICIO Y PRESTAMO IDIEM UNIVERSIDAD DE CHILE LTDA | C11: REGIÓN METROPOLITANA | D11: Vigente | E11: 0 | F11: 1
A12: 70777900-4 | B12: COOPERATIVA DE AHORRO Y CREDITO MACUL LTDA. | C12: REGIÓN METROPOLITANA | D12: Vigente | E12: 2 | F12: 1
A13: 70487300-K | B13: COOPERATIVA AGRICOLA AGRUPACION DE PEQUEÑOS CHACAREROS DE CHILE LIMITADA | C13: REGIÓN METROPOLITANA | D13: Vigente | E13: 1 | F13: 3
A14: 83990500-9 | B14: COOPERATIVA DE AHORRO Y CRÉDITO DREVES LIMITADA | C14: REGIÓN DE LA ARAUCANÍA | D14: Vigente | E14: 0 | F14: 1
A15: 82877300-3 | B15: COOPERATIVA DE SERVICIOS Y TRANSPORTES EXPRESOS VIÑA DEL MAR LTDA. | C15: REGIÓN DE VALPARAISO | D15: Vigente | E15: 0 | F15: 3
A16: 70286300-7 | B16: COOPERATIVA DE AHORRO Y CREDITO NACIONAL PARA LA FAMILIA LIMITADA | C16: REGIÓN DE VALPARAISO | D16: Vigente | E16: 103 | F16: 10 | G16: 139 | H16: 9
A17: 70019910-K | B17: COOPERATIVA CAMPESINA SAN NICOLAS DE HIJUELAS LTDA. | C17: REGIÓN DE VALPARAISO | D17: Vigente | E17: 0 | F17: 1
A18: 70905600-K | B18: COOPERATIVA DE SERVICIOS DE PRESTAMOS SOLIDARIOS LORENZO ARENAS LTDA. | C18: REGIÓN DEL BÍO-BÍO | D18: Vigente | E18: 0 | F18: 1
A19: 70704000-9 | B19: COOPERATIVA CAMPESINA CHILLAN VIEJO LIMITADA | C19: REGIÓN DE ÑUBLE | D19: Vigente | E19: 0 | F19: 1
A20: 81836800-3 | B20: COOPERATIVA DE AHORRO, CREDITO Y SERVICIOS FINANCIEROS AHORROCOOP DIEGO PORTALES LIMITADA. | C20: REGIÓN METROPOLITANA | D20: Vigente | E20: 217 | F20: 11 | G20: 194 | H20: 7
A21: 82706600-1 | B21: SOCIEDAD COOPERATIVA PORTEÑA DE CONSUMOS Y SERVICIOS LIMITADA | C21: REGIÓN DE VALPARAISO | D21: Vigente | E21: 0 | F21: 1
A22: 70816600-6 | B22: COOPERATIVA DE AHORRO Y CREDITO SUBOFICIAL MAYOR DE CARABINEROS R ERNESTO LAVANDEROS CARRILLO LIMITADA | C22: REGIÓN METROPOLITANA | D22: Vigente | E22: 10 | F22: 1
A23: 82000200-8 | B23: COOPERATIVA AGRICOLA Y LECHERA BIOBIO LTDA. | C23: REGIÓN DEL BÍO-BÍO | D23: Vigente | E23: 0 | F23: 1
A24: 81805700-8 | B24: COOPERATIVA AGRICOLA CONTROL PISQUERO DE ELQUI Y LIMARI LIMITADA | C24: REGIÓN DE COQUIMBO | D24: Vigente | E24: 87 | F24: 11
A25: 70543100-0 | B25: COOPERATIVA DE SERVICIOS LIBERACION | C25: REGIÓN METROPOLITANA | D25: Vigente | E25: 0 | F25: 1
A26: 81242500-5 | B26: COOPERATIVA DE CONSUMOS CARABINEROS DE CHILE LIMITADA | C26: REGIÓN METROPOLITANA | D26: Vigente | E26: 405 | F26: 12
A27: 70405200-6 | B27: COOPERATIVA DE AGUA POTABLE ALCANTARILLADO Y SANEAMIENTO AMBIENTAL DE LA COMUNA DE SAN FABIÁN LIMITADA | C27: REGIÓN DE ÑUBLE | D27: Vigente | E27: 11 | F27: 7
A28: 76493461-k | B28: COOPERATIVA CAMPESINA CUNCUMEN LTDA. | C28: REGIÓN DE VALPARAISO | D28: Vigente | E28: 0 | F28: 3
A29: 82021300-9 | B29: COOPERATIVA CAMPESINA FAJA MAISAN LTDA. | C29: REGIÓN DE LA ARAUCANÍA | D29: Vigente | E29: 1 | F29: 6
A30: 84666200-6 | B30: COOPERATIVA DE SERVICIO SANITARIO RURAL AGUA POTABLE, Y ALCANTARILLADO ARTIFICIO DE CABILDO LTDA | C30: REGIÓN DE VALPARAISO | D30: Vigente | E30: 6 | F30: 5
A31: 81209700-8 | B31: COOPERATIVA AGRICOLA Y LECHERA FRUTILLAR LIMITADA | C31: REGIÓN DE LOS LAGOS | D31: Vigente | E31: 20 | F31: 7
A32: 70227100-2 | B32: COOPERATIVA DE SERVICIO DE AGUA POTABLE, ALCANTARILLADO Y SANEAMIENTO AMBIENTAL RAU LTDA | C32: REGIÓN DEL MAULE | D32: Vigente | E32: 20 | F32: 7
... A84: 71283200-2 | B84: COOPERATIVA DE SERVICIO DE ABASTECIMIENTO DE AGUA POTABLE, ALCANTARILLADO Y SANEAMIENTO AMBIENTAL RASTROJOS LIMITADA | C84: REGIÓN DEL LIBERTADOR GENERAL BERNARDO O HIGGINS | D84: Vigente | E84: 6 | F84: 5
A85: 82878900-7 | B85: COOPERATIVA DE AHORRO Y CREDITO COOPEUCH | C85: REGIÓN METROPOLITANA | D85: Vigente | E85: 2265 | F85: 13 | G85: 2064 | H85: 78
A86: 81094100-6 | B86: COOPERATIVA AGRICOLA Y LECHERA DE LA UNION LIMITADA | C86: REGIÓN DE LOS RÍOS | D86: Vigente | E86: 1628 | F86: 13
A87: 65098715-2 | B87: COOPERATIVA AGRICOLA DE COLONIZACION LA RINCONADA | C87: REGIÓN DEL LIBERTADOR GENERAL BERNARDO O HIGGINS | D87: Vigente | E87: 0 | F87: 1
A88: 83908800-0 | B88: SOCIEDAD COOPERATIVA DE AHORRO Y CREDITO MAULE | C88: REGIÓN DEL MAULE | D88: Vigente | E88: 12 | F88: 6
A89: 82787300-4 | B89: COOPERATIVA AGRICOLA E INDUSTRIALIZADORA DE CERDOS RELONCAVI LTDA. | C89: REGIÓN DE LOS LAGOS | D89: Vigente | E89: 0 | F89: 3
A90: 70006870-6 | B90: COOPERATIVA DE SERVICIOS DE VERANEO LONQUIMAY LTDA. | C90: REGIÓN DE VALPARAISO | D90: Vigente | E90: 7 | F90: 5
A91: 70482300-2 | B91: COOPERATIVA DE SERVICIOS DE ABASTECIMIENTO Y DISTRIBUCIÓN DE AGUA POTABLE, ALCANTARILLADO Y SANEAMIENTO AMBIENTAL EL RULO MILLAHUE LIMITADA | C91: REGIÓN DEL LIBERTADOR GENERAL BERNARDO O HIGGINS | D91: Vigente | E91: 6 | F91: 5
A92: 82262700-5 | B92: COOPERATIVA AGRICOLA DE PRODUCTORES DE BIO BIO LIMITADA | C92: REGIÓN DEL BÍO-BÍO | D92: Vigente | E92: 9 | F92: 8
A93: 82101500-6 | B93: COOPERATIVA CAMPESINA EL CORAZON LIMITADA | C93: REGIÓN DEL MAULE | D93: Vigente | E93: 0 | F93: 4
A94: 84665900-5 | B94: COOPERATIVA DE SERVICIO DE ABASTECIMIENTO Y DISTRIBUCION DE AGUA POTABLE, ALCANTARILLADO Y SANEAMIENTO AMBIENTAL LA PUNTILLA PUEBLO DE INDIOS LIMITADA. | C94: REGIÓN DEL LIBERTADOR GENERAL BERNARDO O HIGGINS | D94: Vigente | E94: 7 | F94: 5
A95: 81915900-9 | B95: COOPERATIVA DE SERVICIOS DE DUEÑOS DE AUTOBUSES DE CAUTIN LIMITADA | C95: REGIÓN DE LA ARAUCANÍA | D95: Vigente | E95: 1 | F95: 10
A96: 84526700-6 | B96: COOPERATIVA DE SERVICIO DE ABASTECIMIENTO Y DISTRIBUCION DE AGUA POTABLE ALCANTARILLADO Y SANEAMIENTO AMBIENTAL DE RAPEL LTDA. | C96: REGIÓN DEL LIBERTADOR GENERAL BERNARDO O HIGGINS | D96: Vigente | E96: 4 | F96: 5
A97: 85349100-4 | B97: COOPERATIVA CAMPESINA TULAHUEN LTDA. | C97: REGIÓN DE COQUIMBO | D97: Vigente | E97: 0 | F97: 4
... A180: 84527500-9 | B180: COOPERATIVA DE SERVICIO SANITARIOS LOS MAITENES | C180: REGIÓN DE VALPARAISO | D180: Vigente | E180: 21 | F180: 7
A181: 70017860-9 | B181: COOPERATIVA DE AHORRO Y CRÉDITO EL DETALLISTA LIMITADA | C181: REGIÓN METROPOLITANA | D181: Vigente | E181: 322 | F181: 11 | G181: 278 | H181: 29
A182: 70052100-1 | B182: COOPERATIVA HUERTOS FAMILIARES DE POLPAICO LIMITADA | C182: REGIÓN METROPOLITANA | D182: Vigente | E182: 1 | F182: 6
A183: 70000770-7 | B183: COOPERATIVA DE AHORRO Y CREDITO ISLA DE MAIPO LIMITADA | C183: REGIÓN METROPOLITANA | D183: Vigente | E183: 16 | F183: 1
A184: 84662500-3 | B184: COOPERATIVA DE SERVICIOS DE ABASTECIMIENTO Y DISTRIBUCION DE AGUA POTABLE ALCANTARILLADO Y SANEAMIENTO AMBIENTAL SANTA MARGARITA | C184: REGIÓN METROPOLITANA | D184: Vigente | E184: 16 | F184: 7
A185: 70013720-1 | B185: COOPERATIVA DE AHORRO Y CREDITO TALCAHUANO LIMITADA | C185: REGIÓN DEL BÍO-BÍO | D185: Vigente | E185: 8 | F185: 7
A186: 70066100-8 | B186: COOPERATIVA CAMPESINA PINTUE (COCAPIN) LIMITADA | C186: REGIÓN METROPOLITANA | D186: Vigente | E186: 0 | F186: 1
A187: 70019970-3 | B187: COOPERATIVA DE VACACIONES EL TABITO LIMITADA | C187: REGIÓN DE VALPARAISO | D187: Vigente | E187: 20 | F187: 4
A188: 84801300-5 | B188: COOPERATIVA DE SERVICIO DE ABASTECIMIENTO Y DISTRIBUCIÓN DE AGUA POTABLE, ALCANTARILLADO Y SANEAMIENTO AMBIENTAL JUAN NUÑEZ VALENZUELA LTDA. | C188: REGIÓN DEL LIBERTADOR GENERAL BERNARDO O HIGGINS | D188: Vigente | E188: 8 | F188: 5
A189: 70400400-1 | B189: COOPERATIVA DE VIVIENDA Y SERVICIOS HABITACIONALES EL ROTO CHILENO LIMITADA | C189: REGIÓN METROPOLITANA | D189: Vigente | E189: 0 | F189: 1
A190: 81863900-7 | B190: COOPERATIVA DE AHORRO Y CREDITO NORTE GRANDE LIMITADA | C190: REGIÓN DE ANTOFAGASTA | D190: Vigente | E190: 47 | F190: 9
A191: 77595810-3 | B191: COOPERATIVA AGRICOLA DE COLONIZACION CHUCHIÑI LIMITADA | C191: REGIÓN DE COQUIMBO | D191: Vigente | E191: 0 | F191: 4
A192: 70287900-0 | B192: COOPERATIVA DE ABASTECIMIENTO DE ENERGIA ELECTRICA CURICO LIMITADA | C192: REGIÓN DEL MAULE | D192: Vigente | E192: 53 | F192: 11
A193: 80237700-2 | B193: COOPERATIVA DE CONSUMO DE ENERGIA ELECTRICA CHILLAN LIMITADA | C193: REGIÓN DE ÑUBLE | D193: Vigente | E193: 288 | F193: 13
... A290: 65790340-K | B290: COOPERATIVA DE SERVICIO DE AGUA POTABLE, ALCANTARILLADO Y SANEAMIENTO AMBIENTAL MARIPOSAS LTDA. | C290: REGIÓN DEL MAULE | D290: Vigente | E290: 4 | F290: 6
A291: 70010920-8 | B291: COOPERATIVA DE AHORRO Y CREDITO ORIENTE LIMITADA | C291: REGIÓN DEL MAULE | D291: Vigente | E291: 332 | F291: 12 | G291: 336 | H291: 21
A292: 65810660-0 | B292: COOPERATIVA DE SERVICIOS SANITARIOS CARELMAPU LIMITADA | C292: REGIÓN DE LOS LAGOS | D292: Vigente | E292: 6 | F292: 6
A293: 65839250-6 | B293: COOPERATIVA DE CONSUMO ÑGEN DE CURARREHUE | C293: REGIÓN DE LA ARAUCANÍA | D293: Vigente | E293: 0 | F293: 3
A294: 65826510-5 | B294: COOPERATIVA DE SERVICIO DE ABASTECIMIENTO Y DISTRIBUCION DE AGUA POTABLE, ALCANTARILLADO Y SANEAMIENTO AMBIENTAL GACITUA. | C294: REGIÓN METROPOLITANA | D294: Vigente | E294: 4 | F294: 5
A295: 76845590-2 | B295: COOPERATIVA DE SERVICIOS DE TRABAJADORES DE EDYCE "COOTREDY" | C295: REGIÓN DEL BÍO-BÍO | D295: Vigente | E295: 0 | F295: 1
A296: 65269340-7 | B296: COOPERATIVA DE SERVICIO DE AGUA POTABLE Y ALCANTARILLADO SANTA OLGA-LOS AROMOS-CRUCE EMPEDRADO LIMITADA | C296: REGIÓN DEL MAULE | D296: Vigente | E296: 7 | F296: 5
A297: 65834380-7 | B297: COOPERATIVA DE AGUA POTABLE RURAL EL BOSQUE DE PANIMAVIDA LTDA. | C297: REGIÓN DEL MAULE | D297: Vigente | E297: 2 | F297: 4
A298: 65825930-K | B298: COOPERATIVA DE AGUA POTABLE RURAL FLOR MARÍA LTDA. | C298: REGIÓN DEL MAULE | D298: Vigente | E298: 4 | F298: 5
A299: 76828890-9 | B299: COOPERATIVA DE SERVICIOS DE AGUA POTABLE Y ALCANTARILLADO LAS ENCINAS | C299: REGIÓN DEL MAULE | D299: Vigente | E299: 3 | F299: 5
A300: 76866660-1 | B300: COOPERATIVA DE COMERCIANTES AMBULANTES EL ESFUERZO DE LOS VILOS | C300: REGIÓN DE COQUIMBO | D300: Vigente | E300: 0 | F300: 2
A301: 76932850-5 | B301: COOPERATIVA DE SERVICIOS LOCALES DE INFORMACIÓN Y COMUNICACIONES | C301: REGIÓN DE VALPARAISO | D301: Vigente | E301: 1 | F301: 4
A302: 65974100-8 | B302: COOPERATIVA DE PESCADORES Y ARMADORES ARTESANALES DE LOTA | C302: REGIÓN DEL BÍO-BÍO | D302: Vigente | E302: 1 | F302: 1
A303: 65851260-9 | B303: COOPERATIVA CAMPESINA WULL-AGRO | C303: REGIÓN DE LA ARAUCANÍA | D303: Vigente | E303: 3 | F303: 7
... A323: 76044544-4 | B323: COOPERATIVA AGRÍCOLA APÍCOLA LOMAS DE LIRCAY LIMITADA. | C323: REGIÓN DEL MAULE | D323: Vigente | E323: 0 | F323: 1
A324: 65003472-4 | B324: FEDERACION NACIONAL DE COOPERATIVAS DE SERVICIOS SANITARIOS LIMITADA | C324: REGIÓN DE VALPARAISO | D324: Vigente
A325: 65005079-7 | B325: COOPERATIVA DE SERVICIOS DE ABASTECIMIENTO Y DISTRIBUCIÓN DE AGUA POTABLE, ALCANTARILLADO Y SANEAMIENTO AMBIENTAL MALALHUE LIMITADA. | C325: REGIÓN DE LOS RÍOS | D325: Vigente | E325: 6 | F325: 5
A326: 65002821-K | B326: COOPERATIVA DE AHORRO Y CREDITO BANSUR | C326: REGIÓN DE LOS LAGOS | D326: Vigente | E326: 23 | F326: 8
A327: 65011875-8 | B327: COOPERATIVA DE TRABAJO DE DUEÑOS DE TAXIS COLECTIVOS LINEA VEINTIUNO | C327: REGIÓN DE MAGALLANES Y LA ANTARTICA CHILENA | D327: Vigente | E327: 1 | F327: 2
A328: 65009033-0 | B328: COOPERATIVA DE SERVICIO DE AGUA POTABLE DE FLOR DEL LLANO LTDA. | C328: REGIÓN DEL MAULE | D328: Vigente | E328: 4 | F328: 5
A329: 65006248-5 | B329: COOPERATIVA DE PESCADORES ARTESANALES PUERTO MONTT | C329: REGIÓN DE LOS LAGOS | D329: Vigente | E329: 0 | F329: 4
A330: 65019789-5 | B330: COOPERATIVA AGRÍCOLA MULTIBERRIES GORBEA LIMITADA | C330: REGIÓN DE LA ARAUCANÍA | D330: Vigente | E330: 0 | F330: 2
A331: 65019227-3 | B331: COOPERATIVA DE TRABAJO WITRALTU MAPU LIMITADA | C331: REGIÓN DE LA ARAUCANÍA | D331: Vigente | E331: 0 | F331: 3
A332: 65011753-0 | B332: COOPERATIVA DE TRABAJO DE DUEÑOS DE TAXIS COLECTIVOS SOL DE LA PATAGONIA LINEA CIENTO CATORCE | C332: REGIÓN DE MAGALLANES Y LA ANTARTICA CHILENA | D332: Vigente | E332: 2 | F332: 3
A333: 65026358-8 | B333: COOPERATIVA CAMPESINA DE SALINEROS DE CAHUIL, BARRANCA Y LA VILLA | C333: REGIÓN DEL LIBERTADOR GENERAL BERNARDO O HIGGINS | D333: Vigente | E333: 0 | F333: 1
A334: 65020693-2 | B334: COOPERATIVA DE SERVICIOS EL SALVADOR LIMITADA | C334: REGIÓN DE ATACAMA | D334: Vigente | E334: 2 | F334: 4
A335: 65020501-4 | B335: COOPERATIVA DE CONSUMO RESPONSABLE DE VALDIVIA | C335: REGIÓN DE LOS RÍOS | D335: Vigente | E335: 5 | F335: 5
A336: 65021263-0 | B336: FEDERACION NACIONAL DE COOPERATIVAS DE SERVICIOS LTDA. | C336: REGIÓN DEL MAULE | D336: Vigente | E336: 0 | F336: 4
... A535: 65167881-1 | B535: COOPERATIVA DE TRABAJO DEL CERDO AVELLANERO DE LA COMUNA DE LUMACO | C535: REGIÓN DE LA ARAUCANÍA | D535: Vigente | E535: 0 | F535: 1
A536: 65168122-7 | B536: COOPERATIVA DE TRABAJO EN SOFTWARE LIBRE Y TECNOLOGIAS DE LA INFORMACION ITCOOP LIMITADA | C536: REGIÓN DE VALPARAISO | D536: Vigente
A537: 65167011-K | B537: COOPERATIVA DE SERVICIOS DE DIFUSION Y PUBLICIDAD LIMITADA | C537: REGIÓN DE LOS RÍOS | D537: Vigente | E537: 0 | F537: 3
A538: 65169605-4 | B538: COOPERATIVA AGRÍCOLA Y VITIVINÍCOLA CAUPOLICÁN LIMITADA | C538: REGIÓN DEL MAULE | D538: Vigente | E538: 5 | F538: 7
A539: 53331807-k | B539: COOPERATIVA DE SERVICIOS TURISTICOS CARAMUCHO | C539: REGIÓN DE TARAPACÁ | D539: Vigente | E539: 0 | F539: 1
A540: 65170766-8 | B540: COOPERATIVA AGRICOLA MERKEN DE NAHUELBUTA LIMITADA | C540: REGIÓN DE LA ARAUCANÍA | D540: Vigente | E540: 0 | F540: 1
A541: 76911877-2 | B541: COOPERATIVA AGRICOLA GENTE DE LA TIERRA LIMITADA | C541: REGIÓN DEL BÍO-BÍO | D541: Vigente | E541: 0 | F541: 2
A542: 65168034-4 | B542: COOPERATIVA MAPUCHE DE TRABAJO TRAWUN KO | C542: REGIÓN DE LA ARAUCANÍA | D542: Vigente | E542: 0 | F542: 1
A543: 76917468-0 | B543: COOPERATIVA CAMPESINA CHILOE TURISMO RURAL LIMITADA | C543: REGIÓN DE LOS LAGOS | D543: Vigente | E543: 0 | F543: 2
A544: 65176086-0 | B544: COOPERATIVA DE TRABAJO PROYECTO ESPERANZA | C544: REGIÓN DE VALPARAISO | D544: Vigente | E544: 87 | F544: 7
A545: 65170664-5 | B545: COOPERATIVA AGRICOLA DE PRODUCTOS ORGANICOS MARIA HORTENCIA LIMITADA | C545: REGIÓN DEL MAULE | D545: Vigente | E545: 0 | F545: 1
A546: 65169781-6 | B546: COOPERATIVA MULTIACTIVA DE SERVICIOS INTEGRALES PANGUISUR | C546: REGIÓN DE LOS LAGOS | D546: Vigente | E546: 0 | F546: 2
...

Sheet Cobertura de Datos
A1: SEGMENTO DAES — CAC no supervisadas por CMF (Universo: 38 CAC)
A2: Año | B2: N en panel | C2: Universo | D2: P1 | E2: % de cobertura para ese año | F2: D1 | H2: F2 | J2: F4 | L2: Activos | N2: Patrimonio
D3: N | E3: % | F3: N | G3: % | H3: N | I3: % | J3: N | K3: % | L3: N | M3: % | N3: N | O3: %
A4: 2014 | B4: =+COUNTIF('📁 Panel DAES'!$D$3:$D$135,'Cobertura de Datos'!A4) -> 2 | C4: 35 | D4: =COUNTIFS('📁 Panel DAES'!$D$3:$D$135,'Cobertura de Datos'!A4, '📁 Panel DAES'!$E$3:$E$135,"<>") -> 2 | E4: =+(D4/B4) -> 1 | F4: =COUNTIFS('📁 Panel DAES'!$D$3:$D$135,'Cobertura de Datos'!A4, '📁 Panel DAES'!$D$3:$D$135,"<>") -> 2 | G4: =+F4/C4 -> 0.057142857 | H4: =COUNTIFS('📁 Panel DAES'!$D$3:$D$135,'Cobertura de Datos'!A4, '📁 Panel DAES'!$M$3:$M$135,"<>") -> 2 | I4: =+H4/C4 -> 0.057142857 | J4: =COUNTIFS('📁 Panel DAES'!$D$3:$D$135,'Cobertura de Datos'!A4, '📁 Panel DAES'!$N$3:$N$135,"<>") -> 2 | K4: =+J4/C4 -> 0.057142857 | L4: =COUNTIFS('📁 Panel DAES'!$D$3:$D$135,'Cobertura de Datos'!A4, '📁 Panel DAES'!$K$3:$K$135,"<>") -> 2 | M4: =+L4/C4 -> 0.057142857 | N4: =COUNTIFS('📁 Panel DAES'!$D$3:$D$135,'Cobertura de Datos'!A4, '📁 Panel DAES'!$L$3:$L$135,"<>") -> 2 | O4: =+N4/C4 -> 0.057142857
A5: 2015 | B5: =+COUNTIF('📁 Panel DAES'!$D$3:$D$135,'Cobertura de Datos'!A5) -> 8 | C5: 35 | D5: =COUNTIFS('📁 Panel DAES'!$D$3:$D$135,'Cobertura de Datos'!A5, '📁 Panel DAES'!$E$3:$E$135,"<>") -> 8 | E5: =+(D5/B5) -> 1 | F5: =COUNTIFS('📁 Panel DAES'!$D$3:$D$135,'Cobertura de Datos'!A5, '📁 Panel DAES'!$D$3:$D$135,"<>") -> 8 | G5: =+F5/C5 -> 0.22857143 | H5: =COUNTIFS('📁 Panel DAES'!$D$3:$D$135,'Cobertura de Datos'!A5, '📁 Panel DAES'!$M$3:$M$135,"<>") -> 7 | I5: =+H5/C5 -> 0.2 | J5: =COUNTIFS('📁 Panel DAES'!$D$3:$D$135,'Cobertura de Datos'!A5, '📁 Panel DAES'!$N$3:$N$135,"<>") -> 7 | K5: =+J5/C5 -> 0.2 | L5: =COUNTIFS('📁 Panel DAES'!$D$3:$D$135,'Cobertura de Datos'!A5, '📁 Panel DAES'!$K$3:$K$135,"<>") -> 7 | M5: =+L5/C5 -> 0.2 | N5: =COUNTIFS('📁 Panel DAES'!$D$3:$D$135,'Cobertura de Datos'!A5, '📁 Panel DAES'!$L$3:$L$135,"<>") -> 7 | O5: =+N5/C5 -> 0.2
A6: 2016 | B6: =+COUNTIF('📁 Panel DAES'!$D$3:$D$135,'Cobertura de Datos'!A6) -> 10 | C6: 35 | D6: =COUNTIFS('📁 Panel DAES'!$D$3:$D$135,'Cobertura de Datos'!A6, '📁 Panel DAES'!$E$3:$E$135,"<>") -> 10 | E6: =+(D6/B6) -> 1 | F6: =COUNTIFS('📁 Panel DAES'!$D$3:$D$135,'Cobertura de Datos'!A6, '📁 Panel DAES'!$D$3:$D$135,"<>") -> 10 | G6: =+F6/C6 -> 0.28571429 | H6: =COUNTIFS('📁 Panel DAES'!$D$3:$D$135,'Cobertura de Datos'!A6, '📁 Panel DAES'!$M$3:$M$135,"<>") -> 7 | I6: =+H6/C6 -> 0.2 | J6: =COUNTIFS('📁 Panel DAES'!$D$3:$D$135,'Cobertura de Datos'!A6, '📁 Panel DAES'!$N$3:$N$135,"<>") -> 7 | K6: =+J6/C6 -> 0.2 | L6: =COUNTIFS('📁 Panel DAES'!$D$3:$D$135,'Cobertura de Datos'!A6, '📁 Panel DAES'!$K$3:$K$135,"<>") -> 7 | M6: =+L6/C6 -> 0.2 | N6: =COUNTIFS('📁 Panel DAES'!$D$3:$D$135,'Cobertura de Datos'!A6, '📁 Panel DAES'!$L$3:$L$135,"<>") -> 7 | O6: =+N6/C6 -> 0.2
A7: 2017 | B7: =+COUNTIF('📁 Panel DAES'!$D$3:$D$135,'Cobertura de Datos'!A7) -> 14 | C7: 35 | D7: =COUNTIFS('📁 Panel DAES'!$D$3:$D$135,'Cobertura de Datos'!A7, '📁 Panel DAES'!$E$3:$E$135,"<>") -> 12 | E7: =+(D7/B7) -> 0.85714286 | F7: =COUNTIFS('📁 Panel DAES'!$D$3:$D$135,'Cobertura de Datos'!A7, '📁 Panel DAES'!$D$3:$D$135,"<>") -> 14 | G7: =+F7/C7 -> 0.4 | H7: =COUNTIFS('📁 Panel DAES'!$D$3:$D$135,'Cobertura de Datos'!A7, '📁 Panel DAES'!$M$3:$M$135,"<>") -> 8 | I7: =+H7/C7 -> 0.22857143 | J7: =COUNTIFS('📁 Panel DAES'!$D$3:$D$135,'Cobertura de Datos'!A7, '📁 Panel DAES'!$N$3:$N$135,"<>") -> 8 | K7: =+J7/C7 -> 0.22857143 | L7: =COUNTIFS('📁 Panel DAES'!$D$3:$D$135,'Cobertura de Datos'!A7, '📁 Panel DAES'!$K$3:$K$135,"<>") -> 11 | M7: =+L7/C7 -> 0.31428571 | N7: =COUNTIFS('📁 Panel DAES'!$D$3:$D$135,'Cobertura de Datos'!A7, '📁 Panel DAES'!$L$3:$L$135,"<>") -> 11 | O7: =+N7/C7 -> 0.31428571
A8: 2018 | B8: =+COUNTIF('📁 Panel DAES'!$D$3:$D$135,'Cobertura de Datos'!A8) -> 16 | C8: 35 | D8: =COUNTIFS('📁 Panel DAES'!$D$3:$D$135,'Cobertura de Datos'!A8, '📁 Panel DAES'!$E$3:$E$135,"<>") -> 14 | E8: =+(D8/B8) -> 0.875 | F8: =COUNTIFS('📁 Panel DAES'!$D$3:$D$135,'Cobertura de Datos'!A8, '📁 Panel DAES'!$D$3:$D$135,"<>") -> 16 | G8: =+F8/C8 -> 0.45714286 | H8: =COUNTIFS('📁 Panel DAES'!$D$3:$D$135,'Cobertura de Datos'!A8, '📁 Panel DAES'!$M$3:$M$135,"<>") -> 11 | I8: =+H8/C8 -> 0.31428571 | J8: =COUNTIFS('📁 Panel DAES'!$D$3:$D$135,'Cobertura de Datos'!A8, '📁 Panel DAES'!$N$3:$N$135,"<>") -> 12 | K8: =+J8/C8 -> 0.34285714 | L8: =COUNTIFS('📁 Panel DAES'!$D$3:$D$135,'Cobertura de Datos'!A8, '📁 Panel DAES'!$K$3:$K$135,"<>") -> 15 | M8: =+L8/C8 -> 0.42857143 | N8: =COUNTIFS('📁 Panel DAES'!$D$3:$D$135,'Cobertura de Datos'!A8, '📁 Panel DAES'!$L$3:$L$135,"<>") -> 14 | O8: =+N8/C8 -> 0.4
A9: 2019 | B9: =+COUNTIF('📁 Panel DAES'!$D$3:$D$135,'Cobertura de Datos'!A9) -> 6 | C9: 35 | D9: =COUNTIFS('📁 Panel DAES'!$D$3:$D$135,'Cobertura de Datos'!A9, '📁 Panel DAES'!$E$3:$E$135,"<>") -> 6 | E9: =+(D9/B9) -> 1 | F9: =COUNTIFS('📁 Panel DAES'!$D$3:$D$135,'Cobertura de Datos'!A9, '📁 Panel DAES'!$D$3:$D$135,"<>") -> 6 | G9: =+F9/C9 -> 0.17142857 | H9: =COUNTIFS('📁 Panel DAES'!$D$3:$D$135,'Cobertura de Datos'!A9, '📁 Panel DAES'!$M$3:$M$135,"<>") -> 6 | I9: =+H9/C9 -> 0.17142857 | J9: =COUNTIFS('📁 Panel DAES'!$D$3:$D$135,'Cobertura de Datos'!A9, '📁 Panel DAES'!$N$3:$N$135,"<>") -> 6 | K9: =+J9/C9 -> 0.17142857 | L9: =COUNTIFS('📁 Panel DAES'!$D$3:$D$135,'Cobertura de Datos'!A9, '📁 Panel DAES'!$K$3:$K$135,"<>") -> 6 | M9: =+L9/C9 -> 0.17142857 | N9: =COUNTIFS('📁 Panel DAES'!$D$3:$D$135,'Cobertura de Datos'!A9, '📁 Panel DAES'!$L$3:$L$135,"<>") -> 6 | O9: =+N9/C9 -> 0.17142857
A10: 2020 | B10: =+COUNTIF('📁 Panel DAES'!$D$3:$D$135,'Cobertura de Datos'!A10) -> 10 | C10: 35 | D10: =COUNTIFS('📁 Panel DAES'!$D$3:$D$135,'Cobertura de Datos'!A10, '📁 Panel DAES'!$E$3:$E$135,"<>") -> 10 | E10: =+(D10/B10) -> 1 | F10: =COUNTIFS('📁 Panel DAES'!$D$3:$D$135,'Cobertura de Datos'!A10, '📁 Panel DAES'!$D$3:$D$135,"<>") -> 10 | G10: =+F10/C10 -> 0.28571429 | H10: =COUNTIFS('📁 Panel DAES'!$D$3:$D$135,'Cobertura de Datos'!A10, '📁 Panel DAES'!$M$3:$M$135,"<>") -> 9 | I10: =+H10/C10 -> 0.25714286 | J10: =COUNTIFS('📁 Panel DAES'!$D$3:$D$135,'Cobertura de Datos'!A10, '📁 Panel DAES'!$N$3:$N$135,"<>") -> 9 | K10: =+J10/C10 -> 0.25714286 | L10: =COUNTIFS('📁 Panel DAES'!$D$3:$D$135,'Cobertura de Datos'!A10, '📁 Panel DAES'!$K$3:$K$135,"<>") -> 9 | M10: =+L10/C10 -> 0.25714286 | N10: =COUNTIFS('📁 Panel DAES'!$D$3:$D$135,'Cobertura de Datos'!A10, '📁 Panel DAES'!$L$3:$L$135,"<>") -> 9 | O10: =+N10/C10 -> 0.25714286
A11: 2021 | B11: =+COUNTIF('📁 Panel DAES'!$D$3:$D$135,'Cobertura de Datos'!A11) -> 11 | C11: 35 | D11: =COUNTIFS('📁 Panel DAES'!$D$3:$D$135,'Cobertura de Datos'!A11, '📁 Panel DAES'!$E$3:$E$135,"<>") -> 11 | E11: =+(D11/B11) -> 1 | F11: =COUNTIFS('📁 Panel DAES'!$D$3:$D$135,'Cobertura de Datos'!A11, '📁 Panel DAES'!$D$3:$D$135,"<>") -> 11 | G11: =+F11/C11 -> 0.31428571 | H11: =COUNTIFS('📁 Panel DAES'!$D$3:$D$135,'Cobertura de Datos'!A11, '📁 Panel DAES'!$M$3:$M$135,"<>") -> 9 | I11: =+H11/C11 -> 0.25714286 | J11: =COUNTIFS('📁 Panel DAES'!$D$3:$D$135,'Cobertura de Datos'!A11, '📁 Panel DAES'!$N$3:$N$135,"<>") -> 8 | K11: =+J11/C11 -> 0.22857143 | L11: =COUNTIFS('📁 Panel DAES'!$D$3:$D$135,'Cobertura de Datos'!A11, '📁 Panel DAES'!$K$3:$K$135,"<>") -> 9 | M11: =+L11/C11 -> 0.25714286 | N11: =COUNTIFS('📁 Panel DAES'!$D$3:$D$135,'Cobertura de Datos'!A11, '📁 Panel DAES'!$L$3:$L$135,"<>") -> 9 | O11: =+N11/C11 -> 0.25714286
A12: 2022 | B12: =+COUNTIF('📁 Panel DAES'!$D$3:$D$135,'Cobertura de Datos'!A12) -> 20 | C12: 35 | D12: =COUNTIFS('📁 Panel DAES'!$D$3:$D$135,'Cobertura de Datos'!A12, '📁 Panel DAES'!$E$3:$E$135,"<>") -> 20 | E12: =+(D12/B12) -> 1 | F12: =COUNTIFS('📁 Panel DAES'!$D$3:$D$135,'Cobertura de Datos'!A12, '📁 Panel DAES'!$D$3:$D$135,"<>") -> 20 | G12: =+F12/C12 -> 0.57142857 | H12: =COUNTIFS('📁 Panel DAES'!$D$3:$D$135,'Cobertura de Datos'!A12, '📁 Panel DAES'!$M$3:$M$135,"<>") -> 16 | I12: =+H12/C12 -> 0.45714286 | J12: =COUNTIFS('📁 Panel DAES'!$D$3:$D$135,'Cobertura de Datos'!A12, '📁 Panel DAES'!$N$3:$N$135,"<>") -> 16 | K12: =+J12/C12 -> 0.45714286 | L12: =COUNTIFS('📁 Panel DAES'!$D$3:$D$135,'Cobertura de Datos'!A12, '📁 Panel DAES'!$K$3:$K$135,"<>") -> 17 | M12: =+L12/C12 -> 0.48571429 | N12: =COUNTIFS('📁 Panel DAES'!$D$3:$D$135,'Cobertura de Datos'!A12, '📁 Panel DAES'!$L$3:$L$135,"<>") -> 17 | O12: =+N12/C12 -> 0.48571429
A13: 2023 | B13: =+COUNTIF('📁 Panel DAES'!$D$3:$D$135,'Cobertura de Datos'!A13) -> 24 | C13: 35 | D13: =COUNTIFS('📁 Panel DAES'!$D$3:$D$135,'Cobertura de Datos'!A13, '📁 Panel DAES'!$E$3:$E$135,"<>") -> 24 | E13: =+(D13/B13) -> 1 | F13: =COUNTIFS('📁 Panel DAES'!$D$3:$D$135,'Cobertura de Datos'!A13, '📁 Panel DAES'!$D$3:$D$135,"<>") -> 24 | G13: =+F13/C13 -> 0.68571429 | H13: =COUNTIFS('📁 Panel DAES'!$D$3:$D$135,'Cobertura de Datos'!A13, '📁 Panel DAES'!$M$3:$M$135,"<>") -> 20 | I13: =+H13/C13 -> 0.57142857 | J13: =COUNTIFS('📁 Panel DAES'!$D$3:$D$135,'Cobertura de Datos'!A13, '📁 Panel DAES'!$N$3:$N$135,"<>") -> 20 | K13: =+J13/C13 -> 0.57142857 | L13: =COUNTIFS('📁 Panel DAES'!$D$3:$D$135,'Cobertura de Datos'!A13, '📁 Panel DAES'!$K$3:$K$135,"<>") -> 22 | M13: =+L13/C13 -> 0.62857143 | N13: =COUNTIFS('📁 Panel DAES'!$D$3:$D$135,'Cobertura de Datos'!A13, '📁 Panel DAES'!$L$3:$L$135,"<>") -> 22 | O13: =+N13/C13 -> 0.62857143
A14: 2024 | B14: =+COUNTIF('📁 Panel DAES'!$D$3:$D$135,'Cobertura de Datos'!A14) -> 12 | C14: 35 | D14: =COUNTIFS('📁 Panel DAES'!$D$3:$D$135,'Cobertura de Datos'!A14, '📁 Panel DAES'!$E$3:$E$135,"<>") -> 12 | E14: =+(D14/B14) -> 1 | F14: =COUNTIFS('📁 Panel DAES'!$D$3:$D$135,'Cobertura de Datos'!A14, '📁 Panel DAES'!$D$3:$D$135,"<>") -> 12 | G14: =+F14/C14 -> 0.34285714 | H14: =COUNTIFS('📁 Panel DAES'!$D$3:$D$135,'Cobertura de Datos'!A14, '📁 Panel DAES'!$M$3:$M$135,"<>") -> 11 | I14: =+H14/C14 -> 0.31428571 | J14: =COUNTIFS('📁 Panel DAES'!$D$3:$D$135,'Cobertura de Datos'!A14, '📁 Panel DAES'!$N$3:$N$135,"<>") -> 12 | K14: =+J14/C14 -> 0.34285714 | L14: =COUNTIFS('📁 Panel DAES'!$D$3:$D$135,'Cobertura de Datos'!A14, '📁 Panel DAES'!$K$3:$K$135,"<>") -> 12 | M14: =+L14/C14 -> 0.34285714 | N14: =COUNTIFS('📁 Panel DAES'!$D$3:$D$135,'Cobertura de Datos'!A14, '📁 Panel DAES'!$L$3:$L$135,"<>") -> 12 | O14: =+N14/C14 -> 0.34285714
E15: Sacamos porcentaje de variable con dato/ total de cooperativas con al menos un dato ese año o variable con dato/ total de cooperativas que tienen al menos un dato entre 2014 y 2024
A16: SEGMENTO CMF — 7 CAC supervisadas (Universo: 7 CAC)
A17: Año | B17: N en panel | C17: Universo | D17: P1 | F17: D1 | H17: F2 | J17: F4 | L17: Activos | N17: Patrimonio
D18: N | E18: % | F18: N | G18: % | H18: N | I18: % | J18: N | K18: % | L18: N | M18: % | N18: N | O18: %
A19: 2013 | B19: 7 | C19: 7 | D19: 7 | E19: 1 | F19: 7 | G19: 1 | H19: 7 | I19: 1 | J19: 7 | K19: 1 | L19: 7 | M19: 1 | N19: 7 | O19: 1
A20: 2014 | B20: 7 | C20: 7 | D20: 7 | E20: 1 | F20: 7 | G20: 1 | H20: 7 | I20: 1 | J20: 7 | K20: 1 | L20: 7 | M20: 1 | N20: 7 | O20: 1
A21: 2015 | B21: 7 | C21: 7 | D21: 7 | E21: 1 | F21: 7 | G21: 1 | H21: 7 | I21: 1 | J21: 7 | K21: 1 | L21: 7 | M21: 1 | N21: 7 | O21: 1
A22: 2016 | B22: 7 | C22: 7 | D22: 7 | E22: 1 | F22: 7 | G22: 1 | H22: 7 | I22: 1 | J22: 7 | K22: 1 | L22: 7 | M22: 1 | N22: 7 | O22: 1
A23: 2017 | B23: 7 | C23: 7 | D23: 7 | E23: 1 | F23: 7 | G23: 1 | H23: 7 | I23: 1 | J23: 7 | K23: 1 | L23: 7 | M23: 1 | N23: 7 | O23: 1
A24: 2018 | B24: 7 | C24: 7 | D24: 7 | E24: 1 | F24: 7 | G24: 1 | H24: 7 | I24: 1 | J24: 7 | K24: 1 | L24: 7 | M24: 1 | N24: 7 | O24: 1
A25: 2019 | B25: 7 | C25: 7 | D25: 7 | E25: 1 | F25: 7 | G25: 1 | H25: 7 | I25: 1 | J25: 7 | K25: 1 | L25: 7 | M25: 1 | N25: 7 | O25: 1
A26: 2020 | B26: 7 | C26: 7 | D26: 7 | E26: 1 | F26: 7 | G26: 1 | H26: 7 | I26: 1 | J26: 7 | K26: 1 | L26: 7 | M26: 1 | N26: 7 | O26: 1
A27: 2021 | B27: 7 | C27: 7 | D27: 7 | E27: 1 | F27: 7 | G27: 1 | H27: 7 | I27: 1 | J27: 7 | K27: 1 | L27: 7 | M27: 1 | N27: 7 | O27: 1
A28: 2022 | B28: 7 | C28: 7 | D28: 7 | E28: 1 | F28: 7 | G28: 1 | H28: 7 | I28: 1 | J28: 7 | K28: 1 | L28: 7 | M28: 1 | N28: 7 | O28: 1
A29: 2023 | B29: 7 | C29: 7 | D29: 7 | E29: 1 | F29: 7 | G29: 1 | H29: 7 | I29: 1 | J29: 7 | K29: 1 | L29: 7 | M29: 1 | N29: 7 | O29: 1
A30: 2024 | B30: 7 | C30: 7 | D30: 7 | E30: 1 | F30: 7 | G30: 1 | H30: 7 | I30: 1 | J30: 7 | K30: 1 | L30: 7 | M30: 1 | N30: 7 | O30: 1
A31: 2025 | B31: 7 | C31: 7 | D31: 7 | E31: 1 | F31: 7 | G31: 1 | H31: 7 | I31: 1 | J31: 7 | K31: 1 | L31: 7 | M31: 1 | N31: 7 | O31: 1

Sheet Estadística Descriptiva
A1: DAES Y CMF— Estadística descriptiva por variable y año — Cifras en MM$
A2: Supervisor | B2: Variable | C2: Año | D2: N | E2: Media | F2: Mediana | G2: Std | H2: Min | I2: Max
A3: DAES | B3: P1 | C3: 2014 | D3: =COUNTIFS('📁 Panel DAES'!$D$3:$D$135,'Cobertura de Datos'!A4, '📁 Panel DAES'!$E$3:$E$135,"<>") -> 2 | E3: =+AVERAGEIF('📁 Panel DAES'!$D$3:$D$135,'Estadística Descriptiva'!C3,'📁 Panel DAES'!$E$3:$E$135) -> 123.94641 | F3: {=+MEDIAN(IF('📁 Panel DAES'!$D$3:$D$135='Estadística Descriptiva'!C3,'📁 Panel DAES'!$E$3:$E$135))} -> 123.94641 | G3: {=+_xlfn.STDEV.S(IF('📁 Panel DAES'!$D$3:$D$135='Estadística Descriptiva'!C3,'📁 Panel DAES'!$E$3:$E$135))} -> 174.21249 | H3: {=+MIN(IF('📁 Panel DAES'!$D$3:$D$135='Estadística Descriptiva'!C3,'📁 Panel DAES'!$E$3:$E$135))} -> 0.759577 | I3: {=+MAX(IF('📁 Panel DAES'!$D$3:$D$135='Estadística Descriptiva'!C3,'📁 Panel DAES'!$E$3:$E$135))} -> 247.13324
A4: DAES | B4: P1 | C4: 2015 | D4: =COUNTIFS('📁 Panel DAES'!$D$3:$D$135,'Cobertura de Datos'!A5, '📁 Panel DAES'!$E$3:$E$135,"<>") -> 8 | E4: =+AVERAGEIF('📁 Panel DAES'!$D$3:$D$135,'Estadística Descriptiva'!C4,'📁 Panel DAES'!$E$3:$E$135) -> 678.25805 | F4: {=+MEDIAN(IF('📁 Panel DAES'!$D$3:$D$135='Estadística Descriptiva'!C4,'📁 Panel DAES'!$E$3:$E$135))} -> 166.90107 | G4: {=+_xlfn.STDEV.S(IF('📁 Panel DAES'!$D$3:$D$135='Estadística Descriptiva'!C4,'📁 Panel DAES'!$E$3:$E$135))} -> 1146.2995 | H4: {=+MIN(IF('📁 Panel DAES'!$D$3:$D$135='Estadística Descriptiva'!C4,'📁 Panel DAES'!$E$3:$E$135))} -> 0 | I4: {=+MAX(IF('📁 Panel DAES'!$D$3:$D$135='Estadística Descriptiva'!C4,'📁 Panel DAES'!$E$3:$E$135))} -> 3368.8769
A5: DAES | B5: P1 | C5: 2016 | D5: =COUNTIFS('📁 Panel DAES'!$D$3:$D$135,'Cobertura de Datos'!A6, '📁 Panel DAES'!$E$3:$E$135,"<>") -> 10 | E5: =+AVERAGEIF('📁 Panel DAES'!$D$3:$D$135,'Estadística Descriptiva'!C5,'📁 Panel DAES'!$E$3:$E$135) -> 608.32353 | F5: {=+MEDIAN(IF('📁 Panel DAES'!$D$3:$D$135='Estadística Descriptiva'!C5,'📁 Panel DAES'!$E$3:$E$135))} -> 140.01144 | G5: {=+_xlfn.STDEV.S(IF('📁 Panel DAES'!$D$3:$D$135='Estadística Descriptiva'!C5,'📁 Panel DAES'!$E$3:$E$135))} -> 1158.0689 | H5: {=+MIN(IF('📁 Panel DAES'!$D$3:$D$135='Estadística Descriptiva'!C5,'📁 Panel DAES'!$E$3:$E$135))} -> 0.002191 | I5: {=+MAX(IF('📁 Panel DAES'!$D$3:$D$135='Estadística Descriptiva'!C5,'📁 Panel DAES'!$E$3:$E$135))} -> 3715.6684
A6: DAES | B6: P1 | C6: 2017 | D6: =COUNTIFS('📁 Panel DAES'!$D$3:$D$135,'Cobertura de Datos'!A7, '📁 Panel DAES'!$E$3:$E$135,"<>") -> 12 | E6: =+AVERAGEIF('📁 Panel DAES'!$D$3:$D$135,'Estadística Descriptiva'!C6,'📁 Panel DAES'!$E$3:$E$135) -> 518.68734 | F6: {=+MEDIAN(IF('📁 Panel DAES'!$D$3:$D$135='Estadística Descriptiva'!C6,'📁 Panel DAES'!$E$3:$E$135))} -> 250.46229 | G6: {=+_xlfn.STDEV.S(IF('📁 Panel DAES'!$D$3:$D$135='Estadística Descriptiva'!C6,'📁 Panel DAES'!$E$3:$E$135))} -> 597.91082 | H6: {=+MIN(IF('📁 Panel DAES'!$D$3:$D$135='Estadística Descriptiva'!C6,'📁 Panel DAES'!$E$3:$E$135))} -> 0 | I6: {=+MAX(IF('📁 Panel DAES'!$D$3:$D$135='Estadística Descriptiva'!C6,'📁 Panel DAES'!$E$3:$E$135))} -> 2207.2309
A7: DAES | B7: P1 | C7: 2018 | D7: =COUNTIFS('📁 Panel DAES'!$D$3:$D$135,'Cobertura de Datos'!A8, '📁 Panel DAES'!$E$3:$E$135,"<>") -> 14 | E7: =+AVERAGEIF('📁 Panel DAES'!$D$3:$D$135,'Estadística Descriptiva'!C7,'📁 Panel DAES'!$E$3:$E$135) -> 641.23288 | F7: {=+MEDIAN(IF('📁 Panel DAES'!$D$3:$D$135='Estadística Descriptiva'!C7,'📁 Panel DAES'!$E$3:$E$135))} -> 247.19757 | G7: {=+_xlfn.STDEV.S(IF('📁 Panel DAES'!$D$3:$D$135='Estadística Descriptiva'!C7,'📁 Panel DAES'!$E$3:$E$135))} -> 794.5229 | H7: {=+MIN(IF('📁 Panel DAES'!$D$3:$D$135='Estadística Descriptiva'!C7,'📁 Panel DAES'!$E$3:$E$135))} -> 0 | I7: {=+MAX(IF('📁 Panel DAES'!$D$3:$D$135='Estadística Descriptiva'!C7,'📁 Panel DAES'!$E$3:$E$135))} -> 2617.4222
A8: DAES | B8: P1 | C8: 2019 | D8: =COUNTIFS('📁 Panel DAES'!$D$3:$D$135,'Cobertura de Datos'!A9, '📁 Panel DAES'!$E$3:$E$135,"<>") -> 6 | E8: =+AVERAGEIF('📁 Panel DAES'!$D$3:$D$135,'Estadística Descriptiva'!C8,'📁 Panel DAES'!$E$3:$E$135) -> 777.87528 | F8: {=+MEDIAN(IF('📁 Panel DAES'!$D$3:$D$135='Estadística Descriptiva'!C8,'📁 Panel DAES'!$E$3:$E$135))} -> 772.07054 | G8: {=+_xlfn.STDEV.S(IF('📁 Panel DAES'!$D$3:$D$135='Estadística Descriptiva'!C8,'📁 Panel DAES'!$E$3:$E$135))} -> 618.02704 | H8: {=+MIN(IF('📁 Panel DAES'!$D$3:$D$135='Estadística Descriptiva'!C8,'📁 Panel DAES'!$E$3:$E$135))} -> 0.351286 | I8: {=+MAX(IF('📁 Panel DAES'!$D$3:$D$135='Estadística Descriptiva'!C8,'📁 Panel DAES'!$E$3:$E$135))} -> 1756.1494
A9: DAES | B9: P1 | C9: 2020 | D9: =COUNTIFS('📁 Panel DAES'!$D$3:$D$135,'Cobertura de Datos'!A10, '📁 Panel DAES'!$E$3:$E$135,"<>") -> 10 | E9: =+AVERAGEIF('📁 Panel DAES'!$D$3:$D$135,'Estadística Descriptiva'!C9,'📁 Panel DAES'!$E$3:$E$135) -> 616.46371 | F9: {=+MEDIAN(IF('📁 Panel DAES'!$D$3:$D$135='Estadística Descriptiva'!C9,'📁 Panel DAES'!$E$3:$E$135))} -> 348.9929 | G9: {=+_xlfn.STDEV.S(IF('📁 Panel DAES'!$D$3:$D$135='Estadística Descriptiva'!C9,'📁 Panel DAES'!$E$3:$E$135))} -> 618.81468 | H9: {=+MIN(IF('📁 Panel DAES'!$D$3:$D$135='Estadística Descriptiva'!C9,'📁 Panel DAES'!$E$3:$E$135))} -> 0.244807 | I9: {=+MAX(IF('📁 Panel DAES'!$D$3:$D$135='Estadística Descriptiva'!C9,'📁 Panel DAES'!$E$3:$E$135))} -> 1927.2509
A10: DAES | B10: P1 | C10: 2021 | D10: =COUNTIFS('📁 Panel DAES'!$D$3:$D$135,'Cobertura de Datos'!A11, '📁 Panel DAES'!$E$3:$E$135,"<>") -> 11 | E10: =+AVERAGEIF('📁 Panel DAES'!$D$3:$D$135,'Estadística Descriptiva'!C10,'📁 Panel DAES'!$E$3:$E$135) -> 546.41092 | F10: {=+MEDIAN(IF('📁 Panel DAES'!$D$3:$D$135='Estadística Descriptiva'!C10,'📁 Panel DAES'!$E$3:$E$135))} -> 321.61466 | G10: {=+_xlfn.STDEV.S(IF('📁 Panel DAES'!$D$3:$D$135='Estadística Descriptiva'!C10,'📁 Panel DAES'!$E$3:$E$135))} -> 669.48074 | H10: {=+MIN(IF('📁 Panel DAES'!$D$3:$D$135='Estadística Descriptiva'!C10,'📁 Panel DAES'!$E$3:$E$135))} -> 0.261336 | I10: {=+MAX(IF('📁 Panel DAES'!$D$3:$D$135='Estadística Descriptiva'!C10,'📁 Panel DAES'!$E$3:$E$135))} -> 2286.0596
A11: DAES | B11: P1 | C11: 2022 | D11: =COUNTIFS('📁 Panel DAES'!$D$3:$D$135,'Cobertura de Datos'!A12, '📁 Panel DAES'!$E$3:$E$135,"<>") -> 20 | E11: =+AVERAGEIF('📁 Panel DAES'!$D$3:$D$135,'Estadística Descriptiva'!C11,'📁 Panel DAES'!$E$3:$E$135) -> 1108.5994 | F11: {=+MEDIAN(IF('📁 Panel DAES'!$D$3:$D$135='Estadística Descriptiva'!C11,'📁 Panel DAES'!$E$3:$E$135))} -> 731.60728 | G11: {=+_xlfn.STDEV.S(IF('📁 Panel DAES'!$D$3:$D$135='Estadística Descriptiva'!C11,'📁 Panel DAES'!$E$3:$E$135))} -> 1071.5091 | H11: {=+MIN(IF('📁 Panel DAES'!$D$3:$D$135='Estadística Descriptiva'!C11,'📁 Panel DAES'!$E$3:$E$135))} -> 2.92309 | I11: {=+MAX(IF('📁 Panel DAES'!$D$3:$D$135='Estadística Descriptiva'!C11,'📁 Panel DAES'!$E$3:$E$135))} -> 3902.0546
A12: DAES | B12: P1 | C12: 2023 | D12: =COUNTIFS('📁 Panel DAES'!$D$3:$D$135,'Cobertura de Datos'!A13, '📁 Panel DAES'!$E$3:$E$135,"<>") -> 24 | E12: =+AVERAGEIF('📁 Panel DAES'!$D$3:$D$135,'Estadística Descriptiva'!C12,'📁 Panel DAES'!$E$3:$E$135) -> 1975.1928 | F12: {=+MEDIAN(IF('📁 Panel DAES'!$D$3:$D$135='Estadística Descriptiva'!C12,'📁 Panel DAES'!$E$3:$E$135))} -> 645.82355 | G12: {=+_xlfn.STDEV.S(IF('📁 Panel DAES'!$D$3:$D$135='Estadística Descriptiva'!C12,'📁 Panel DAES'!$E$3:$E$135))} -> 2506.4407 | H12: {=+MIN(IF('📁 Panel DAES'!$D$3:$D$135='Estadística Descriptiva'!C12,'📁 Panel DAES'!$E$3:$E$135))} -> 0.343607 | I12: {=+MAX(IF('📁 Panel DAES'!$D$3:$D$135='Estadística Descriptiva'!C12,'📁 Panel DAES'!$E$3:$E$135))} -> 9903.39
A13: DAES | B13: P1 | C13: 2024 | D13: =COUNTIFS('📁 Panel DAES'!$D$3:$D$135,'Cobertura de Datos'!A14, '📁 Panel DAES'!$E$3:$E$135,"<>") -> 12 | E13: =+AVERAGEIF('📁 Panel DAES'!$D$3:$D$135,'Estadística Descriptiva'!C13,'📁 Panel DAES'!$E$3:$E$135) -> 1511.3217 | F13: {=+MEDIAN(IF('📁 Panel DAES'!$D$3:$D$135='Estadística Descriptiva'!C13,'📁 Panel DAES'!$E$3:$E$135))} -> 565.72779 | G13: {=+_xlfn.STDEV.S(IF('📁 Panel DAES'!$D$3:$D$135='Estadística Descriptiva'!C13,'📁 Panel DAES'!$E$3:$E$135))} -> 2960.2847 | H13: {=+MIN(IF('📁 Panel DAES'!$D$3:$D$135='Estadística Descriptiva'!C13,'📁 Panel DAES'!$E$3:$E$135))} -> 8.197293 | I13: {=+MAX(IF('📁 Panel DAES'!$D$3:$D$135='Estadística Descriptiva'!C13,'📁 Panel DAES'!$E$3:$E$135))} -> 10773.726
A14: DAES | B14: D1 | C14: 2014 | D14: =COUNTIFS('📁 Panel DAES'!$D$3:$D$135,'Cobertura de Datos'!A4, '📁 Panel DAES'!$H$3:$H$135,"<>") -> 2 | E14: =+AVERAGEIF('📁 Panel DAES'!$D$3:$D$135,C14,'📁 Panel DAES'!$H$3:$H$135) -> 39.111799 | F14: {=+MEDIAN(IF('📁 Panel DAES'!$D$3:$D$135=C14,'📁 Panel DAES'!$H$3:$H$135))} -> 39.111798 | G14: {=+_xlfn.STDEV.S(IF('📁 Panel DAES'!$D$3:$D$135='Estadística Descriptiva'!C14,'📁 Panel DAES'!$H$3:$H$135))} -> 49.843123 | H14: {=+MIN(IF('📁 Panel DAES'!$D$3:$D$135='Estadística Descriptiva'!C14,'📁 Panel DAES'!$H$3:$H$135))} -> 3.867388 | I14: {=+MAX(IF('📁 Panel DAES'!$D$3:$D$135='Estadística Descriptiva'!C14,'📁 Panel DAES'!$H$3:$H$135))} -> 74.356209
A15: DAES | B15: D1 | C15: 2015 | D15: =COUNTIFS('📁 Panel DAES'!$D$3:$D$135,'Cobertura de Datos'!A5, '📁 Panel DAES'!$H$3:$H$135,"<>") -> 7 | E15: =+AVERAGEIF('📁 Panel DAES'!$D$3:$D$135,C15,'📁 Panel DAES'!$H$3:$H$135) -> 251.83083 | F15: {=+MEDIAN(IF('📁 Panel DAES'!$D$3:$D$135=C15,'📁 Panel DAES'!$H$3:$H$135))} -> 74.453214 | G15: {=+_xlfn.STDEV.S(IF('📁 Panel DAES'!$D$3:$D$135='Estadística Descriptiva'!C15,'📁 Panel DAES'!$H$3:$H$135))} -> 332.81617 | H15: {=+MIN(IF('📁 Panel DAES'!$D$3:$D$135='Estadística Descriptiva'!C15,'📁 Panel DAES'!$H$3:$H$135))} -> 0 | I15: {=+MAX(IF('📁 Panel DAES'!$D$3:$D$135='Estadística Descriptiva'!C15,'📁 Panel DAES'!$H$3:$H$135))} -> 984.36359
A16: DAES | B16: D1 | C16: 2016 | D16: =COUNTIFS('📁 Panel DAES'!$D$3:$D$135,'Cobertura de Datos'!A6, '📁 Panel DAES'!$H$3:$H$135,"<>") -> 9 | E16: =+AVERAGEIF('📁 Panel DAES'!$D$3:$D$135,C16,'📁 Panel DAES'!$H$3:$H$135) -> 222.25286 | F16: {=+MEDIAN(IF('📁 Panel DAES'!$D$3:$D$135=C16,'📁 Panel DAES'!$H$3:$H$135))} -> 83.038392 | G16: {=+_xlfn.STDEV.S(IF('📁 Panel DAES'!$D$3:$D$135='Estadística Descriptiva'!C16,'📁 Panel DAES'!$H$3:$H$135))} -> 337.40553 | H16: {=+MIN(IF('📁 Panel DAES'!$D$3:$D$135='Estadística Descriptiva'!C16,'📁 Panel DAES'!$H$3:$H$135))} -> 0 | I16: {=+MAX(IF('📁 Panel DAES'!$D$3:$D$135='Estadística Descriptiva'!C16,'📁 Panel DAES'!$H$3:$H$135))} -> 1094.6625
A17: DAES | B17: D1 | C17: 2017 | D17: =COUNTIFS('📁 Panel DAES'!$D$3:$D$135,'Cobertura de Datos'!A7, '📁 Panel DAES'!$H$3:$H$135,"<>") -> 14 | E17: =+AVERAGEIF('📁 Panel DAES'!$D$3:$D$135,C17,'📁 Panel DAES'!$H$3:$H$135) -> 187.3018 | F17: {=+MEDIAN(IF('📁 Panel DAES'!$D$3:$D$135=C17,'📁 Panel DAES'!$H$3:$H$135))} -> 125.4804 | G17: {=+_xlfn.STDEV.S(IF('📁 Panel DAES'!$D$3:$D$135='Estadística Descriptiva'!C17,'📁 Panel DAES'!$H$3:$H$135))} -> 236.06749 | H17: {=+MIN(IF('📁 Panel DAES'!$D$3:$D$135='Estadística Descriptiva'!C17,'📁 Panel DAES'!$H$3:$H$135))} -> 0.083293 | I17: {=+MAX(IF('📁 Panel DAES'!$D$3:$D$135='Estadística Descriptiva'!C17,'📁 Panel DAES'!$H$3:$H$135))} -> 942.66384
A18: DAES | B18: D1 | C18: 2018 | D18: =COUNTIFS('📁 Panel DAES'!$D$3:$D$135,'Cobertura de Datos'!A8, '📁 Panel DAES'!$H$3:$H$135,"<>") -> 16 | E18: =+AVERAGEIF('📁 Panel DAES'!$D$3:$D$135,C18,'📁 Panel DAES'!$H$3:$H$135) -> 274.0776 | F18: {=+MEDIAN(IF('📁 Panel DAES'!$D$3:$D$135=C18,'📁 Panel DAES'!$H$3:$H$135))} -> 135.68929 | G18: {=+_xlfn.STDEV.S(IF('📁 Panel DAES'!$D$3:$D$135='Estadística Descriptiva'!C18,'📁 Panel DAES'!$H$3:$H$135))} -> 388.85852 | H18: {=+MIN(IF('📁 Panel DAES'!$D$3:$D$135='Estadística Descriptiva'!C18,'📁 Panel DAES'!$H$3:$H$135))} -> 0.112391 | I18: {=+MAX(IF('📁 Panel DAES'!$D$3:$D$135='Estadística Descriptiva'!C18,'📁 Panel DAES'!$H$3:$H$135))} -> 1353.3568
A19: DAES | B19: D1 | C19: 2019 | D19: =COUNTIFS('📁 Panel DAES'!$D$3:$D$135,'Cobertura de Datos'!A9, '📁 Panel DAES'!$H$3:$H$135,"<>") -> 6 | E19: =+AVERAGEIF('📁 Panel DAES'!$D$3:$D$135,C19,'📁 Panel DAES'!$H$3:$H$135) -> 309.16459 | F19: {=+MEDIAN(IF('📁 Panel DAES'!$D$3:$D$135=C19,'📁 Panel DAES'!$H$3:$H$135))} -> 308.07733 | G19: {=+_xlfn.STDEV.S(IF('📁 Panel DAES'!$D$3:$D$135='Estadística Descriptiva'!C19,'📁 Panel DAES'!$H$3:$H$135))} -> 189.2011 | H19: {=+MIN(IF('📁 Panel DAES'!$D$3:$D$135='Estadística Descriptiva'!C19,'📁 Panel DAES'!$H$3:$H$135))} -> 0.126394 | I19: {=+MAX(IF('📁 Panel DAES'!$D$3:$D$135='Estadística Descriptiva'!C19,'📁 Panel DAES'!$H$3:$H$135))} -> 529.27133
A20: DAES | B20: D1 | C20: 2020 | D20: =COUNTIFS('📁 Panel DAES'!$D$3:$D$135,'Cobertura de Datos'!A10, '📁 Panel DAES'!$H$3:$H$135,"<>") -> 10 | E20: =+AVERAGEIF('📁 Panel DAES'!$D$3:$D$135,C20,'📁 Panel DAES'!$H$3:$H$135) -> 241.99054 | F20: {=+MEDIAN(IF('📁 Panel DAES'!$D$3:$D$135=C20,'📁 Panel DAES'!$H$3:$H$135))} -> 153.78262 | G20: {=+_xlfn.STDEV.S(IF('📁 Panel DAES'!$D$3:$D$135='Estadística Descriptiva'!C20,'📁 Panel DAES'!$H$3:$H$135))} -> 235.38341 | H20: {=+MIN(IF('📁 Panel DAES'!$D$3:$D$135='Estadística Descriptiva'!C20,'📁 Panel DAES'!$H$3:$H$135))} -> 0.125367 | I20: {=+MAX(IF('📁 Panel DAES'!$D$3:$D$135='Estadística Descriptiva'!C20,'📁 Panel DAES'!$H$3:$H$135))} -> 644.20884
A21: DAES | B21: D1 | C21: 2021 | D21: =COUNTIFS('📁 Panel DAES'!$D$3:$D$135,'Cobertura de Datos'!A11, '📁 Panel DAES'!$H$3:$H$135,"<>") -> 10 | E21: =+AVERAGEIF('📁 Panel DAES'!$D$3:$D$135,C21,'📁 Panel DAES'!$H$3:$H$135) -> 203.00232 | F21: {=+MEDIAN(IF('📁 Panel DAES'!$D$3:$D$135=C21,'📁 Panel DAES'!$H$3:$H$135))} -> 87.097456 | G21: {=+_xlfn.STDEV.S(IF('📁 Panel DAES'!$D$3:$D$135='Estadística Descriptiva'!C21,'📁 Panel DAES'!$H$3:$H$135))} -> 195.33259 | H21: {=+MIN(IF('📁 Panel DAES'!$D$3:$D$135='Estadística Descriptiva'!C21,'📁 Panel DAES'!$H$3:$H$135))} -> 0 | I21: {=+MAX(IF('📁 Panel DAES'!$D$3:$D$135='Estadística Descriptiva'!C21,'📁 Panel DAES'!$H$3:$H$135))} -> 629.90945
A22: DAES | B22: D1 | C22: 2022 | D22: =COUNTIFS('📁 Panel DAES'!$D$3:$D$135,'Cobertura de Datos'!A12, '📁 Panel DAES'!$H$3:$H$135,"<>") -> 19 | E22: =+AVERAGEIF('📁 Panel DAES'!$D$3:$D$135,C22,'📁 Panel DAES'!$H$3:$H$135) -> 366.70378 | F22: {=+MEDIAN(IF('📁 Panel DAES'!$D$3:$D$135=C22,'📁 Panel DAES'!$H$3:$H$135))} -> 239.41073 | G22: {=+_xlfn.STDEV.S(IF('📁 Panel DAES'!$D$3:$D$135='Estadística Descriptiva'!C22,'📁 Panel DAES'!$H$3:$H$135))} -> 387.68507 | H22: {=+MIN(IF('📁 Panel DAES'!$D$3:$D$135='Estadística Descriptiva'!C22,'📁 Panel DAES'!$H$3:$H$135))} -> 0 | I22: {=+MAX(IF('📁 Panel DAES'!$D$3:$D$135='Estadística Descriptiva'!C22,'📁 Panel DAES'!$H$3:$H$135))} -> 1596.0623
A23: DAES | B23: D1 | C23: 2023 | D23: =COUNTIFS('📁 Panel DAES'!$D$3:$D$135,'Cobertura de Datos'!A13, '📁 Panel DAES'!$H$3:$H$135,"<>") -> 22 | E23: =+AVERAGEIF('📁 Panel DAES'!$D$3:$D$135,C23,'📁 Panel DAES'!$H$3:$H$135) -> 571.92656 | F23: {=+MEDIAN(IF('📁 Panel DAES'!$D$3:$D$135=C23,'📁 Panel DAES'!$H$3:$H$135))} -> 279.55718 | G23: {=+_xlfn.STDEV.S(IF('📁 Panel DAES'!$D$3:$D$135='Estadística Descriptiva'!C23,'📁 Panel DAES'!$H$3:$H$135))} -> 778.50805 | H23: {=+MIN(IF('📁 Panel DAES'!$D$3:$D$135='Estadística Descriptiva'!C23,'📁 Panel DAES'!$H$3:$H$135))} -> 0 | I23: {=+MAX(IF('📁 Panel DAES'!$D$3:$D$135='Estadística Descriptiva'!C23,'📁 Panel DAES'!$H$3:$H$135))} -> 3648.234
A24: DAES | B24: D1 | C24: 2024 | D24: =COUNTIFS('📁 Panel DAES'!$D$3:$D$135,'Cobertura de Datos'!A14, '📁 Panel DAES'!$H$3:$H$135,"<>") -> 11 | E24: =+AVERAGEIF('📁 Panel DAES'!$D$3:$D$135,C24,'📁 Panel DAES'!$H$3:$H$135) -> 751.76796 | F24: {=+MEDIAN(IF('📁 Panel DAES'!$D$3:$D$135=C24,'📁 Panel DAES'!$H$3:$H$135))} -> 251.99392 | G24: {=+_xlfn.STDEV.S(IF('📁 Panel DAES'!$D$3:$D$135='Estadística Descriptiva'!C24,'📁 Panel DAES'!$H$3:$H$135))} -> 1144.2809 | H24: {=+MIN(IF('📁 Panel DAES'!$D$3:$D$135='Estadística Descriptiva'!C24,'📁 Panel DAES'!$H$3:$H$135))} -> 0 | I24: {=+MAX(IF('📁 Panel DAES'!$D$3:$D$135='Estadística Descriptiva'!C24,'📁 Panel DAES'!$H$3:$H$135))} -> 3985.462
A25: DAES | B25: Activos | C25: 2014 | D25: =COUNTIFS('📁 Panel DAES'!$D$3:$D$135,'Cobertura de Datos'!A4, '📁 Panel DAES'!$K$3:$K$135,"<>") -> 2 | E25: =+AVERAGEIF('📁 Panel DAES'!$D$3:$D$135,C25,'📁 Panel DAES'!$K$3:$K$135) -> 613.29897 | F25: {=+MEDIAN(IF('📁 Panel DAES'!$D$3:$D$135=C25,'📁 Panel DAES'!$K$3:$K$135))} -> 613.29897 | G25: {=+_xlfn.STDEV.S(IF('📁 Panel DAES'!$D$3:$D$135='Estadística Descriptiva'!C25,'📁 Panel DAES'!$K$3:$K$135))} -> 791.01848 | H25: {=+MIN(IF('📁 Panel DAES'!$D$3:$D$135='Estadística Descriptiva'!C25,'📁 Panel DAES'!$K$3:$K$135))} -> 53.964438 | I25: {=+MAX(IF('📁 Panel DAES'!$D$3:$D$135='Estadística Descriptiva'!C25,'📁 Panel DAES'!$K$3:$K$135))} -> 1172.6335
A26: DAES | B26: Activos | C26: 2015 | D26: =COUNTIFS('📁 Panel DAES'!$D$3:$D$135,'Cobertura de Datos'!A5, '📁 Panel DAES'!$K$3:$K$135,"<>") -> 7 | E26: =+AVERAGEIF('📁 Panel DAES'!$D$3:$D$135,C26,'📁 Panel DAES'!$K$3:$K$135) -> 4577.1228 | F26: {=+MEDIAN(IF('📁 Panel DAES'!$D$3:$D$135=C26,'📁 Panel DAES'!$K$3:$K$135))} -> 392.55507 | G26: {=+_xlfn.STDEV.S(IF('📁 Panel DAES'!$D$3:$D$135='Estadística Descriptiva'!C26,'📁 Panel DAES'!$K$3:$K$135))} -> 9774.3871 | H26: {=+MIN(IF('📁 Panel DAES'!$D$3:$D$135='Estadística Descriptiva'!C26,'📁 Panel DAES'!$K$3:$K$135))} -> 0 | I26: {=+MAX(IF('📁 Panel DAES'!$D$3:$D$135='Estadística Descriptiva'!C26,'📁 Panel DAES'!$K$3:$K$135))} -> 28146.628
A27: DAES | B27: Activos | C27: 2016 | D27: =COUNTIFS('📁 Panel DAES'!$D$3:$D$135,'Cobertura de Datos'!A6, '📁 Panel DAES'!$K$3:$K$135,"<>") -> 7 | E27: =+AVERAGEIF('📁 Panel DAES'!$D$3:$D$135,C27,'📁 Panel DAES'!$K$3:$K$135) -> 1478.5687 | F27: {=+MEDIAN(IF('📁 Panel DAES'!$D$3:$D$135=C27,'📁 Panel DAES'!$K$3:$K$135))} -> 3.1110745 | G27: {=+_xlfn.STDEV.S(IF('📁 Panel DAES'!$D$3:$D$135='Estadística Descriptiva'!C27,'📁 Panel DAES'!$K$3:$K$135))} -> 2399.1098 | H27: {=+MIN(IF('📁 Panel DAES'!$D$3:$D$135='Estadística Descriptiva'!C27,'📁 Panel DAES'!$K$3:$K$135))} -> 0 | I27: {=+MAX(IF('📁 Panel DAES'!$D$3:$D$135='Estadística Descriptiva'!C27,'📁 Panel DAES'!$K$3:$K$135))} -> 7731.3594
A28: DAES | B28: Activos | C28: 2017 | D28: =COUNTIFS('📁 Panel DAES'!$D$3:$D$135,'Cobertura de Datos'!A7, '📁 Panel DAES'!$K$3:$K$135,"<>") -> 11 | E28: =+AVERAGEIF('📁 Panel DAES'!$D$3:$D$135,C28,'📁 Panel DAES'!$K$3:$K$135) -> 2950.2371 | F28: {=+MEDIAN(IF('📁 Panel DAES'!$D$3:$D$135=C28,'📁 Panel DAES'!$K$3:$K$135))} -> 559.22518 | G28: {=+_xlfn.STDEV.S(IF('📁 Panel DAES'!$D$3:$D$135='Estadística Descriptiva'!C28,'📁 Panel DAES'!$K$3:$K$135))} -> 4344.5356 | H28: {=+MIN(IF('📁 Panel DAES'!$D$3:$D$135='Estadística Descriptiva'!C28,'📁 Panel DAES'!$K$3:$K$135))} -> 0 | I28: {=+MAX(IF('📁 Panel DAES'!$D$3:$D$135='Estadística Descriptiva'!C28,'📁 Panel DAES'!$K$3:$K$135))} -> 15720.697
A29: DAES | B29: Activos | C29: 2018 | D29: =COUNTIFS('📁 Panel DAES'!$D$3:$D$135,'Cobertura de Datos'!A8, '📁 Panel DAES'!$K$3:$K$135,"<>") -> 15 | E29: =+AVERAGEIF('📁 Panel DAES'!$D$3:$D$135,C29,'📁 Panel DAES'!$K$3:$K$135) -> 3455.0456 | F29: {=+MEDIAN(IF('📁 Panel DAES'!$D$3:$D$135=C29,'📁 Panel DAES'!$K$3:$K$135))} -> 1027.7734 | G29: {=+_xlfn.STDEV.S(IF('📁 Panel DAES'!$D$3:$D$135='Estadística Descriptiva'!C29,'📁 Panel DAES'!$K$3:$K$135))} -> 4928.8193 | H29: {=+MIN(IF('📁 Panel DAES'!$D$3:$D$135='Estadística Descriptiva'!C29,'📁 Panel DAES'!$K$3:$K$135))} -> 0 | I29: {=+MAX(IF('📁 Panel DAES'!$D$3:$D$135='Estadística Descriptiva'!C29,'📁 Panel DAES'!$K$3:$K$135))} -> 15924.49
A30: DAES | B30: Activos | C30: 2019 | D30: =COUNTIFS('📁 Panel DAES'!$D$3:$D$135,'Cobertura de Datos'!A9, '📁 Panel DAES'!$K$3:$K$135,"<>") -> 6 | E30: =+AVERAGEIF('📁 Panel DAES'!$D$3:$D$135,C30,'📁 Panel DAES'!$K$3:$K$135) -> 5506.6117 | F30: {=+MEDIAN(IF('📁 Panel DAES'!$D$3:$D$135=C30,'📁 Panel DAES'!$K$3:$K$135))} -> 6182.751 | G30: {=+_xlfn.STDEV.S(IF('📁 Panel DAES'!$D$3:$D$135='Estadística Descriptiva'!C30,'📁 Panel DAES'!$K$3:$K$135))} -> 4478.4007 | H30: {=+MIN(IF('📁 Panel DAES'!$D$3:$D$135='Estadística Descriptiva'!C30,'📁 Panel DAES'!$K$3:$K$135))} -> 3.317151 | I30: {=+MAX(IF('📁 Panel DAES'!$D$3:$D$135='Estadística Descriptiva'!C30,'📁 Panel DAES'!$K$3:$K$135))} -> 12489.058
A31: DAES | B31: Activos | C31: 2020 | D31: =COUNTIFS('📁 Panel DAES'!$D$3:$D$135,'Cobertura de Datos'!A10, '📁 Panel DAES'!$K$3:$K$135,"<>") -> 9 | E31: =+AVERAGEIF('📁 Panel DAES'!$D$3:$D$135,C31,'📁 Panel DAES'!$K$3:$K$135) -> 5233.1915 | F31: {=+MEDIAN(IF('📁 Panel DAES'!$D$3:$D$135=C31,'📁 Panel DAES'!$K$3:$K$135))} -> 2537.7817 | G31: {=+_xlfn.STDEV.S(IF('📁 Panel DAES'!$D$3:$D$135='Estadística Descriptiva'!C31,'📁 Panel DAES'!$K$3:$K$135))} -> 5224.1533 | H31: {=+MIN(IF('📁 Panel DAES'!$D$3:$D$135='Estadística Descriptiva'!C31,'📁 Panel DAES'!$K$3:$K$135))} -> 0 | I31: {=+MAX(IF('📁 Panel DAES'!$D$3:$D$135='Estadística Descriptiva'!C31,'📁 Panel DAES'!$K$3:$K$135))} -> 14013.131
A32: DAES | B32: Activos | C32: 2021 | D32: =COUNTIFS('📁 Panel DAES'!$D$3:$D$135,'Cobertura de Datos'!A11, '📁 Panel DAES'!$K$3:$K$135,"<>") -> 9 | E32: =+AVERAGEIF('📁 Panel DAES'!$D$3:$D$135,C32,'📁 Panel DAES'!$K$3:$K$135) -> 5199.5573 | F32: {=+MEDIAN(IF('📁 Panel DAES'!$D$3:$D$135=C32,'📁 Panel DAES'!$K$3:$K$135))} -> 1941.5712 | G32: {=+_xlfn.STDEV.S(IF('📁 Panel DAES'!$D$3:$D$135='Estadística Descriptiva'!C32,'📁 Panel DAES'!$K$3:$K$135))} -> 5381.645 | H32: {=+MIN(IF('📁 Panel DAES'!$D$3:$D$135='Estadística Descriptiva'!C32,'📁 Panel DAES'!$K$3:$K$135))} -> 0 | I32: {=+MAX(IF('📁 Panel DAES'!$D$3:$D$135='Estadística Descriptiva'!C32,'📁 Panel DAES'!$K$3:$K$135))} -> 17342.469
A33: DAES | B33: Activos | C33: 2022 | D33: =COUNTIFS('📁 Panel DAES'!$D$3:$D$135,'Cobertura de Datos'!A12, '📁 Panel DAES'!$K$3:$K$135,"<>") -> 17 | E33: =+AVERAGEIF('📁 Panel DAES'!$D$3:$D$135,C33,'📁 Panel DAES'!$K$3:$K$135) -> 4975.8035 | F33: {=+MEDIAN(IF('📁 Panel DAES'!$D$3:$D$135=C33,'📁 Panel DAES'!$K$3:$K$135))} -> 2819.4288 | G33: {=+_xlfn.STDEV.S(IF('📁 Panel DAES'!$D$3:$D$135='Estadística Descriptiva'!C33,'📁 Panel DAES'!$K$3:$K$135))} -> 4451.9804 | H33: {=+MIN(IF('📁 Panel DAES'!$D$3:$D$135='Estadística Descriptiva'!C33,'📁 Panel DAES'!$K$3:$K$135))} -> 0 | I33: {=+MAX(IF('📁 Panel DAES'!$D$3:$D$135='Estadística Descriptiva'!C33,'📁 Panel DAES'!$K$3:$K$135))} -> 15117.112
A34: DAES | B34: Activos | C34: 2023 | D34: =COUNTIFS('📁 Panel DAES'!$D$3:$D$135,'Cobertura de Datos'!A13, '📁 Panel DAES'!$K$3:$K$135,"<>") -> 22 | E34: =+AVERAGEIF('📁 Panel DAES'!$D$3:$D$135,C34,'📁 Panel DAES'!$K$3:$K$135) -> 7541.1514 | F34: {=+MEDIAN(IF('📁 Panel DAES'!$D$3:$D$135=C34,'📁 Panel DAES'!$K$3:$K$135))} -> 3692.0319 | G34: {=+_xlfn.STDEV.S(IF('📁 Panel DAES'!$D$3:$D$135='Estadística Descriptiva'!C34,'📁 Panel DAES'!$K$3:$K$135))} -> 8863.5066 | H34: {=+MIN(IF('📁 Panel DAES'!$D$3:$D$135='Estadística Descriptiva'!C34,'📁 Panel DAES'!$K$3:$K$135))} -> 0 | I34: {=+MAX(IF('📁 Panel DAES'!$D$3:$D$135='Estadística Descriptiva'!C34,'📁 Panel DAES'!$K$3:$K$135))} -> 40048.604
A35: DAES | B35: Activos | C35: 2024 | D35: =COUNTIFS('📁 Panel DAES'!$D$3:$D$135,'Cobertura de Datos'!A14, '📁 Panel DAES'!$K$3:$K$135,"<>") -> 12 | E35: =+AVERAGEIF('📁 Panel DAES'!$D$3:$D$135,C35,'📁 Panel DAES'!$K$3:$K$135) -> 8993.5581 | F35: {=+MEDIAN(IF('📁 Panel DAES'!$D$3:$D$135=C35,'📁 Panel DAES'!$K$3:$K$135))} -> 4590.4825 | G35: {=+_xlfn.STDEV.S(IF('📁 Panel DAES'!$D$3:$D$135='Estadística Descriptiva'!C35,'📁 Panel DAES'!$K$3:$K$135))} -> 11339.012 | H35: {=+MIN(IF('📁 Panel DAES'!$D$3:$D$135='Estadística Descriptiva'!C35,'📁 Panel DAES'!$K$3:$K$135))} -> 42.551814 | I35: {=+MAX(IF('📁 Panel DAES'!$D$3:$D$135='Estadística Descriptiva'!C35,'📁 Panel DAES'!$K$3:$K$135))} -> 41370.8
A36: DAES | B36: Patrimonio | C36: 2014 | D36: =COUNTIFS('📁 Panel DAES'!$D$3:$D$135,'Cobertura de Datos'!A4, '📁 Panel DAES'!$L$3:$L$135,"<>") -> 2 | E36: =+AVERAGEIF('📁 Panel DAES'!$D$3:$D$135,C36,'📁 Panel DAES'!$L$3:$L$135) -> 566.26047 | F36: {=+MEDIAN(IF('📁 Panel DAES'!$D$3:$D$135=C36,'📁 Panel DAES'!$L$3:$L$135))} -> 566.26047 | G36: {=+_xlfn.STDEV.S(IF('📁 Panel DAES'!$D$3:$D$135='Estadística Descriptiva'!C36,'📁 Panel DAES'!$L$3:$L$135))} -> 773.84664 | H36: {=+MIN(IF('📁 Panel DAES'!$D$3:$D$135='Estadística Descriptiva'!C36,'📁 Panel DAES'!$L$3:$L$135))} -> 19.068257 | I36: {=+MAX(IF('📁 Panel DAES'!$D$3:$D$135='Estadística Descriptiva'!C36,'📁 Panel DAES'!$L$3:$L$135))} -> 1113.4527
A37: DAES | B37: Patrimonio | C37: 2015 | D37: =COUNTIFS('📁 Panel DAES'!$D$3:$D$135,'Cobertura de Datos'!A5, '📁 Panel DAES'!$L$3:$L$135,"<>") -> 7 | E37: =+AVERAGEIF('📁 Panel DAES'!$D$3:$D$135,C37,'📁 Panel DAES'!$L$3:$L$135) -> 3823.1592 | F37: {=+MEDIAN(IF('📁 Panel DAES'!$D$3:$D$135=C37,'📁 Panel DAES'!$L$3:$L$135))} -> 379.71975 | G37: {=+_xlfn.STDEV.S(IF('📁 Panel DAES'!$D$3:$D$135='Estadística Descriptiva'!C37,'📁 Panel DAES'!$L$3:$L$135))} -> 8246.0566 | H37: {=+MIN(IF('📁 Panel DAES'!$D$3:$D$135='Estadística Descriptiva'!C37,'📁 Panel DAES'!$L$3:$L$135))} -> 0 | I37: {=+MAX(IF('📁 Panel DAES'!$D$3:$D$135='Estadística Descriptiva'!C37,'📁 Panel DAES'!$L$3:$L$135))} -> 23719.671
A38: DAES | B38: Patrimonio | C38: 2016 | D38: =COUNTIFS('📁 Panel DAES'!$D$3:$D$135,'Cobertura de Datos'!A6, '📁 Panel DAES'!$L$3:$L$135,"<>") -> 7 | E38: =+AVERAGEIF('📁 Panel DAES'!$D$3:$D$135,C38,'📁 Panel DAES'!$L$3:$L$135) -> 668.65743 | F38: {=+MEDIAN(IF('📁 Panel DAES'!$D$3:$D$135=C38,'📁 Panel DAES'!$L$3:$L$135))} -> 1.1486485 | G38: {=+_xlfn.STDEV.S(IF('📁 Panel DAES'!$D$3:$D$135='Estadística Descriptiva'!C38,'📁 Panel DAES'!$L$3:$L$135))} -> 790.93578 | H38: {=+MIN(IF('📁 Panel DAES'!$D$3:$D$135='Estadística Descriptiva'!C38,'📁 Panel DAES'!$L$3:$L$135))} -> 0 | I38: {=+MAX(IF('📁 Panel DAES'!$D$3:$D$135='Estadística Descriptiva'!C38,'📁 Panel DAES'!$L$3:$L$135))} -> 2370.6909
A39: DAES | B39: Patrimonio | C39: 2017 | D39: =COUNTIFS('📁 Panel DAES'!$D$3:$D$135,'Cobertura de Datos'!A7, '📁 Panel DAES'!$L$3:$L$135,"<>") -> 11 | E39: =+AVERAGEIF('📁 Panel DAES'!$D$3:$D$135,C39,'📁 Panel DAES'!$L$3:$L$135) -> 1575.4663 | F39: {=+MEDIAN(IF('📁 Panel DAES'!$D$3:$D$135=C39,'📁 Panel DAES'!$L$3:$L$135))} -> 383.08579 | G39: {=+_xlfn.STDEV.S(IF('📁 Panel DAES'!$D$3:$D$135='Estadística Descriptiva'!C39,'📁 Panel DAES'!$L$3:$L$135))} -> 2197.2655 | H39: {=+MIN(IF('📁 Panel DAES'!$D$3:$D$135='Estadística Descriptiva'!C39,'📁 Panel DAES'!$L$3:$L$135))} -> 0 | I39: {=+MAX(IF('📁 Panel DAES'!$D$3:$D$135='Estadística Descriptiva'!C39,'📁 Panel DAES'!$L$3:$L$135))} -> 8261.1877
A40: DAES | B40: Patrimonio | C40: 2018 | D40: =COUNTIFS('📁 Panel DAES'!$D$3:$D$135,'Cobertura de Datos'!A8, '📁 Panel DAES'!$L$3:$L$135,"<>") -> 14 | E40: =+AVERAGEIF('📁 Panel DAES'!$D$3:$D$135,C40,'📁 Panel DAES'!$L$3:$L$135) -> 1384.453 | F40: {=+MEDIAN(IF('📁 Panel DAES'!$D$3:$D$135=C40,'📁 Panel DAES'!$L$3:$L$135))} -> 491.24374 | G40: {=+_xlfn.STDEV.S(IF('📁 Panel DAES'!$D$3:$D$135='Estadística Descriptiva'!C40,'📁 Panel DAES'!$L$3:$L$135))} -> 2193.6118 | H40: {=+MIN(IF('📁 Panel DAES'!$D$3:$D$135='Estadística Descriptiva'!C40,'📁 Panel DAES'!$L$3:$L$135))} -> 0 | I40: {=+MAX(IF('📁 Panel DAES'!$D$3:$D$135='Estadística Descriptiva'!C40,'📁 Panel DAES'!$L$3:$L$135))} -> 8477.3638
A41: DAES | B41: Patrimonio | C41: 2019 | D41: =COUNTIFS('📁 Panel DAES'!$D$3:$D$135,'Cobertura de Datos'!A9, '📁 Panel DAES'!$L$3:$L$135,"<>") -> 6 | E41: =+AVERAGEIF('📁 Panel DAES'!$D$3:$D$135,C41,'📁 Panel DAES'!$L$3:$L$135) -> 2482.2662 | F41: {=+MEDIAN(IF('📁 Panel DAES'!$D$3:$D$135=C41,'📁 Panel DAES'!$L$3:$L$135))} -> 1133.2454 | G41: {=+_xlfn.STDEV.S(IF('📁 Panel DAES'!$D$3:$D$135='Estadística Descriptiva'!C41,'📁 Panel DAES'!$L$3:$L$135))} -> 2777.4276 | H41: {=+MIN(IF('📁 Panel DAES'!$D$3:$D$135='Estadística Descriptiva'!C41,'📁 Panel DAES'!$L$3:$L$135))} -> 1.388231 | I41: {=+MAX(IF('📁 Panel DAES'!$D$3:$D$135='Estadística Descriptiva'!C41,'📁 Panel DAES'!$L$3:$L$135))} -> 6660.1537
A42: DAES | B42: Patrimonio | C42: 2020 | D42: =COUNTIFS('📁 Panel DAES'!$D$3:$D$135,'Cobertura de Datos'!A10, '📁 Panel DAES'!$L$3:$L$135,"<>") -> 9 | E42: =+AVERAGEIF('📁 Panel DAES'!$D$3:$D$135,C42,'📁 Panel DAES'!$L$3:$L$135) -> 2626.632 | F42: {=+MEDIAN(IF('📁 Panel DAES'!$D$3:$D$135=C42,'📁 Panel DAES'!$L$3:$L$135))} -> 1225.8241 | G42: {=+_xlfn.STDEV.S(IF('📁 Panel DAES'!$D$3:$D$135='Estadística Descriptiva'!C42,'📁 Panel DAES'!$L$3:$L$135))} -> 2691.4513 | H42: {=+MIN(IF('📁 Panel DAES'!$D$3:$D$135='Estadística Descriptiva'!C42,'📁 Panel DAES'!$L$3:$L$135))} -> 0 | I42: {=+MAX(IF('📁 Panel DAES'!$D$3:$D$135='Estadística Descriptiva'!C42,'📁 Panel DAES'!$L$3:$L$135))} -> 6783.906
A43: DAES | B43: Patrimonio | C43: 2021 | D43: =COUNTIFS('📁 Panel DAES'!$D$3:$D$135,'Cobertura de Datos'!A11, '📁 Panel DAES'!$L$3:$L$135,"<>") -> 9 | E43: =+AVERAGEIF('📁 Panel DAES'!$D$3:$D$135,C43,'📁 Panel DAES'!$L$3:$L$135) -> 2789.2937 | F43: {=+MEDIAN(IF('📁 Panel DAES'!$D$3:$D$135=C43,'📁 Panel DAES'!$L$3:$L$135))} -> 1336.7627 | G43: {=+_xlfn.STDEV.S(IF('📁 Panel DAES'!$D$3:$D$135='Estadística Descriptiva'!C43,'📁 Panel DAES'!$L$3:$L$135))} -> 2843.784 | H43: {=+MIN(IF('📁 Panel DAES'!$D$3:$D$135='Estadística Descriptiva'!C43,'📁 Panel DAES'!$L$3:$L$135))} -> 0 | I43: {=+MAX(IF('📁 Panel DAES'!$D$3:$D$135='Estadística Descriptiva'!C43,'📁 Panel DAES'!$L$3:$L$135))} -> 7440.152
A44: DAES | B44: Patrimonio | C44: 2022 | D44: =COUNTIFS('📁 Panel DAES'!$D$3:$D$135,'Cobertura de Datos'!A12, '📁 Panel DAES'!$L$3:$L$135,"<>") -> 17 | E44: =+AVERAGEIF('📁 Panel DAES'!$D$3:$D$135,C44,'📁 Panel DAES'!$L$3:$L$135) -> 2724.2012 | F44: {=+MEDIAN(IF('📁 Panel DAES'!$D$3:$D$135=C44,'📁 Panel DAES'!$L$3:$L$135))} -> 1532.6451 | G44: {=+_xlfn.STDEV.S(IF('📁 Panel DAES'!$D$3:$D$135='Estadística Descriptiva'!C44,'📁 Panel DAES'!$L$3:$L$135))} -> 2515.7355 | H44: {=+MIN(IF('📁 Panel DAES'!$D$3:$D$135='Estadística Descriptiva'!C44,'📁 Panel DAES'!$L$3:$L$135))} -> 0 | I44: {=+MAX(IF('📁 Panel DAES'!$D$3:$D$135='Estadística Descriptiva'!C44,'📁 Panel DAES'!$L$3:$L$135))} -> 8289.0517
A45: DAES | B45: Patrimonio | C45: 2023 | D45: =COUNTIFS('📁 Panel DAES'!$D$3:$D$135,'Cobertura de Datos'!A13, '📁 Panel DAES'!$L$3:$L$135,"<>") -> 22 | E45: =+AVERAGEIF('📁 Panel DAES'!$D$3:$D$135,C45,'📁 Panel DAES'!$L$3:$L$135) -> 3257.0892 | F45: {=+MEDIAN(IF('📁 Panel DAES'!$D$3:$D$135=C45,'📁 Panel DAES'!$L$3:$L$135))} -> 1516.0313 | G45: {=+_xlfn.STDEV.S(IF('📁 Panel DAES'!$D$3:$D$135='Estadística Descriptiva'!C45,'📁 Panel DAES'!$L$3:$L$135))} -> 3038.0597 | H45: {=+MIN(IF('📁 Panel DAES'!$D$3:$D$135='Estadística Descriptiva'!C45,'📁 Panel DAES'!$L$3:$L$135))} -> 0 | I45: {=+MAX(IF('📁 Panel DAES'!$D$3:$D$135='Estadística Descriptiva'!C45,'📁 Panel DAES'!$L$3:$L$135))} -> 9413.563
A46: DAES | B46: Patrimonio | C46: 2024 | D46: =COUNTIFS('📁 Panel DAES'!$D$3:$D$135,'Cobertura de Datos'!A14, '📁 Panel DAES'!$L$3:$L$135,"<>") -> 12 | E46: =+AVERAGEIF('📁 Panel DAES'!$D$3:$D$135,C46,'📁 Panel DAES'!$L$3:$L$135) -> 3692.6634 | F46: {=+MEDIAN(IF('📁 Panel DAES'!$D$3:$D$135=C46,'📁 Panel DAES'!$L$3:$L$135))} -> 2743.3375 | G46: {=+_xlfn.STDEV.S(IF('📁 Panel DAES'!$D$3:$D$135='Estadística Descriptiva'!C46,'📁 Panel DAES'!$L$3:$L$135))} -> 3143.127 | H46: {=+MIN(IF('📁 Panel DAES'!$D$3:$D$135='Estadística Descriptiva'!C46,'📁 Panel DAES'!$L$3:$L$135))} -> 4.076304 | I46: {=+MAX(IF('📁 Panel DAES'!$D$3:$D$135='Estadística Descriptiva'!C46,'📁 Panel DAES'!$L$3:$L$135))} -> 10163.465
A47: DAES | B47: F2 | C47: 2014 | D47: =COUNTIFS('📁 Panel DAES'!$D$3:$D$135,'Cobertura de Datos'!A4, '📁 Panel DAES'!$M$3:$M$135,"<>") -> 2 | E47: =+AVERAGEIF('📁 Panel DAES'!$D$3:$D$135,C47,'📁 Panel DAES'!$M$3:$M$135) -> 36.311861 | F47: {=+MEDIAN(IF('📁 Panel DAES'!$D$3:$D$135=C47,'📁 Panel DAES'!$M$3:$M$135))} -> 36.311861 | G47: {=+_xlfn.STDEV.S(IF('📁 Panel DAES'!$D$3:$D$135='Estadística Descriptiva'!C47,'📁 Panel DAES'!$M$3:$M$135))} -> 4.6647622 | H47: {=+MIN(IF('📁 Panel DAES'!$D$3:$D$135='Estadística Descriptiva'!C47,'📁 Panel DAES'!$M$3:$M$135))} -> 33.013376 | I47: {=+MAX(IF('📁 Panel DAES'!$D$3:$D$135='Estadística Descriptiva'!C47,'📁 Panel DAES'!$M$3:$M$135))} -> 39.610346
A48: DAES | B48: F2 | C48: 2015 | D48: =COUNTIFS('📁 Panel DAES'!$D$3:$D$135,'Cobertura de Datos'!A5, '📁 Panel DAES'!$M$3:$M$135,"<>") -> 7 | E48: =+AVERAGEIF('📁 Panel DAES'!$D$3:$D$135,C48,'📁 Panel DAES'!$M$3:$M$135) -> 713.80922 | F48: {=+MEDIAN(IF('📁 Panel DAES'!$D$3:$D$135=C48,'📁 Panel DAES'!$M$3:$M$135))} -> 32.397901 | G48: {=+_xlfn.STDEV.S(IF('📁 Panel DAES'!$D$3:$D$135='Estadística Descriptiva'!C48,'📁 Panel DAES'!$M$3:$M$135))} -> 1460.0921 | H48: {=+MIN(IF('📁 Panel DAES'!$D$3:$D$135='Estadística Descriptiva'!C48,'📁 Panel DAES'!$M$3:$M$135))} -> 0 | I48: {=+MAX(IF('📁 Panel DAES'!$D$3:$D$135='Estadística Descriptiva'!C48,'📁 Panel DAES'!$M$3:$M$135))} -> 4202.1048
A49: DAES | B49: F2 | C49: 2016 | D49: =COUNTIFS('📁 Panel DAES'!$D$3:$D$135,'Cobertura de Datos'!A6, '📁 Panel DAES'!$M$3:$M$135,"<>") -> 7 | E49: =+AVERAGEIF('📁 Panel DAES'!$D$3:$D$135,C49,'📁 Panel DAES'!$M$3:$M$135) -> 722.95278 | F49: {=+MEDIAN(IF('📁 Panel DAES'!$D$3:$D$135=C49,'📁 Panel DAES'!$M$3:$M$135))} -> 1.9520315 | G49: {=+_xlfn.STDEV.S(IF('📁 Panel DAES'!$D$3:$D$135='Estadística Descriptiva'!C49,'📁 Panel DAES'!$M$3:$M$135))} -> 1504.3253 | H49: {=+MIN(IF('📁 Panel DAES'!$D$3:$D$135='Estadística Descriptiva'!C49,'📁 Panel DAES'!$M$3:$M$135))} -> 0 | I49: {=+MAX(IF('📁 Panel DAES'!$D$3:$D$135='Estadística Descriptiva'!C49,'📁 Panel DAES'!$M$3:$M$135))} -> 4783.8802
A50: DAES | B50: F2 | C50: 2017 | D50: =COUNTIFS('📁 Panel DAES'!$D$3:$D$135,'Cobertura de Datos'!A7, '📁 Panel DAES'!$M$3:$M$135,"<>") -> 8 | E50: =+AVERAGEIF('📁 Panel DAES'!$D$3:$D$135,C50,'📁 Panel DAES'!$M$3:$M$135) -> 1091.6672 | F50: {=+MEDIAN(IF('📁 Panel DAES'!$D$3:$D$135=C50,'📁 Panel DAES'!$M$3:$M$135))} -> 1.2249815 | G50: {=+_xlfn.STDEV.S(IF('📁 Panel DAES'!$D$3:$D$135='Estadística Descriptiva'!C50,'📁 Panel DAES'!$M$3:$M$135))} -> 1280.5416 | H50: {=+MIN(IF('📁 Panel DAES'!$D$3:$D$135='Estadística Descriptiva'!C50,'📁 Panel DAES'!$M$3:$M$135))} -> 0 | I50: {=+MAX(IF('📁 Panel DAES'!$D$3:$D$135='Estadística Descriptiva'!C50,'📁 Panel DAES'!$M$3:$M$135))} -> 4177.837
A51: DAES | B51: F2 | C51: 2018 | D51: =COUNTIFS('📁 Panel DAES'!$D$3:$D$135,'Cobertura de Datos'!A8, '📁 Panel DAES'!$M$3:$M$135,"<>") -> 11 | E51: =+AVERAGEIF('📁 Panel DAES'!$D$3:$D$135,C51,'📁 Panel DAES'!$M$3:$M$135) -> 1147.2631 | F51: {=+MEDIAN(IF('📁 Panel DAES'!$D$3:$D$135=C51,'📁 Panel DAES'!$M$3:$M$135))} -> 33.258277 | G51: {=+_xlfn.STDEV.S(IF('📁 Panel DAES'!$D$3:$D$135='Estadística Descriptiva'!C51,'📁 Panel DAES'!$M$3:$M$135))} -> 1362.1091 | H51: {=+MIN(IF('📁 Panel DAES'!$D$3:$D$135='Estadística Descriptiva'!C51,'📁 Panel DAES'!$M$3:$M$135))} -> 0 | I51: {=+MAX(IF('📁 Panel DAES'!$D$3:$D$135='Estadística Descriptiva'!C51,'📁 Panel DAES'!$M$3:$M$135))} -> 4014.9295
A52: DAES | B52: F2 | C52: 2019 | D52: =COUNTIFS('📁 Panel DAES'!$D$3:$D$135,'Cobertura de Datos'!A9, '📁 Panel DAES'!$M$3:$M$135,"<>") -> 6 | E52: =+AVERAGEIF('📁 Panel DAES'!$D$3:$D$135,C52,'📁 Panel DAES'!$M$3:$M$135) -> 2564.5126 | F52: {=+MEDIAN(IF('📁 Panel DAES'!$D$3:$D$135=C52,'📁 Panel DAES'!$M$3:$M$135))} -> 2274.9676 | G52: {=+_xlfn.STDEV.S(IF('📁 Panel DAES'!$D$3:$D$135='Estadística Descriptiva'!C52,'📁 Panel DAES'!$M$3:$M$135))} -> 2790.8768 | H52: {=+MIN(IF('📁 Panel DAES'!$D$3:$D$135='Estadística Descriptiva'!C52,'📁 Panel DAES'!$M$3:$M$135))} -> 1.246578 | I52: {=+MAX(IF('📁 Panel DAES'!$D$3:$D$135='Estadística Descriptiva'!C52,'📁 Panel DAES'!$M$3:$M$135))} -> 5618.2172
A53: DAES | B53: F2 | C53: 2020 | D53: =COUNTIFS('📁 Panel DAES'!$D$3:$D$135,'Cobertura de Datos'!A10, '📁 Panel DAES'!$M$3:$M$135,"<>") -> 9 | E53: =+AVERAGEIF('📁 Panel DAES'!$D$3:$D$135,C53,'📁 Panel DAES'!$M$3:$M$135) -> 2367.3396 | F53: {=+MEDIAN(IF('📁 Panel DAES'!$D$3:$D$135=C53,'📁 Panel DAES'!$M$3:$M$135))} -> 517.07151 | G53: {=+_xlfn.STDEV.S(IF('📁 Panel DAES'!$D$3:$D$135='Estadística Descriptiva'!C53,'📁 Panel DAES'!$M$3:$M$135))} -> 2949.497 | H53: {=+MIN(IF('📁 Panel DAES'!$D$3:$D$135='Estadística Descriptiva'!C53,'📁 Panel DAES'!$M$3:$M$135))} -> 0 | I53: {=+MAX(IF('📁 Panel DAES'!$D$3:$D$135='Estadística Descriptiva'!C53,'📁 Panel DAES'!$M$3:$M$135))} -> 6590.1232
A54: DAES | B54: F2 | C54: 2021 | D54: =COUNTIFS('📁 Panel DAES'!$D$3:$D$135,'Cobertura de Datos'!A11, '📁 Panel DAES'!$M$3:$M$135,"<>") -> 9 | E54: =+AVERAGEIF('📁 Panel DAES'!$D$3:$D$135,C54,'📁 Panel DAES'!$M$3:$M$135) -> 2188.1621 | F54: {=+MEDIAN(IF('📁 Panel DAES'!$D$3:$D$135=C54,'📁 Panel DAES'!$M$3:$M$135))} -> 74.755298 | G54: {=+_xlfn.STDEV.S(IF('📁 Panel DAES'!$D$3:$D$135='Estadística Descriptiva'!C54,'📁 Panel DAES'!$M$3:$M$135))} -> 2880.0777 | H54: {=+MIN(IF('📁 Panel DAES'!$D$3:$D$135='Estadística Descriptiva'!C54,'📁 Panel DAES'!$M$3:$M$135))} -> 0 | I54: {=+MAX(IF('📁 Panel DAES'!$D$3:$D$135='Estadística Descriptiva'!C54,'📁 Panel DAES'!$M$3:$M$135))} -> 8471.075
A55: DAES | B55: F2 | C55: 2022 | D55: =COUNTIFS('📁 Panel DAES'!$D$3:$D$135,'Cobertura de Datos'!A12, '📁 Panel DAES'!$M$3:$M$135,"<>") -> 16 | E55: =+AVERAGEIF('📁 Panel DAES'!$D$3:$D$135,C55,'📁 Panel DAES'!$M$3:$M$135) -> 2134.0894 | F55: {=+MEDIAN(IF('📁 Panel DAES'!$D$3:$D$135=C55,'📁 Panel DAES'!$M$3:$M$135))} -> 860.00942 | G55: {=+_xlfn.STDEV.S(IF('📁 Panel DAES'!$D$3:$D$135='Estadística Descriptiva'!C55,'📁 Panel DAES'!$M$3:$M$135))} -> 2236.8127 | H55: {=+MIN(IF('📁 Panel DAES'!$D$3:$D$135='Estadística Descriptiva'!C55,'📁 Panel DAES'!$M$3:$M$135))} -> 0 | I55: {=+MAX(IF('📁 Panel DAES'!$D$3:$D$135='Estadística Descriptiva'!C55,'📁 Panel DAES'!$M$3:$M$135))} -> 7271.1128
A56: DAES | B56: F2 | C56: 2023 | D56: =COUNTIFS('📁 Panel DAES'!$D$3:$D$135,'Cobertura de Datos'!A13, '📁 Panel DAES'!$M$3:$M$135,"<>") -> 20 | E56: =+AVERAGEIF('📁 Panel DAES'!$D$3:$D$135,C56,'📁 Panel DAES'!$M$3:$M$135) -> 4367.6574 | F56: {=+MEDIAN(IF('📁 Panel DAES'!$D$3:$D$135=C56,'📁 Panel DAES'!$M$3:$M$135))} -> 867.81257 | G56: {=+_xlfn.STDEV.S(IF('📁 Panel DAES'!$D$3:$D$135='Estadística Descriptiva'!C56,'📁 Panel DAES'!$M$3:$M$135))} -> 6067.5045 | H56: {=+MIN(IF('📁 Panel DAES'!$D$3:$D$135='Estadística Descriptiva'!C56,'📁 Panel DAES'!$M$3:$M$135))} -> 0 | I56: {=+MAX(IF('📁 Panel DAES'!$D$3:$D$135='Estadística Descriptiva'!C56,'📁 Panel DAES'!$M$3:$M$135))} -> 26433.091
A57: DAES | B57: F2 | C57: 2024 | D57: =COUNTIFS('📁 Panel DAES'!$D$3:$D$135,'Cobertura de Datos'!A14, '📁 Panel DAES'!$M$3:$M$135,"<>") -> 11 | E57: =+AVERAGEIF('📁 Panel DAES'!$D$3:$D$135,C57,'📁 Panel DAES'!$M$3:$M$135) -> 5436.2639 | F57: {=+MEDIAN(IF('📁 Panel DAES'!$D$3:$D$135=C57,'📁 Panel DAES'!$M$3:$M$135))} -> 2163.1368 | G57: {=+_xlfn.STDEV.S(IF('📁 Panel DAES'!$D$3:$D$135='Estadística Descriptiva'!C57,'📁 Panel DAES'!$M$3:$M$135))} -> 8041.4849 | H57: {=+MIN(IF('📁 Panel DAES'!$D$3:$D$135='Estadística Descriptiva'!C57,'📁 Panel DAES'!$M$3:$M$135))} -> 0 | I57: {=+MAX(IF('📁 Panel DAES'!$D$3:$D$135='Estadística Descriptiva'!C57,'📁 Panel DAES'!$M$3:$M$135))} -> 28369.726
A58: DAES | B58: F4 | C58: 2014 | D58: =COUNTIFS('📁 Panel DAES'!$D$3:$D$135,'Cobertura de Datos'!A4, '📁 Panel DAES'!$N$3:$N$135,"<>") -> 2 | E58: =+AVERAGEIF('📁 Panel DAES'!$D$3:$D$135,C58,'📁 Panel DAES'!$N$3:$N$135) -> 423.67558 | F58: {=+MEDIAN(IF('📁 Panel DAES'!$D$3:$D$135=C58,'📁 Panel DAES'!$N$3:$N$135))} -> 423.67558 | G58: {=+_xlfn.STDEV.S(IF('📁 Panel DAES'!$D$3:$D$135='Estadística Descriptiva'!C58,'📁 Panel DAES'!$N$3:$N$135))} -> 562.2286 | H58: {=+MIN(IF('📁 Panel DAES'!$D$3:$D$135='Estadística Descriptiva'!C58,'📁 Panel DAES'!$N$3:$N$135))} -> 26.119924 | I58: {=+MAX(IF('📁 Panel DAES'!$D$3:$D$135='Estadística Descriptiva'!C58,'📁 Panel DAES'!$N$3:$N$135))} -> 821.23124
A59: DAES | B59: F4 | C59: 2015 | D59: =COUNTIFS('📁 Panel DAES'!$D$3:$D$135,'Cobertura de Datos'!A5, '📁 Panel DAES'!$N$3:$N$135,"<>") -> 7 | E59: =+AVERAGEIF('📁 Panel DAES'!$D$3:$D$135,C59,'📁 Panel DAES'!$N$3:$N$135) -> 3426.8843 | F59: {=+MEDIAN(IF('📁 Panel DAES'!$D$3:$D$135=C59,'📁 Panel DAES'!$N$3:$N$135))} -> 253.17385 | G59: {=+_xlfn.STDEV.S(IF('📁 Panel DAES'!$D$3:$D$135='Estadística Descriptiva'!C59,'📁 Panel DAES'!$N$3:$N$135))} -> 7380.332 | H59: {=+MIN(IF('📁 Panel DAES'!$D$3:$D$135='Estadística Descriptiva'!C59,'📁 Panel DAES'!$N$3:$N$135))} -> 0 | I59: {=+MAX(IF('📁 Panel DAES'!$D$3:$D$135='Estadística Descriptiva'!C59,'📁 Panel DAES'!$N$3:$N$135))} -> 21229.854
A60: DAES | B60: F4 | C60: 2016 | D60: =COUNTIFS('📁 Panel DAES'!$D$3:$D$135,'Cobertura de Datos'!A6, '📁 Panel DAES'!$N$3:$N$135,"<>") -> 7 | E60: =+AVERAGEIF('📁 Panel DAES'!$D$3:$D$135,C60,'📁 Panel DAES'!$N$3:$N$135) -> 1039.5262 | F60: {=+MEDIAN(IF('📁 Panel DAES'!$D$3:$D$135=C60,'📁 Panel DAES'!$N$3:$N$135))} -> 2.7196605 | G60: {=+_xlfn.STDEV.S(IF('📁 Panel DAES'!$D$3:$D$135='Estadística Descriptiva'!C60,'📁 Panel DAES'!$N$3:$N$135))} -> 1709.0904 | H60: {=+MIN(IF('📁 Panel DAES'!$D$3:$D$135='Estadística Descriptiva'!C60,'📁 Panel DAES'!$N$3:$N$135))} -> 0 | I60: {=+MAX(IF('📁 Panel DAES'!$D$3:$D$135='Estadística Descriptiva'!C60,'📁 Panel DAES'!$N$3:$N$135))} -> 5505.8147
A61: DAES | B61: F4 | C61: 2017 | D61: =COUNTIFS('📁 Panel DAES'!$D$3:$D$135,'Cobertura de Datos'!A7, '📁 Panel DAES'!$N$3:$N$135,"<>") -> 8 | E61: =+AVERAGEIF('📁 Panel DAES'!$D$3:$D$135,C61,'📁 Panel DAES'!$N$3:$N$135) -> 1909.7972 | F61: {=+MEDIAN(IF('📁 Panel DAES'!$D$3:$D$135=C61,'📁 Panel DAES'!$N$3:$N$135))} -> 99.446804 | G61: {=+_xlfn.STDEV.S(IF('📁 Panel DAES'!$D$3:$D$135='Estadística Descriptiva'!C61,'📁 Panel DAES'!$N$3:$N$135))} -> 2288.4144 | H61: {=+MIN(IF('📁 Panel DAES'!$D$3:$D$135='Estadística Descriptiva'!C61,'📁 Panel DAES'!$N$3:$N$135))} -> 0 | I61: {=+MAX(IF('📁 Panel DAES'!$D$3:$D$135='Estadística Descriptiva'!C61,'📁 Panel DAES'!$N$3:$N$135))} -> 8472.8268
A62: DAES | B62: F4 | C62: 2018 | D62: =COUNTIFS('📁 Panel DAES'!$D$3:$D$135,'Cobertura de Datos'!A8, '📁 Panel DAES'!$N$3:$N$135,"<>") -> 12 | E62: =+AVERAGEIF('📁 Panel DAES'!$D$3:$D$135,C62,'📁 Panel DAES'!$N$3:$N$135) -> 2477.745 | F62: {=+MEDIAN(IF('📁 Panel DAES'!$D$3:$D$135=C62,'📁 Panel DAES'!$N$3:$N$135))} -> 519.13248 | G62: {=+_xlfn.STDEV.S(IF('📁 Panel DAES'!$D$3:$D$135='Estadística Descriptiva'!C62,'📁 Panel DAES'!$N$3:$N$135))} -> 3342.638 | H62: {=+MIN(IF('📁 Panel DAES'!$D$3:$D$135='Estadística Descriptiva'!C62,'📁 Panel DAES'!$N$3:$N$135))} -> 0 | I62: {=+MAX(IF('📁 Panel DAES'!$D$3:$D$135='Estadística Descriptiva'!C62,'📁 Panel DAES'!$N$3:$N$135))} -> 11600.089
A63: DAES | B63: F4 | C63: 2019 | D63: =COUNTIFS('📁 Panel DAES'!$D$3:$D$135,'Cobertura de Datos'!A9, '📁 Panel DAES'!$N$3:$N$135,"<>") -> 6 | E63: =+AVERAGEIF('📁 Panel DAES'!$D$3:$D$135,C63,'📁 Panel DAES'!$N$3:$N$135) -> 3936.3419 | F63: {=+MEDIAN(IF('📁 Panel DAES'!$D$3:$D$135=C63,'📁 Panel DAES'!$N$3:$N$135))} -> 4177.3744 | G63: {=+_xlfn.STDEV.S(IF('📁 Panel DAES'!$D$3:$D$135='Estadística Descriptiva'!C63,'📁 Panel DAES'!$N$3:$N$135))} -> 3346.0874 | H63: {=+MIN(IF('📁 Panel DAES'!$D$3:$D$135='Estadística Descriptiva'!C63,'📁 Panel DAES'!$N$3:$N$135))} -> 2.805438 | I63: {=+MAX(IF('📁 Panel DAES'!$D$3:$D$135='Estadística Descriptiva'!C63,'📁 Panel DAES'!$N$3:$N$135))} -> 9199.1197
A64: DAES | B64: F4 | C64: 2020 | D64: =COUNTIFS('📁 Panel DAES'!$D$3:$D$135,'Cobertura de Datos'!A10, '📁 Panel DAES'!$N$3:$N$135,"<>") -> 9 | E64: =+AVERAGEIF('📁 Panel DAES'!$D$3:$D$135,C64,'📁 Panel DAES'!$N$3:$N$135) -> 3051.3436 | F64: {=+MEDIAN(IF('📁 Panel DAES'!$D$3:$D$135=C64,'📁 Panel DAES'!$N$3:$N$135))} -> 1801.2299 | G64: {=+_xlfn.STDEV.S(IF('📁 Panel DAES'!$D$3:$D$135='Estadística Descriptiva'!C64,'📁 Panel DAES'!$N$3:$N$135))} -> 3156.6621 | H64: {=+MIN(IF('📁 Panel DAES'!$D$3:$D$135='Estadística Descriptiva'!C64,'📁 Panel DAES'!$N$3:$N$135))} -> 0 | I64: {=+MAX(IF('📁 Panel DAES'!$D$3:$D$135='Estadística Descriptiva'!C64,'📁 Panel DAES'!$N$3:$N$135))} -> 10029.748
A65: DAES | B65: F4 | C65: 2021 | D65: =COUNTIFS('📁 Panel DAES'!$D$3:$D$135,'Cobertura de Datos'!A11, '📁 Panel DAES'!$N$3:$N$135,"<>") -> 8 | E65: =+AVERAGEIF('📁 Panel DAES'!$D$3:$D$135,C65,'📁 Panel DAES'!$N$3:$N$135) -> 3462.7364 | F65: {=+MEDIAN(IF('📁 Panel DAES'!$D$3:$D$135=C65,'📁 Panel DAES'!$N$3:$N$135))} -> 1187.013 | G65: {=+_xlfn.STDEV.S(IF('📁 Panel DAES'!$D$3:$D$135='Estadística Descriptiva'!C65,'📁 Panel DAES'!$N$3:$N$135))} -> 3633.7737 | H65: {=+MIN(IF('📁 Panel DAES'!$D$3:$D$135='Estadística Descriptiva'!C65,'📁 Panel DAES'!$N$3:$N$135))} -> 0 | I65: {=+MAX(IF('📁 Panel DAES'!$D$3:$D$135='Estadística Descriptiva'!C65,'📁 Panel DAES'!$N$3:$N$135))} -> 12188.388
A66: DAES | B66: F4 | C66: 2022 | D66: =COUNTIFS('📁 Panel DAES'!$D$3:$D$135,'Cobertura de Datos'!A12, '📁 Panel DAES'!$N$3:$N$135,"<>") -> 16 | E66: =+AVERAGEIF('📁 Panel DAES'!$D$3:$D$135,C66,'📁 Panel DAES'!$N$3:$N$135) -> 3535.2037 | F66: {=+MEDIAN(IF('📁 Panel DAES'!$D$3:$D$135=C66,'📁 Panel DAES'!$N$3:$N$135))} -> 1889.1407 | G66: {=+_xlfn.STDEV.S(IF('📁 Panel DAES'!$D$3:$D$135='Estadística Descriptiva'!C66,'📁 Panel DAES'!$N$3:$N$135))} -> 3549.3161 | H66: {=+MIN(IF('📁 Panel DAES'!$D$3:$D$135='Estadística Descriptiva'!C66,'📁 Panel DAES'!$N$3:$N$135))} -> 0 | I66: {=+MAX(IF('📁 Panel DAES'!$D$3:$D$135='Estadística Descriptiva'!C66,'📁 Panel DAES'!$N$3:$N$135))} -> 12052.562
A67: DAES | B67: F4 | C67: 2023 | D67: =COUNTIFS('📁 Panel DAES'!$D$3:$D$135,'Cobertura de Datos'!A13, '📁 Panel DAES'!$N$3:$N$135,"<>") -> 20 | E67: =+AVERAGEIF('📁 Panel DAES'!$D$3:$D$135,C67,'📁 Panel DAES'!$N$3:$N$135) -> 5740.4138 | F67: {=+MEDIAN(IF('📁 Panel DAES'!$D$3:$D$135=C67,'📁 Panel DAES'!$N$3:$N$135))} -> 1822.0604 | G67: {=+_xlfn.STDEV.S(IF('📁 Panel DAES'!$D$3:$D$135='Estadística Descriptiva'!C67,'📁 Panel DAES'!$N$3:$N$135))} -> 8125.3873 | H67: {=+MIN(IF('📁 Panel DAES'!$D$3:$D$135='Estadística Descriptiva'!C67,'📁 Panel DAES'!$N$3:$N$135))} -> 0 | I67: {=+MAX(IF('📁 Panel DAES'!$D$3:$D$135='Estadística Descriptiva'!C67,'📁 Panel DAES'!$N$3:$N$135))} -> 36951.95
A68: DAES | B68: F4 | C68: 2024 | D68: =COUNTIFS('📁 Panel DAES'!$D$3:$D$135,'Cobertura de Datos'!A14, '📁 Panel DAES'!$N$3:$N$135,"<>") -> 12 | E68: =+AVERAGEIF('📁 Panel DAES'!$D$3:$D$135,C68,'📁 Panel DAES'!$N$3:$N$135) -> 6775.419 | F68: {=+MEDIAN(IF('📁 Panel DAES'!$D$3:$D$135=C68,'📁 Panel DAES'!$N$3:$N$135))} -> 3033.157 | G68: {=+_xlfn.STDEV.S(IF('📁 Panel DAES'!$D$3:$D$135='Estadística Descriptiva'!C68,'📁 Panel DAES'!$N$3:$N$135))} -> 10356.306 | H68: {=+MIN(IF('📁 Panel DAES'!$D$3:$D$135='Estadística Descriptiva'!C68,'📁 Panel DAES'!$N$3:$N$135))} -> 32.154974 | I68: {=+MAX(IF('📁 Panel DAES'!$D$3:$D$135='Estadística Descriptiva'!C68,'📁 Panel DAES'!$N$3:$N$135))} -> 37253.149
A69: CMF | B69: P1 | C69: 2013 | D69: =COUNTIFS('📁 Panel CMF'!$D$3:$D$93,'Cobertura de Datos'!A19,'📁 Panel CMF'!$E$3:$E$93,"<>") -> 7 | E69: =+AVERAGEIF('📁 Panel CMF'!$D$3:$D$93,'Estadística Descriptiva'!C69,'📁 Panel CMF'!$E$3:$E$93) -> 37210.714 | F69: {=+MEDIAN(IF('📁 Panel CMF'!$D$3:$D$93=C69,'📁 Panel CMF'!$E$3:$E$93))} -> 6948.1 | G69: {=+_xlfn.STDEV.S(IF('📁 Panel CMF'!$D$3:$D$93='Estadística Descriptiva'!C69,'📁 Panel CMF'!$E$3:$E$93))} -> 73679.362 | H69: {=+MIN(IF('📁 Panel CMF'!$D$3:$D$93='Estadística Descriptiva'!C69,'📁 Panel CMF'!$E$3:$E$93))} -> 3166.3 | I69: {=+MAX(IF('📁 Panel CMF'!$D$3:$D$93='Estadística Descriptiva'!C69,'📁 Panel CMF'!$E$3:$E$93))} -> 203410.1
A70: CMF | B70: P1 | C70: 2014 | D70: =COUNTIFS('📁 Panel CMF'!$D$3:$D$93,'Cobertura de Datos'!A20,'📁 Panel CMF'!$E$3:$E$93,"<>") -> 7 | E70: =+AVERAGEIF('📁 Panel CMF'!$D$3:$D$93,'Estadística Descriptiva'!C70,'📁 Panel CMF'!$E$3:$E$93) -> 35486.443 | F70: {=+MEDIAN(IF('📁 Panel CMF'!$D$3:$D$93=C70,'📁 Panel CMF'!$E$3:$E$93))} -> 5701.9 | G70: {=+_xlfn.STDEV.S(IF('📁 Panel CMF'!$D$3:$D$93='Estadística Descriptiva'!C70,'📁 Panel CMF'!$E$3:$E$93))} -> 72615.74 | H70: {=+MIN(IF('📁 Panel CMF'!$D$3:$D$93='Estadística Descriptiva'!C70,'📁 Panel CMF'!$E$3:$E$93))} -> 3119.1 | I70: {=+MAX(IF('📁 Panel CMF'!$D$3:$D$93='Estadística Descriptiva'!C70,'📁 Panel CMF'!$E$3:$E$93))} -> 199513.2
A71: CMF | B71: P1 | C71: 2015 | D71: =COUNTIFS('📁 Panel CMF'!$D$3:$D$93,'Cobertura de Datos'!A21,'📁 Panel CMF'!$E$3:$E$93,"<>") -> 7 | E71: =+AVERAGEIF('📁 Panel CMF'!$D$3:$D$93,'Estadística Descriptiva'!C71,'📁 Panel CMF'!$E$3:$E$93) -> 36260.286 | F71: {=+MEDIAN(IF('📁 Panel CMF'!$D$3:$D$93=C71,'📁 Panel CMF'!$E$3:$E$93))} -> 5838.4 | G71: {=+_xlfn.STDEV.S(IF('📁 Panel CMF'!$D$3:$D$93='Estadística Descriptiva'!C71,'📁 Panel CMF'!$E$3:$E$93))} -> 75078.982 | H71: {=+MIN(IF('📁 Panel CMF'!$D$3:$D$93='Estadística Descriptiva'!C71,'📁 Panel CMF'!$E$3:$E$93))} -> 3273.9 | I71: {=+MAX(IF('📁 Panel CMF'!$D$3:$D$93='Estadística Descriptiva'!C71,'📁 Panel CMF'!$E$3:$E$93))} -> 205966.5
A72: CMF | B72: P1 | C72: 2016 | D72: =COUNTIFS('📁 Panel CMF'!$D$3:$D$93,'Cobertura de Datos'!A22,'📁 Panel CMF'!$E$3:$E$93,"<>") -> 7 | E72: =+AVERAGEIF('📁 Panel CMF'!$D$3:$D$93,'Estadística Descriptiva'!C72,'📁 Panel CMF'!$E$3:$E$93) -> 38318.7 | F72: {=+MEDIAN(IF('📁 Panel CMF'!$D$3:$D$93=C72,'📁 Panel CMF'!$E$3:$E$93))} -> 7215 | G72: {=+_xlfn.STDEV.S(IF('📁 Panel CMF'!$D$3:$D$93='Estadística Descriptiva'!C72,'📁 Panel CMF'!$E$3:$E$93))} -> 78491.819 | H72: {=+MIN(IF('📁 Panel CMF'!$D$3:$D$93='Estadística Descriptiva'!C72,'📁 Panel CMF'!$E$3:$E$93))} -> 3389.2 | I72: {=+MAX(IF('📁 Panel CMF'!$D$3:$D$93='Estadística Descriptiva'!C72,'📁 Panel CMF'!$E$3:$E$93))} -> 215779.1
A73: CMF | B73: P1 | C73: 2017 | D73: =COUNTIFS('📁 Panel CMF'!$D$3:$D$93,'Cobertura de Datos'!A23,'📁 Panel CMF'!$E$3:$E$93,"<>") -> 7 | E73: =+AVERAGEIF('📁 Panel CMF'!$D$3:$D$93,'Estadística Descriptiva'!C73,'📁 Panel CMF'!$E$3:$E$93) -> 34682.714 | F73: {=+MEDIAN(IF('📁 Panel CMF'!$D$3:$D$93=C73,'📁 Panel CMF'!$E$3:$E$93))} -> 5915 | G73: {=+_xlfn.STDEV.S(IF('📁 Panel CMF'!$D$3:$D$93='Estadística Descriptiva'!C73,'📁 Panel CMF'!$E$3:$E$93))} -> 71317.13 | H73: {=+MIN(IF('📁 Panel CMF'!$D$3:$D$93='Estadística Descriptiva'!C73,'📁 Panel CMF'!$E$3:$E$93))} -> 3458 | I73: {=+MAX(IF('📁 Panel CMF'!$D$3:$D$93='Estadística Descriptiva'!C73,'📁 Panel CMF'!$E$3:$E$93))} -> 195996
A74: CMF | B74: P1 | C74: 2018 | D74: =COUNTIFS('📁 Panel CMF'!$D$3:$D$93,'Cobertura de Datos'!A24,'📁 Panel CMF'!$E$3:$E$93,"<>") -> 7 | E74: =+AVERAGEIF('📁 Panel CMF'!$D$3:$D$93,'Estadística Descriptiva'!C74,'📁 Panel CMF'!$E$3:$E$93) -> 36811.143 | F74: {=+MEDIAN(IF('📁 Panel CMF'!$D$3:$D$93=C74,'📁 Panel CMF'!$E$3:$E$93))} -> 7611 | G74: {=+_xlfn.STDEV.S(IF('📁 Panel CMF'!$D$3:$D$93='Estadística Descriptiva'!C74,'📁 Panel CMF'!$E$3:$E$93))} -> 75436.337 | H74: {=+MIN(IF('📁 Panel CMF'!$D$3:$D$93='Estadística Descriptiva'!C74,'📁 Panel CMF'!$E$3:$E$93))} -> 3218 | I74: {=+MAX(IF('📁 Panel CMF'!$D$3:$D$93='Estadística Descriptiva'!C74,'📁 Panel CMF'!$E$3:$E$93))} -> 207410
A75: CMF | B75: P1 | C75: 2019 | D75: =COUNTIFS('📁 Panel CMF'!$D$3:$D$93,'Cobertura de Datos'!A25,'📁 Panel CMF'!$E$3:$E$93,"<>") -> 7 | E75: =+AVERAGEIF('📁 Panel CMF'!$D$3:$D$93,'Estadística Descriptiva'!C75,'📁 Panel CMF'!$E$3:$E$93) -> 39674 | F75: {=+MEDIAN(IF('📁 Panel CMF'!$D$3:$D$93=C75,'📁 Panel CMF'!$E$3:$E$93))} -> 8768 | G75: {=+_xlfn.STDEV.S(IF('📁 Panel CMF'!$D$3:$D$93='Estadística Descriptiva'!C75,'📁 Panel CMF'!$E$3:$E$93))} -> 80082.779 | H75: {=+MIN(IF('📁 Panel CMF'!$D$3:$D$93='Estadística Descriptiva'!C75,'📁 Panel CMF'!$E$3:$E$93))} -> 2805 | I75: {=+MAX(IF('📁 Panel CMF'!$D$3:$D$93='Estadística Descriptiva'!C75,'📁 Panel CMF'!$E$3:$E$93))} -> 220878
A76: CMF | B76: P1 | C76: 2020 | D76: =COUNTIFS('📁 Panel CMF'!$D$3:$D$93,'Cobertura de Datos'!A26,'📁 Panel CMF'!$E$3:$E$93,"<>") -> 7 | E76: =+AVERAGEIF('📁 Panel CMF'!$D$3:$D$93,'Estadística Descriptiva'!C76,'📁 Panel CMF'!$E$3:$E$93) -> 38555.143 | F76: {=+MEDIAN(IF('📁 Panel CMF'!$D$3:$D$93=C76,'📁 Panel CMF'!$E$3:$E$93))} -> 11592 | G76: {=+_xlfn.STDEV.S(IF('📁 Panel CMF'!$D$3:$D$93='Estadística Descriptiva'!C76,'📁 Panel CMF'!$E$3:$E$93))} -> 77887.213 | H76: {=+MIN(IF('📁 Panel CMF'!$D$3:$D$93='Estadística Descriptiva'!C76,'📁 Panel CMF'!$E$3:$E$93))} -> 1915 | I76: {=+MAX(IF('📁 Panel CMF'!$D$3:$D$93='Estadística Descriptiva'!C76,'📁 Panel CMF'!$E$3:$E$93))} -> 214852
A77: CMF | B77: P1 | C77: 2021 | D77: =COUNTIFS('📁 Panel CMF'!$D$3:$D$93,'Cobertura de Datos'!A27,'📁 Panel CMF'!$E$3:$E$93,"<>") -> 7 | E77: =+AVERAGEIF('📁 Panel CMF'!$D$3:$D$93,'Estadística Descriptiva'!C77,'📁 Panel CMF'!$E$3:$E$93) -> 39373.143 | F77: {=+MEDIAN(IF('📁 Panel CMF'!$D$3:$D$93=C77,'📁 Panel CMF'!$E$3:$E$93))} -> 9254 | G77: {=+_xlfn.STDEV.S(IF('📁 Panel CMF'!$D$3:$D$93='Estadística Descriptiva'!C77,'📁 Panel CMF'!$E$3:$E$93))} -> 83205.472 | H77: {=+MIN(IF('📁 Panel CMF'!$D$3:$D$93='Estadística Descriptiva'!C77,'📁 Panel CMF'!$E$3:$E$93))} -> 2188 | I77: {=+MAX(IF('📁 Panel CMF'!$D$3:$D$93='Estadística Descriptiva'!C77,'📁 Panel CMF'!$E$3:$E$93))} -> 227719
A78: CMF | B78: P1 | C78: 2022 | D78: =COUNTIFS('📁 Panel CMF'!$D$3:$D$93,'Cobertura de Datos'!A28,'📁 Panel CMF'!$E$3:$E$93,"<>") -> 7 | E78: =+AVERAGEIF('📁 Panel CMF'!$D$3:$D$93,'Estadística Descriptiva'!C78,'📁 Panel CMF'!$E$3:$E$93) -> 48564 | F78: {=+MEDIAN(IF('📁 Panel CMF'!$D$3:$D$93=C78,'📁 Panel CMF'!$E$3:$E$93))} -> 11783 | G78: {=+_xlfn.STDEV.S(IF('📁 Panel CMF'!$D$3:$D$93='Estadística Descriptiva'!C78,'📁 Panel CMF'!$E$3:$E$93))} -> 104833.32 | H78: {=+MIN(IF('📁 Panel CMF'!$D$3:$D$93='Estadística Descriptiva'!C78,'📁 Panel CMF'!$E$3:$E$93))} -> 3323 | I78: {=+MAX(IF('📁 Panel CMF'!$D$3:$D$93='Estadística Descriptiva'!C78,'📁 Panel CMF'!$E$3:$E$93))} -> 286085
A79: CMF | B79: P1 | C79: 2023 | D79: =COUNTIFS('📁 Panel CMF'!$D$3:$D$93,'Cobertura de Datos'!A29,'📁 Panel CMF'!$E$3:$E$93,"<>") -> 7 | E79: =+AVERAGEIF('📁 Panel CMF'!$D$3:$D$93,'Estadística Descriptiva'!C79,'📁 Panel CMF'!$E$3:$E$93) -> 48230.571 | F79: {=+MEDIAN(IF('📁 Panel CMF'!$D$3:$D$93=C79,'📁 Panel CMF'!$E$3:$E$93))} -> 11267 | G79: {=+_xlfn.STDEV.S(IF('📁 Panel CMF'!$D$3:$D$93='Estadística Descriptiva'!C79,'📁 Panel CMF'!$E$3:$E$93))} -> 100365.07 | H79: {=+MIN(IF('📁 Panel CMF'!$D$3:$D$93='Estadística Descriptiva'!C79,'📁 Panel CMF'!$E$3:$E$93))} -> 2591 | I79: {=+MAX(IF('📁 Panel CMF'!$D$3:$D$93='Estadística Descriptiva'!C79,'📁 Panel CMF'!$E$3:$E$93))} -> 275445
A80: CMF | B80: P1 | C80: 2024 | D80: =COUNTIFS('📁 Panel CMF'!$D$3:$D$93,'Cobertura de Datos'!A30,'📁 Panel CMF'!$E$3:$E$93,"<>") -> 7 | E80: =+AVERAGEIF('📁 Panel CMF'!$D$3:$D$93,'Estadística Descriptiva'!C80,'📁 Panel CMF'!$E$3:$E$93) -> 57819.714 | F80: {=+MEDIAN(IF('📁 Panel CMF'!$D$3:$D$93=C80,'📁 Panel CMF'!$E$3:$E$93))} -> 13928 | G80: {=+_xlfn.STDEV.S(IF('📁 Panel CMF'!$D$3:$D$93='Estadística Descriptiva'!C80,'📁 Panel CMF'!$E$3:$E$93))} -> 119776.34 | H80: {=+MIN(IF('📁 Panel CMF'!$D$3:$D$93='Estadística Descriptiva'!C80,'📁 Panel CMF'!$E$3:$E$93))} -> 2322 | I80: {=+MAX(IF('📁 Panel CMF'!$D$3:$D$93='Estadística Descriptiva'!C80,'📁 Panel CMF'!$E$3:$E$93))} -> 328952
A81: CMF | B81: P1 | C81: 2025 | D81: =COUNTIFS('📁 Panel CMF'!$D$3:$D$93,'Cobertura de Datos'!A31,'📁 Panel CMF'!$E$3:$E$93,"<>") -> 7 | E81: =+AVERAGEIF('📁 Panel CMF'!$D$3:$D$93,'Estadística Descriptiva'!C81,'📁 Panel CMF'!$E$3:$E$93) -> 63697.857 | F81: {=+MEDIAN(IF('📁 Panel CMF'!$D$3:$D$93=C81,'📁 Panel CMF'!$E$3:$E$93))} -> 16292 | G81: {=+_xlfn.STDEV.S(IF('📁 Panel CMF'!$D$3:$D$93='Estadística Descriptiva'!C81,'📁 Panel CMF'!$E$3:$E$93))} -> 130675.14 | H81: {=+MIN(IF('📁 Panel CMF'!$D$3:$D$93='Estadística Descriptiva'!C81,'📁 Panel CMF'!$E$3:$E$93))} -> 2284 | I81: {=+MAX(IF('📁 Panel CMF'!$D$3:$D$93='Estadística Descriptiva'!C81,'📁 Panel CMF'!$E$3:$E$93))} -> 359492
A82: CMF | B82: D1 | C82: 2013 | D82: =COUNTIFS('📁 Panel CMF'!$D$3:$D$93,C82,'📁 Panel CMF'!$E$3:$E$93,"<>") -> 7 | E82: =+AVERAGEIF('📁 Panel CMF'!$D$3:$D$93,'Estadística Descriptiva'!C82,'📁 Panel CMF'!$H$3:$H$93) -> 8839.6143 | F82: {=+MEDIAN(IF('📁 Panel CMF'!$D$3:$D$93=C82,'📁 Panel CMF'!$H$3:$H$93))} -> 3146.5 | G82: {=+_xlfn.STDEV.S(IF('📁 Panel CMF'!$D$3:$D$93='Estadística Descriptiva'!C82,'📁 Panel CMF'!$H$3:$H$93))} -> 14835.766 | H82: {=+MIN(IF('📁 Panel CMF'!$D$3:$D$93='Estadística Descriptiva'!C82,'📁 Panel CMF'!$H$3:$H$93))} -> 685.6 | I82: {=+MAX(IF('📁 Panel CMF'!$D$3:$D$93='Estadística Descriptiva'!C82,'📁 Panel CMF'!$H$3:$H$93))} -> 42042.9
A83: CMF | B83: D1 | C83: 2014 | D83: =COUNTIFS('📁 Panel CMF'!$D$3:$D$93,C83,'📁 Panel CMF'!$E$3:$E$93,"<>") -> 7 | E83: =+AVERAGEIF('📁 Panel CMF'!$D$3:$D$93,'Estadística Descriptiva'!C83,'📁 Panel CMF'!$H$3:$H$93) -> 8363.5429 | F83: {=+MEDIAN(IF('📁 Panel CMF'!$D$3:$D$93=C83,'📁 Panel CMF'!$H$3:$H$93))} -> 2930.6 | G83: {=+_xlfn.STDEV.S(IF('📁 Panel CMF'!$D$3:$D$93='Estadística Descriptiva'!C83,'📁 Panel CMF'!$H$3:$H$93))} -> 14776.565 | H83: {=+MIN(IF('📁 Panel CMF'!$D$3:$D$93='Estadística Descriptiva'!C83,'📁 Panel CMF'!$H$3:$H$93))} -> 816.6 | I83: {=+MAX(IF('📁 Panel CMF'!$D$3:$D$93='Estadística Descriptiva'!C83,'📁 Panel CMF'!$H$3:$H$93))} -> 41701.1
A84: CMF | B84: D1 | C84: 2015 | D84: =COUNTIFS('📁 Panel CMF'!$D$3:$D$93,C84,'📁 Panel CMF'!$E$3:$E$93,"<>") -> 7 | E84: =+AVERAGEIF('📁 Panel CMF'!$D$3:$D$93,'Estadística Descriptiva'!C84,'📁 Panel CMF'!$H$3:$H$93) -> 9005.5857 | F84: {=+MEDIAN(IF('📁 Panel CMF'!$D$3:$D$93=C84,'📁 Panel CMF'!$H$3:$H$93))} -> 2625.4 | G84: {=+_xlfn.STDEV.S(IF('📁 Panel CMF'!$D$3:$D$93='Estadística Descriptiva'!C84,'📁 Panel CMF'!$H$3:$H$93))} -> 16531.068 | H84: {=+MIN(IF('📁 Panel CMF'!$D$3:$D$93='Estadística Descriptiva'!C84,'📁 Panel CMF'!$H$3:$H$93))} -> 956.6 | I84: {=+MAX(IF('📁 Panel CMF'!$D$3:$D$93='Estadística Descriptiva'!C84,'📁 Panel CMF'!$H$3:$H$93))} -> 46345.1
A85: CMF | B85: D1 | C85: 2016 | D85: =COUNTIFS('📁 Panel CMF'!$D$3:$D$93,C85,'📁 Panel CMF'!$E$3:$E$93,"<>") -> 7 | E85: =+AVERAGEIF('📁 Panel CMF'!$D$3:$D$93,'Estadística Descriptiva'!C85,'📁 Panel CMF'!$H$3:$H$93) -> 10018.243 | F85: {=+MEDIAN(IF('📁 Panel CMF'!$D$3:$D$93=C85,'📁 Panel CMF'!$H$3:$H$93))} -> 2822.3 | G85: {=+_xlfn.STDEV.S(IF('📁 Panel CMF'!$D$3:$D$93='Estadística Descriptiva'!C85,'📁 Panel CMF'!$H$3:$H$93))} -> 18727.726 | H85: {=+MIN(IF('📁 Panel CMF'!$D$3:$D$93='Estadística Descriptiva'!C85,'📁 Panel CMF'!$H$3:$H$93))} -> 1094.7 | I85: {=+MAX(IF('📁 Panel CMF'!$D$3:$D$93='Estadística Descriptiva'!C85,'📁 Panel CMF'!$H$3:$H$93))} -> 52321.1
A86: CMF | B86: D1 | C86: 2017 | D86: =COUNTIFS('📁 Panel CMF'!$D$3:$D$93,C86,'📁 Panel CMF'!$E$3:$E$93,"<>") -> 7 | E86: =+AVERAGEIF('📁 Panel CMF'!$D$3:$D$93,'Estadística Descriptiva'!C86,'📁 Panel CMF'!$H$3:$H$93) -> 10546.143 | F86: {=+MEDIAN(IF('📁 Panel CMF'!$D$3:$D$93=C86,'📁 Panel CMF'!$H$3:$H$93))} -> 2687 | G86: {=+_xlfn.STDEV.S(IF('📁 Panel CMF'!$D$3:$D$93='Estadística Descriptiva'!C86,'📁 Panel CMF'!$H$3:$H$93))} -> 19767.979 | H86: {=+MIN(IF('📁 Panel CMF'!$D$3:$D$93='Estadística Descriptiva'!C86,'📁 Panel CMF'!$H$3:$H$93))} -> 1225 | I86: {=+MAX(IF('📁 Panel CMF'!$D$3:$D$93='Estadística Descriptiva'!C86,'📁 Panel CMF'!$H$3:$H$93))} -> 55197
A87: CMF | B87: D1 | C87: 2018 | D87: =COUNTIFS('📁 Panel CMF'!$D$3:$D$93,C87,'📁 Panel CMF'!$E$3:$E$93,"<>") -> 7 | E87: =+AVERAGEIF('📁 Panel CMF'!$D$3:$D$93,'Estadística Descriptiva'!C87,'📁 Panel CMF'!$H$3:$H$93) -> 11130.143 | F87: {=+MEDIAN(IF('📁 Panel CMF'!$D$3:$D$93=C87,'📁 Panel CMF'!$H$3:$H$93))} -> 3158 | G87: {=+_xlfn.STDEV.S(IF('📁 Panel CMF'!$D$3:$D$93='Estadística Descriptiva'!C87,'📁 Panel CMF'!$H$3:$H$93))} -> 20945.668 | H87: {=+MIN(IF('📁 Panel CMF'!$D$3:$D$93='Estadística Descriptiva'!C87,'📁 Panel CMF'!$H$3:$H$93))} -> 1281 | I87: {=+MAX(IF('📁 Panel CMF'!$D$3:$D$93='Estadística Descriptiva'!C87,'📁 Panel CMF'!$H$3:$H$93))} -> 58453
A88: CMF | B88: D1 | C88: 2019 | D88: =COUNTIFS('📁 Panel CMF'!$D$3:$D$93,C88,'📁 Panel CMF'!$E$3:$E$93,"<>") -> 7 | E88: =+AVERAGEIF('📁 Panel CMF'!$D$3:$D$93,'Estadística Descriptiva'!C88,'📁 Panel CMF'!$H$3:$H$93) -> 11879.571 | F88: {=+MEDIAN(IF('📁 Panel CMF'!$D$3:$D$93=C88,'📁 Panel CMF'!$H$3:$H$93))} -> 3350 | G88: {=+_xlfn.STDEV.S(IF('📁 Panel CMF'!$D$3:$D$93='Estadística Descriptiva'!C88,'📁 Panel CMF'!$H$3:$H$93))} -> 22235.234 | H88: {=+MIN(IF('📁 Panel CMF'!$D$3:$D$93='Estadística Descriptiva'!C88,'📁 Panel CMF'!$H$3:$H$93))} -> 1434 | I88: {=+MAX(IF('📁 Panel CMF'!$D$3:$D$93='Estadística Descriptiva'!C88,'📁 Panel CMF'!$H$3:$H$93))} -> 62118
A89: CMF | B89: D1 | C89: 2020 | D89: =COUNTIFS('📁 Panel CMF'!$D$3:$D$93,C89,'📁 Panel CMF'!$E$3:$E$93,"<>") -> 7 | E89: =+AVERAGEIF('📁 Panel CMF'!$D$3:$D$93,'Estadística Descriptiva'!C89,'📁 Panel CMF'!$H$3:$H$93) -> 12468.429 | F89: {=+MEDIAN(IF('📁 Panel CMF'!$D$3:$D$93=C89,'📁 Panel CMF'!$H$3:$H$93))} -> 4165 | G89: {=+_xlfn.STDEV.S(IF('📁 Panel CMF'!$D$3:$D$93='Estadística Descriptiva'!C89,'📁 Panel CMF'!$H$3:$H$93))} -> 22605.472 | H89: {=+MIN(IF('📁 Panel CMF'!$D$3:$D$93='Estadística Descriptiva'!C89,'📁 Panel CMF'!$H$3:$H$93))} -> 1831 | I89: {=+MAX(IF('📁 Panel CMF'!$D$3:$D$93='Estadística Descriptiva'!C89,'📁 Panel CMF'!$H$3:$H$93))} -> 63610
A90: CMF | B90: D1 | C90: 2021 | D90: =COUNTIFS('📁 Panel CMF'!$D$3:$D$93,C90,'📁 Panel CMF'!$E$3:$E$93,"<>") -> 7 | E90: =+AVERAGEIF('📁 Panel CMF'!$D$3:$D$93,'Estadística Descriptiva'!C90,'📁 Panel CMF'!$H$3:$H$93) -> 12670.857 | F90: {=+MEDIAN(IF('📁 Panel CMF'!$D$3:$D$93=C90,'📁 Panel CMF'!$H$3:$H$93))} -> 3836 | G90: {=+_xlfn.STDEV.S(IF('📁 Panel CMF'!$D$3:$D$93='Estadística Descriptiva'!C90,'📁 Panel CMF'!$H$3:$H$93))} -> 24250.103 | H90: {=+MIN(IF('📁 Panel CMF'!$D$3:$D$93='Estadística Descriptiva'!C90,'📁 Panel CMF'!$H$3:$H$93))} -> 1269 | I90: {=+MAX(IF('📁 Panel CMF'!$D$3:$D$93='Estadística Descriptiva'!C90,'📁 Panel CMF'!$H$3:$H$93))} -> 67461
A91: CMF | B91: D1 | C91: 2022 | D91: =COUNTIFS('📁 Panel CMF'!$D$3:$D$93,C91,'📁 Panel CMF'!$E$3:$E$93,"<>") -> 7 | E91: =+AVERAGEIF('📁 Panel CMF'!$D$3:$D$93,'Estadística Descriptiva'!C91,'📁 Panel CMF'!$H$3:$H$93) -> 13111.4 | F91: {=+MEDIAN(IF('📁 Panel CMF'!$D$3:$D$93=C91,'📁 Panel CMF'!$H$3:$H$93))} -> 4485 | G91: {=+_xlfn.STDEV.S(IF('📁 Panel CMF'!$D$3:$D$93='Estadística Descriptiva'!C91,'📁 Panel CMF'!$H$3:$H$93))} -> 24975.373 | H91: {=+MIN(IF('📁 Panel CMF'!$D$3:$D$93='Estadística Descriptiva'!C91,'📁 Panel CMF'!$H$3:$H$93))} -> 1018 | I91: {=+MAX(IF('📁 Panel CMF'!$D$3:$D$93='Estadística Descriptiva'!C91,'📁 Panel CMF'!$H$3:$H$93))} -> 69565
A92: CMF | B92: D1 | C92: 2023 | D92: =COUNTIFS('📁 Panel CMF'!$D$3:$D$93,C92,'📁 Panel CMF'!$E$3:$E$93,"<>") -> 7 | E92: =+AVERAGEIF('📁 Panel CMF'!$D$3:$D$93,'Estadística Descriptiva'!C92,'📁 Panel CMF'!$H$3:$H$93) -> 13246.657 | F92: {=+MEDIAN(IF('📁 Panel CMF'!$D$3:$D$93=C92,'📁 Panel CMF'!$H$3:$H$93))} -> 4961 | G92: {=+_xlfn.STDEV.S(IF('📁 Panel CMF'!$D$3:$D$93='Estadística Descriptiva'!C92,'📁 Panel CMF'!$H$3:$H$93))} -> 23846.331 | H92: {=+MIN(IF('📁 Panel CMF'!$D$3:$D$93='Estadística Descriptiva'!C92,'📁 Panel CMF'!$H$3:$H$93))} -> 1432 | I92: {=+MAX(IF('📁 Panel CMF'!$D$3:$D$93='Estadística Descriptiva'!C92,'📁 Panel CMF'!$H$3:$H$93))} -> 67113
A93: CMF | B93: D1 | C93: 2024 | D93: =COUNTIFS('📁 Panel CMF'!$D$3:$D$93,C93,'📁 Panel CMF'!$E$3:$E$93,"<>") -> 7 | E93: =+AVERAGEIF('📁 Panel CMF'!$D$3:$D$93,'Estadística Descriptiva'!C93,'📁 Panel CMF'!$H$3:$H$93) -> 15615.714 | F93: {=+MEDIAN(IF('📁 Panel CMF'!$D$3:$D$93=C93,'📁 Panel CMF'!$H$3:$H$93))} -> 6044 | G93: {=+_xlfn.STDEV.S(IF('📁 Panel CMF'!$D$3:$D$93='Estadística Descriptiva'!C93,'📁 Panel CMF'!$H$3:$H$93))} -> 28056.017 | H93: {=+MIN(IF('📁 Panel CMF'!$D$3:$D$93='Estadística Descriptiva'!C93,'📁 Panel CMF'!$H$3:$H$93))} -> 1554 | I93: {=+MAX(IF('📁 Panel CMF'!$D$3:$D$93='Estadística Descriptiva'!C93,'📁 Panel CMF'!$H$3:$H$93))} -> 79042
A94: CMF | B94: D1 | C94: 2025 | D94: =COUNTIFS('📁 Panel CMF'!$D$3:$D$93,C94,'📁 Panel CMF'!$E$3:$E$93,"<>") -> 7 | E94: =+AVERAGEIF('📁 Panel CMF'!$D$3:$D$93,'Estadística Descriptiva'!C94,'📁 Panel CMF'!$H$3:$H$93) -> 17537.6 | F94: {=+MEDIAN(IF('📁 Panel CMF'!$D$3:$D$93=C94,'📁 Panel CMF'!$H$3:$H$93))} -> 6952 | G94: {=+_xlfn.STDEV.S(IF('📁 Panel CMF'!$D$3:$D$93='Estadística Descriptiva'!C94,'📁 Panel CMF'!$H$3:$H$93))} -> 31769.791 | H94: {=+MIN(IF('📁 Panel CMF'!$D$3:$D$93='Estadística Descriptiva'!C94,'📁 Panel CMF'!$H$3:$H$93))} -> 1205 | I94: {=+MAX(IF('📁 Panel CMF'!$D$3:$D$93='Estadística Descriptiva'!C94,'📁 Panel CMF'!$H$3:$H$93))} -> 89298
A95: CMF | B95: Activos | C95: 2013 | D95: =COUNTIFS('📁 Panel CMF'!$D$3:$D$93,C95,'📁 Panel CMF'!$E$3:$E$93,"<>") -> 7 | E95: =+AVERAGEIF('📁 Panel CMF'!$D$3:$D$93,'Estadística Descriptiva'!C95,'📁 Panel CMF'!$M$3:$M$93) -> 204870.49 | F95: {=+MEDIAN(IF('📁 Panel CMF'!$D$3:$D$93=C95,'📁 Panel CMF'!$M$3:$M$93))} -> 32276.2 | G95: {=+_xlfn.STDEV.S(IF('📁 Panel CMF'!$D$3:$D$93='Estadística Descriptiva'!C95,'📁 Panel CMF'!$M$3:$M$93))} -> 412940.1 | H95: {=+MIN(IF('📁 Panel CMF'!$D$3:$D$93='Estadística Descriptiva'!C95,'📁 Panel CMF'!$M$3:$M$93))} -> 16980.1 | I95: {=+MAX(IF('📁 Panel CMF'!$D$3:$D$93='Estadística Descriptiva'!C95,'📁 Panel CMF'!$M$3:$M$93))} -> 1137043.2
A96: CMF | B96: Activos | C96: 2014 | D96: =COUNTIFS('📁 Panel CMF'!$D$3:$D$93,C96,'📁 Panel CMF'!$E$3:$E$93,"<>") -> 7 | E96: =+AVERAGEIF('📁 Panel CMF'!$D$3:$D$93,'Estadística Descriptiva'!C96,'📁 Panel CMF'!$M$3:$M$93) -> 204578.29 | F96: {=+MEDIAN(IF('📁 Panel CMF'!$D$3:$D$93=C96,'📁 Panel CMF'!$M$3:$M$93))} -> 27036.7 | G96: {=+_xlfn.STDEV.S(IF('📁 Panel CMF'!$D$3:$D$93='Estadística Descriptiva'!C96,'📁 Panel CMF'!$M$3:$M$93))} -> 415784.02 | H96: {=+MIN(IF('📁 Panel CMF'!$D$3:$D$93='Estadística Descriptiva'!C96,'📁 Panel CMF'!$M$3:$M$93))} -> 15653.3 | I96: {=+MAX(IF('📁 Panel CMF'!$D$3:$D$93='Estadística Descriptiva'!C96,'📁 Panel CMF'!$M$3:$M$93))} -> 1143544.2
A97: CMF | B97: Activos | C97: 2015 | D97: =COUNTIFS('📁 Panel CMF'!$D$3:$D$93,C97,'📁 Panel CMF'!$E$3:$E$93,"<>") -> 7 | E97: =+AVERAGEIF('📁 Panel CMF'!$D$3:$D$93,'Estadística Descriptiva'!C97,'📁 Panel CMF'!$M$3:$M$93) -> 218489.21 | F97: {=+MEDIAN(IF('📁 Panel CMF'!$D$3:$D$93=C97,'📁 Panel CMF'!$M$3:$M$93))} -> 28433 | G97: {=+_xlfn.STDEV.S(IF('📁 Panel CMF'!$D$3:$D$93='Estadística Descriptiva'!C97,'📁 Panel CMF'!$M$3:$M$93))} -> 452521.3 | H97: {=+MIN(IF('📁 Panel CMF'!$D$3:$D$93='Estadística Descriptiva'!C97,'📁 Panel CMF'!$M$3:$M$93))} -> 14763.8 | I97: {=+MAX(IF('📁 Panel CMF'!$D$3:$D$93='Estadística Descriptiva'!C97,'📁 Panel CMF'!$M$3:$M$93))} -> 1241436.8
A98: CMF | B98: Activos | C98: 2016 | D98: =COUNTIFS('📁 Panel CMF'!$D$3:$D$93,C98,'📁 Panel CMF'!$E$3:$E$93,"<>") -> 7 | E98: =+AVERAGEIF('📁 Panel CMF'!$D$3:$D$93,'Estadística Descriptiva'!C98,'📁 Panel CMF'!$M$3:$M$93) -> 238066.81 | F98: {=+MEDIAN(IF('📁 Panel CMF'!$D$3:$D$93=C98,'📁 Panel CMF'!$M$3:$M$93))} -> 33393.5 | G98: {=+_xlfn.STDEV.S(IF('📁 Panel CMF'!$D$3:$D$93='Estadística Descriptiva'!C98,'📁 Panel CMF'!$M$3:$M$93))} -> 500901.08 | H98: {=+MIN(IF('📁 Panel CMF'!$D$3:$D$93='Estadística Descriptiva'!C98,'📁 Panel CMF'!$M$3:$M$93))} -> 15715.4 | I98: {=+MAX(IF('📁 Panel CMF'!$D$3:$D$93='Estadística Descriptiva'!C98,'📁 Panel CMF'!$M$3:$M$93))} -> 1371455.7
A99: CMF | B99: Activos | C99: 2017 | D99: =COUNTIFS('📁 Panel CMF'!$D$3:$D$93,C99,'📁 Panel CMF'!$E$3:$E$93,"<>") -> 7 | E99: =+AVERAGEIF('📁 Panel CMF'!$D$3:$D$93,'Estadística Descriptiva'!C99,'📁 Panel CMF'!$M$3:$M$93) -> 258711.14 | F99: {=+MEDIAN(IF('📁 Panel CMF'!$D$3:$D$93=C99,'📁 Panel CMF'!$M$3:$M$93))} -> 37342 | G99: {=+_xlfn.STDEV.S(IF('📁 Panel CMF'!$D$3:$D$93='Estadística Descriptiva'!C99,'📁 Panel CMF'!$M$3:$M$93))} -> 544734.21 | H99: {=+MIN(IF('📁 Panel CMF'!$D$3:$D$93='Estadística Descriptiva'!C99,'📁 Panel CMF'!$M$3:$M$93))} -> 17021 | I99: {=+MAX(IF('📁 Panel CMF'!$D$3:$D$93='Estadística Descriptiva'!C99,'📁 Panel CMF'!$M$3:$M$93))} -> 1491468
A100: CMF | B100: Activos | C100: 2018 | D100: =COUNTIFS('📁 Panel CMF'!$D$3:$D$93,C100,'📁 Panel CMF'!$E$3:$E$93,"<>") -> 7 | E100: =+AVERAGEIF('📁 Panel CMF'!$D$3:$D$93,'Estadística Descriptiva'!C100,'📁 Panel CMF'!$M$3:$M$93) -> 283094.86 | F100: {=+MEDIAN(IF('📁 Panel CMF'!$D$3:$D$93=C100,'📁 Panel CMF'!$M$3:$M$93))} -> 42902 | G100: {=+_xlfn.STDEV.S(IF('📁 Panel CMF'!$D$3:$D$93='Estadística Descriptiva'!C100,'📁 Panel CMF'!$M$3:$M$93))} -> 600128.19 | H100: {=+MIN(IF('📁 Panel CMF'!$D$3:$D$93='Estadística Descriptiva'!C100,'📁 Panel CMF'!$M$3:$M$93))} -> 16872 | I100: {=+MAX(IF('📁 Panel CMF'!$D$3:$D$93='Estadística Descriptiva'!C100,'📁 Panel CMF'!$M$3:$M$93))} -> 1641723
...
